Workbook

Sheet Python vs Excel
A1: Matching outputs: Python (statsmodels) vs Excel (formulas in this workbook)
A2: Python values are pasted from results.json. Excel values are live formulas. Difference should be ~0.
A4: Statistic | B4: Python | C4: Excel | D4: Difference | E4: Match | F4: Excel location
A5: ADF, ln F level | B5: -2.309 | C5: ='1 ADF'!B16 -> -2.309109 | D5: =C5-B5 -> -0.00010902925 | E5: =IF(ABS(D5)<=0.0015,"Yes","No") -> Yes | F5: 1 ADF!B16
A6: ADF, ln B level | B6: -2.367 | C6: ='1 ADF'!B26 -> -2.3671437 | D6: =C6-B6 -> -0.00014366899 | E6: =IF(ABS(D6)<=0.0015,"Yes","No") -> Yes | F6: 1 ADF!B26
A7: Hedge ratio β | B7: 0.91613 | C7: ='2 Hedge ratio'!B5 -> 0.91612676 | D7: =C7-B7 -> -3.2407533e-06 | E7: =IF(ABS(D7)<=0.0015,"Yes","No") -> Yes | F7: 2 Hedge ratio!B5
A8: R² (Step 2) | B8: 0.99564 | C8: ='2 Hedge ratio'!B8 -> 0.99563563 | D8: =C8-B8 -> -4.3730976e-06 | E8: =IF(ABS(D8)<=0.0015,"Yes","No") -> Yes | F8: 2 Hedge ratio!B8
A9: Mean ratio F/B | B9: 89.6795 | C9: ='2 Hedge ratio'!B9 -> 89.679532 | D9: =C9-B9 -> 3.2223533e-05 | E9: =IF(ABS(D9)<=0.0015,"Yes","No") -> Yes | F9: 2 Hedge ratio!B9
A10: Engle–Granger, constant only | B10: -3.096 | C10: ='3 Cointegration'!B7 -> -3.096125 | D10: =C10-B10 -> -0.00012495995 | E10: =IF(ABS(D10)<=0.0015,"Yes","No") -> Yes | F10: 3 Cointegration!B7
A11: Trend in ln(F/B), % per year | B11: -0.01161 | C11: =Carry!B5 -> -0.011614056 | D11: =C11-B11 -> -4.0560557e-06 | E11: =IF(ABS(D11)<=0.00015,"Yes","No") -> Yes | F11: Carry!B5
A12: Implied financing rate r | B12: 0.0654 | C12: =Carry!B9 -> 0.065383462 | D12: =C12-B12 -> -1.6538206e-05 | E12: =IF(ABS(D12)<=0.00015,"Yes","No") -> Yes | F12: Carry!B9
A13: β with trend | B13: 0.99697 | C13: ='5 Re-specification'!B5 -> 0.9969695 | D13: =C13-B13 -> -5.0002121e-07 | E13: =IF(ABS(D13)<=0.0015,"Yes","No") -> Yes | F13: 5 Re-specification!B5
A14: δ, % per year | B14: -0.0113 | C14: ='5 Re-specification'!B8 -> -0.011322188 | D14: =C14-B14 -> -2.218816e-05 | E14: =IF(ABS(D14)<=0.00015,"Yes","No") -> Yes | F14: 5 Re-specification!B8
A15: Engle–Granger, constant + trend | B15: -8.06 | C15: ='5b EG with trend'!B7 -> -8.0604248 | D15: =C15-B15 -> -0.00042484857 | E15: =IF(ABS(D15)<=0.0015,"Yes","No") -> Yes | F15: 5b EG with trend!B7
A16: ECM γ | B16: -0.4832 | C16: ='6 ECM'!B5 -> -0.48320184 | D16: =C16-B16 -> -1.8390417e-06 | E16: =IF(ABS(D16)<=0.0015,"Yes","No") -> Yes | F16: 6 ECM!B5
A17: Half-life (sessions) | B17: 1.43 | C17: ='6 ECM'!B8 -> 1.4344879 | D17: =C17-B17 -> 0.0044878776 | E17: =IF(ABS(D17)<=0.01,"Yes","No") -> Yes | F17: 6 ECM!B8
A18: Signal: trades | B18: 29 | C18: ='7 Signal backtest'!B5 -> 29 | D18: =C18-B18 -> 0 | E18: =IF(ABS(D18)<=0.0015,"Yes","No") -> Yes | F18: 7 Signal backtest!B5
A19: Signal: annual excess return | B19: 0.00515 | C19: ='7 Signal backtest'!B6 -> 0.0051470199 | D19: =C19-B19 -> -2.9801451e-06 | E19: =IF(ABS(D19)<=0.00015,"Yes","No") -> Yes | F19: 7 Signal backtest!B6
A20: Signal: Sharpe ratio | B20: 0.39 | C20: ='7 Signal backtest'!B8 -> 0.3874636 | D20: =C20-B20 -> -0.002536399 | E20: =IF(ABS(D20)<=0.01,"Yes","No") -> Yes | F20: 7 Signal backtest!B8
A21: Aarav: return above risk-free | B21: 0.0019 | C21: ='8 Four people'!B11 -> 0.0018938314 | D21: =C21-B21 -> -6.1685821e-06 | E21: =IF(ABS(D21)<=0.00015,"Yes","No") -> Yes | F21: 8 Four people!B11
A22: Meera: return above risk-free | B22: -0.0165 | C22: ='8 Four people'!C11 -> -0.016478315 | D22: =C22-B22 -> 2.1684979e-05 | E22: =IF(ABS(D22)<=0.00015,"Yes","No") -> Yes | F22: 8 Four people!C11
A23: Rohan: return on incremental cash | B23: -0.4599 | C23: ='8 Four people'!D11 -> -0.45987695 | D23: =C23-B23 -> 2.3046087e-05 | E23: =IF(ABS(D23)<=0.00015,"Yes","No") -> Yes | F23: 8 Four people!D11
A24: Kavya: return on incremental capital | B24: 0.206 | C24: ='8 Four people'!E11 -> 0.20596351 | D24: =C24-B24 -> -3.6494166e-05 | E24: =IF(ABS(D24)<=0.00015,"Yes","No") -> Yes | F24: 8 Four people!E11
A25: 15-min signal: annual net, % of notional | B25: 0.0213 | C25: ='9 Trades 15-min'!F102 -> 0.021338868 | D25: =C25-B25 -> 3.8868323e-05 | E25: =IF(ABS(D25)<=0.00015,"Yes","No") -> Yes | F25: 9 Trades 15-min, summary
A26: 15-min Aarav: return above risk-free | B26: 0.0172 | C26: ='9 Trades 15-min'!F103 -> 0.017220043 | D26: =C26-B26 -> 2.0043189e-05 | E26: =IF(ABS(D26)<=0.00015,"Yes","No") -> Yes | F26: 9 Trades 15-min, summary
A27: 15-min Meera: return above risk-free | B27: -0.0096 | C27: ='9 Trades 15-min'!F104 -> -0.0095932673 | D27: =C27-B27 -> 6.7327487e-06 | E27: =IF(ABS(D27)<=0.00015,"Yes","No") -> Yes | F27: 9 Trades 15-min, summary
A28: 15-min Rohan: return on extra cash | B28: 0.5044 | C28: ='9 Trades 15-min'!F105 -> 0.50438368 | D28: =C28-B28 -> -1.6317226e-05 | E28: =IF(ABS(D28)<=0.00015,"Yes","No") -> Yes | F28: 9 Trades 15-min, summary
A29: 15-min Kavya: return on margin | B29: 0.4948 | C29: ='9 Trades 15-min'!F106 -> 0.49481747 | D29: =C29-B29 -> 1.7468838e-05 | E29: =IF(ABS(D29)<=0.00015,"Yes","No") -> Yes | F29: 9 Trades 15-min, summary
A30: Course test: one-sample t on trades | B30: 3.06 | C30: ='10 Course tests'!B7 -> 3.0579229 | D30: =C30-B30 -> -0.0020771309 | E30: =IF(ABS(D30)<=0.01,"Yes","No") -> Yes | F30: 10 Course tests!B7
A31: Course test: Welch p, two halves | B31: 0.663 | C31: ='10 Course tests'!B15 -> 0.66301579 | D31: =C31-B31 -> 1.5794897e-05 | E31: =IF(ABS(D31)<=0.01,"Yes","No") -> Yes | F31: 10 Course tests!B15
A32: Course test: chi-square p | B32: 0.1277 | C32: ='10 Course tests'!B24 -> 0.12767494 | D32: =C32-B32 -> -2.5062103e-05 | E32: =IF(ABS(D32)<=0.01,"Yes","No") -> Yes | F32: 10 Course tests!B24
A34: Tolerance reflects display rounding of the pasted Python values (3–5 decimals).

Sheet Inputs
A1: Inputs and assumptions
A2: Blue = input you may change. Every other sheet recalculates from these.
A4: Parameter | B4: Value | C4: Source / note
A5: Entry threshold |z| > | B5: 2 | C5: Rule, fixed before any results were seen
A6: Exit threshold |z| < | B6: 0.5
A7: Stop-loss |z| > | B7: 3.5
A8: Time stop (sessions) | B8: 10 | C8: ≈ 7 half-lives
A9: Rolling estimation window (sessions) | B9: 250 | C9: Walk-forward: only the previous 250 sessions are used
A10: Minimum observations before trading | B10: 60
A11: NIFTY lot size (units) | B11: 65 | C11: NSE circular FAOP70616: 75 → 65 from the January 2026 series
A12: Futures margin, % of notional | B12: 0.13 | C12: Assumption: SPAN + exposure margin
A13: Retail MTF interest rate | B13: 0.14 | C13: Assumption: within the 12–18% p.a. range charged by Indian brokers
A14: Institutional funding spread over repo | B14: 0.0075 | C14: Assumption
A15: Cross-margin relief (institution) | B15: 0.7 | C15: Assumption; NSE Clearing permits index futures vs ETF cross-margining
A16: Trading days per year | B16: 252 | C16: Annualisation convention
A17: Futures stamp duty (buy side) | B17: 2e-05 | C17: Indian Stamp Act: 0.002% on futures purchases
A18: Futures other charges per side — retail | B18: 3.5e-05 | C18: Exchange txn + SEBI fee + GST + brokerage (approx.)
A19: Futures slippage per side — retail | B19: 0.0001 | C19: Assumption: 1.0 bp
A20: ETF stamp duty (buy side) | B20: 0.00015 | C20: Indian Stamp Act: 0.015% on delivery purchases
A21: ETF STT (sell side) | B21: 1e-05 | C21: 0.001% on sale of equity-oriented fund units
A22: ETF other charges per side — retail | B22: 5e-05 | C22: Exchange txn + SEBI fee + GST + DP (approx.)
... A30: Brokerage per option order — institution | B30: 1e-06 | C30: Assumption
A32: Futures STT (sell side) is time-varying and sits in Panel column O: 0.0125% to 30-Sep-2024, 0.02% to 31-Mar-2026, 0.05% from 1-Apr-2026 (Union Budgets 2024 and 2026).
A33: Risk-free rate = RBI policy repo path (Panel column N): 6.50% → 6.25% (7-Feb-25) → 6.00% (9-Apr-25) → 5.50% (6-Jun-25) → 5.25% (5-Dec-25).

Sheet Panel
A1: Daily panel and walk-forward backtest (811 sessions)
A2: Columns B, C, G, K, L, N, O are data. Everything else is a formula. Row 5 is the first session.
A4: Date | B4: FUT close | C4: BEES close | D4: ln F | E4: ln B | F4: t | G4: DTE | H4: ln(F/B) | I4: Δ ln F | J4: Δ ln B | K4: Expiry | L4: Splice | M4: Δ ln F adj | N4: Repo | O4: STT fut | P4: Resid naive | Q4: Resid trend | R4: Window | S4: δ roll | T4: β roll | U4: α roll | V4: σ roll | W4: z | X4: held pre | Y4: exit | Z4: cur after | AA4: entry | AB4: POS | AC4: held | AD4: β hold | AE4: ΔqF | AF4: qB | AG4: ΔqB | AH4: Cost retail | AI4: x SIGNAL | AJ4: Cost inst | AK4: x KAVYA | AL4: held pre S | AM4: exit S | AN4: cur after S | AO4: entry S | AP4: POS S | AQ4: held S | AR4: β hold S | AS4: ΔqF S | AT4: qB S | AU4: ΔqB S | AV4: Cost S | AW4: x AARAV | AX4: x MEERA | AY4: Cost fut S | AZ4: x ROHAN | BA4: Cum signal | BB4: Run max | BC4: Drawdown | BD4: Cal days
A5: 45048 | B5: 18202 | C5: 198.2 | D5: =LN(B5) -> 9.8092868 | E5: =LN(C5) -> 5.2892766 | F5: 0 | G5: 23 | H5: =D5-E5 -> 4.5200101 | I5: 0 | J5: 0 | K5: 0 | L5: 0 | M5: 0 | N5: 0.065 | O5: 0.000125 | P5: =D5-('2 Hedge ratio'!$B$6+'2 Hedge ratio'!$B$5*E5) -> 0.0018188254 | Q5: =D5-('5 Re-specification'!$B$7+'5 Re-specification'!$B$5*E5+'5 Re-specification'!$B$6*F5) -> 0.0048382672 | R5: =MIN(F5,Inputs!$B$9) -> 0 | S5: =IF(AND(F5>=1,R5>=Inputs!$B$10),INDEX(LINEST(OFFSET(D5,-R5,0,R5,1),OFFSET(E5,-R5,0,R5,2)),1,1),"") | T5: =IF(AND(F5>=1,R5>=Inputs!$B$10),INDEX(LINEST(OFFSET(D5,-R5,0,R5,1),OFFSET(E5,-R5,0,R5,2)),1,2),"") | U5: =IF(AND(F5>=1,R5>=Inputs!$B$10),INDEX(LINEST(OFFSET(D5,-R5,0,R5,1),OFFSET(E5,-R5,0,R5,2)),1,3),"") | V5: =IF(AND(F5>=1,R5>=Inputs!$B$10),SQRT(SUMPRODUCT((OFFSET(D5,-R5,0,R5,1)-U5-T5*OFFSET(E5,-R5,0,R5,1)-S5*OFFSET(F5,-R5,0,R5,1))^2)/(R5-3)),"") | W5: =IF(AND(F5>=1,R5>=Inputs!$B$10),(D5-U5-T5*E5-S5*F5)/V5,"") | X5: 0 | Y5: 0 | Z5: 0 | AA5: 0 | AB5: 0 | AC5: 0 | AD5: 0 | AE5: 0 | AF5: 0 | AG5: 0 | AH5: 0 | AI5: 0 | AJ5: 0 | AK5: 0 | AL5: 0 | AM5: 0 | AN5: 0 | AO5: 0 | AP5: 0 | AQ5: 0 | AR5: 0 | AS5: 0 | AT5: 0 | AU5: 0 | AV5: 0 | AW5: 0 | AX5: 0 | AY5: 0 | AZ5: 0 | BA5: =AI5 -> 0 | BB5: =MAX(0,BA5) -> 0 | BC5: =BA5-BB5 -> 0 | BD5: =A6-A5 -> 1
A6: 45049 | B6: 18147.3 | C6: 197.58 | D6: =LN(B6) -> 9.8062771 | E6: =LN(C6) -> 5.2861436 | F6: 1 | G6: 22 | H6: =D6-E6 -> 4.5201335 | I6: =D6-D5 -> -0.0030096888 | J6: =E6-E5 -> -0.0031330563 | K6: 0 | L6: 0 | M6: =IF(L6=1,J6-Carry!$B$9/Inputs!$B$16,I6) -> -0.0030096888 | N6: 0.065 | O6: 0.000125 | P6: =D6-('2 Hedge ratio'!$B$6+'2 Hedge ratio'!$B$5*E6) -> 0.0016794133 | Q6: =D6-('5 Re-specification'!$B$7+'5 Re-specification'!$B$5*E6+'5 Re-specification'!$B$6*F6) -> 0.0049970692 | R6: =MIN(F6,Inputs!$B$9) -> 1 | S6: =IF(AND(F6>=1,R6>=Inputs!$B$10),INDEX(LINEST(OFFSET(D6,-R6,0,R6,1),OFFSET(E6,-R6,0,R6,2)),1,1),"") | T6: =IF(AND(F6>=1,R6>=Inputs!$B$10),INDEX(LINEST(OFFSET(D6,-R6,0,R6,1),OFFSET(E6,-R6,0,R6,2)),1,2),"") | U6: =IF(AND(F6>=1,R6>=Inputs!$B$10),INDEX(LINEST(OFFSET(D6,-R6,0,R6,1),OFFSET(E6,-R6,0,R6,2)),1,3),"") | V6: =IF(AND(F6>=1,R6>=Inputs!$B$10),SQRT(SUMPRODUCT((OFFSET(D6,-R6,0,R6,1)-U6-T6*OFFSET(E6,-R6,0,R6,1)-S6*OFFSET(F6,-R6,0,R6,1))^2)/(R6-3)),"") | W6: =IF(AND(F6>=1,R6>=Inputs!$B$10),(D6-U6-T6*E6-S6*F6)/V6,"") | X6: =IF(AB5<>0,AC5+1,0) -> 0 | Y6: =IF(W6="",0,IF(AND(AB5<>0,OR(ABS(W6)>Inputs!$B$7,X6>=Inputs!$B$8,ABS(W6)<Inputs!$B$6)),1,0)) -> 0 | Z6: =IF(Y6=1,0,AB5) -> 0 | AA6: =IF(W6="",0,IF(AND(Z6=0,ABS(W6)>Inputs!$B$5,ABS(W6)<=Inputs!$B$7),1,0)) -> 0 | AB6: =IF(W6="",0,IF(AA6=1,-SIGN(W6),Z6)) -> 0 | AC6: =IF(W6="",0,IF(AA6=1,0,IF(Y6=1,0,X6))) -> 0 | AD6: =IF(AB6=0,0,IF(AB5=AB6,AD5,T6)) -> 0 | AE6: =AB6-AB5 -> 0 | AF6: =-AD6*AB6 -> 0 | AG6: =AF6-AF5 -> 0 | AH6: =MAX(AE6,0)*(Inputs!$B$17+Inputs!$B$18+Inputs!$B$19)+MAX(-AE6,0)*(O6+Inputs!$B$18+Inputs!$B$19)+IF(AND(K6=1,AB6<>0),(Inputs!$B$17+Inputs!$B$18+Inputs!$B$19)+(O6+Inputs!$B$18+Inputs!$B$19),0)+MAX(AG6,0)*(Inputs!$B$20+Inputs!$B$22+Inputs!$B$23)+MAX(-AG6,0)*(Inputs!$B$21+Inputs!$B$22+Inputs!$B$23) -> 0 | AI6: =AB5*(M6-AD5*J6)+AB5*AD5*N6/Inputs!$B$16-AH6 -> 0 | AJ6: =MAX(AE6,0)*(Inputs!$B$17+Inputs!$B$24+Inputs!$B$25)+MAX(-AE6,0)*(O6+Inputs!$B$24+Inputs!$B$25)+IF(AND(K6=1,AB6<>0),(Inputs!$B$17+Inputs!$B$24+Inputs!$B$25)+(O6+Inputs!$B$24+Inputs!$B$25),0)+MAX(AG6,0)*(Inputs!$B$20+Inputs!$B$26+Inputs!$B$27)+MAX(-AG6,0)*(Inputs!$B$21+Inputs!$B$26+Inputs!$B$27) -> 0 | AK6: =AB5*(M6-AD5*J6)+AB5*AD5*(N6+Inputs!$B$14)/Inputs!$B$16-AJ6 -> 0 | AL6: =IF(AP5<>0,AQ5+1,0) -> 0 | AM6: =IF(W6="",0,IF(AND(AP5<>0,OR(ABS(W6)>Inputs!$B$7,AL6>=Inputs!$B$8,ABS(W6)<Inputs!$B$6)),1,0)) -> 0 | AN6: =IF(AM6=1,0,AP5) -> 0 | AO6: =IF(W6="",0,IF(AND(AN6=0,ABS(W6)>Inputs!$B$5,ABS(W6)<=Inputs!$B$7,W6>0),1,0)) -> 0 | AP6: =IF(W6="",0,IF(AO6=1,-SIGN(W6),AN6)) -> 0 | AQ6: =IF(W6="",0,IF(AO6=1,0,IF(AM6=1,0,AL6))) -> 0 | AR6: =IF(AP6=0,0,IF(AP5=AP6,AR5,T6)) -> 0 | AS6: =AP6-AP5 -> 0 | AT6: =-AR6*AP6 -> 0 | AU6: =AT6-AT5 -> 0 | AV6: =MAX(AS6,0)*(Inputs!$B$17+Inputs!$B$18+Inputs!$B$19)+MAX(-AS6,0)*(O6+Inputs!$B$18+Inputs!$B$19)+IF(AND(K6=1,AP6<>0),(Inputs!$B$17+Inputs!$B$18+Inputs!$B$19)+(O6+Inputs!$B$18+Inputs!$B$19),0)+MAX(AU6,0)*(Inputs!$B$20+Inputs!$B$22+Inputs!$B$23)+MAX(-AU6,0)*(Inputs!$B$21+Inputs!$B$22+Inputs!$B$23) -> 0 | AW6: =AP5*(M6-AR5*J6)+AP5*AR5*N6/Inputs!$B$16-AV6 -> 0 | AX6: =AW6-IF(AP5<>0,0.75*AR5*(Inputs!$B$13-N6)/Inputs!$B$16,0) -> 0 | AY6: =MAX(AS6,0)*(Inputs!$B$17+Inputs!$B$18+Inputs!$B$19)+MAX(-AS6,0)*(O6+Inputs!$B$18+Inputs!$B$19)+IF(AND(K6=1,AP6<>0),(Inputs!$B$17+Inputs!$B$18+Inputs!$B$19)+(O6+Inputs!$B$18+Inputs!$B$19),0) -> 0 | AZ6: =AP5*M6-AY6 -> 0 | BA6: =BA5+AI6 -> 0 | BB6: =MAX(BB5,BA6) -> 0 | BC6: =BA6-BB6 -> 0 | BD6: =A7-A6 -> 1
A7: 45050 | B7: 18287 | C7: 199.36 | D7: =LN(B7) -> 9.8139457 | E7: =LN(C7) -> 5.2951122 | F7: 2 | G7: 21 | H7: =D7-E7 -> 4.5188335 | I7: =D7-D6 -> 0.0076686356 | J7: =E7-E6 -> 0.00896867 | K7: 0 | L7: 0 | M7: =IF(L7=1,J7-Carry!$B$9/Inputs!$B$16,I7) -> 0.0076686356 | N7: 0.065 | O7: 0.000125 | P7: =D7-('2 Hedge ratio'!$B$6+'2 Hedge ratio'!$B$5*E7) -> 0.0011316103 | Q7: =D7-('5 Re-specification'!$B$7+'5 Re-specification'!$B$5*E7+'5 Re-specification'!$B$6*F7) -> 0.0037691437 | R7: =MIN(F7,Inputs!$B$9) -> 2 | S7: =IF(AND(F7>=1,R7>=Inputs!$B$10),INDEX(LINEST(OFFSET(D7,-R7,0,R7,1),OFFSET(E7,-R7,0,R7,2)),1,1),"") | T7: =IF(AND(F7>=1,R7>=Inputs!$B$10),INDEX(LINEST(OFFSET(D7,-R7,0,R7,1),OFFSET(E7,-R7,0,R7,2)),1,2),"") | U7: =IF(AND(F7>=1,R7>=Inputs!$B$10),INDEX(LINEST(OFFSET(D7,-R7,0,R7,1),OFFSET(E7,-R7,0,R7,2)),1,3),"") | V7: =IF(AND(F7>=1,R7>=Inputs!$B$10),SQRT(SUMPRODUCT((OFFSET(D7,-R7,0,R7,1)-U7-T7*OFFSET(E7,-R7,0,R7,1)-S7*OFFSET(F7,-R7,0,R7,1))^2)/(R7-3)),"") | W7: =IF(AND(F7>=1,R7>=Inputs!$B$10),(D7-U7-T7*E7-S7*F7)/V7,"") | X7: =IF(AB6<>0,AC6+1,0) -> 0 | Y7: =IF(W7="",0,IF(AND(AB6<>0,OR(ABS(W7)>Inputs!$B$7,X7>=Inputs!$B$8,ABS(W7)<Inputs!$B$6)),1,0)) -> 0 | Z7: =IF(Y7=1,0,AB6) -> 0 | AA7: =IF(W7="",0,IF(AND(Z7=0,ABS(W7)>Inputs!$B$5,ABS(W7)<=Inputs!$B$7),1,0)) -> 0 | AB7: =IF(W7="",0,IF(AA7=1,-SIGN(W7),Z7)) -> 0 | AC7: =IF(W7="",0,IF(AA7=1,0,IF(Y7=1,0,X7))) -> 0 | AD7: =IF(AB7=0,0,IF(AB6=AB7,AD6,T7)) -> 0 | AE7: =AB7-AB6 -> 0 | AF7: =-AD7*AB7 -> 0 | AG7: =AF7-AF6 -> 0 | AH7: =MAX(AE7,0)*(Inputs!$B$17+Inputs!$B$18+Inputs!$B$19)+MAX(-AE7,0)*(O7+Inputs!$B$18+Inputs!$B$19)+IF(AND(K7=1,AB7<>0),(Inputs!$B$17+Inputs!$B$18+Inputs!$B$19)+(O7+Inputs!$B$18+Inputs!$B$19),0)+MAX(AG7,0)*(Inputs!$B$20+Inputs!$B$22+Inputs!$B$23)+MAX(-AG7,0)*(Inputs!$B$21+Inputs!$B$22+Inputs!$B$23) -> 0 | AI7: =AB6*(M7-AD6*J7)+AB6*AD6*N7/Inputs!$B$16-AH7 -> 0 | AJ7: =MAX(AE7,0)*(Inputs!$B$17+Inputs!$B$24+Inputs!$B$25)+MAX(-AE7,0)*(O7+Inputs!$B$24+Inputs!$B$25)+IF(AND(K7=1,AB7<>0),(Inputs!$B$17+Inputs!$B$24+Inputs!$B$25)+(O7+Inputs!$B$24+Inputs!$B$25),0)+MAX(AG7,0)*(Inputs!$B$20+Inputs!$B$26+Inputs!$B$27)+MAX(-AG7,0)*(Inputs!$B$21+Inputs!$B$26+Inputs!$B$27) -> 0 | AK7: =AB6*(M7-AD6*J7)+AB6*AD6*(N7+Inputs!$B$14)/Inputs!$B$16-AJ7 -> 0 | AL7: =IF(AP6<>0,AQ6+1,0) -> 0 | AM7: =IF(W7="",0,IF(AND(AP6<>0,OR(ABS(W7)>Inputs!$B$7,AL7>=Inputs!$B$8,ABS(W7)<Inputs!$B$6)),1,0)) -> 0 | AN7: =IF(AM7=1,0,AP6) -> 0 | AO7: =IF(W7="",0,IF(AND(AN7=0,ABS(W7)>Inputs!$B$5,ABS(W7)<=Inputs!$B$7,W7>0),1,0)) -> 0 | AP7: =IF(W7="",0,IF(AO7=1,-SIGN(W7),AN7)) -> 0 | AQ7: =IF(W7="",0,IF(AO7=1,0,IF(AM7=1,0,AL7))) -> 0 | AR7: =IF(AP7=0,0,IF(AP6=AP7,AR6,T7)) -> 0 | AS7: =AP7-AP6 -> 0 | AT7: =-AR7*AP7 -> 0 | AU7: =AT7-AT6 -> 0 | AV7: =MAX(AS7,0)*(Inputs!$B$17+Inputs!$B$18+Inputs!$B$19)+MAX(-AS7,0)*(O7+Inputs!$B$18+Inputs!$B$19)+IF(AND(K7=1,AP7<>0),(Inputs!$B$17+Inputs!$B$18+Inputs!$B$19)+(O7+Inputs!$B$18+Inputs!$B$19),0)+MAX(AU7,0)*(Inputs!$B$20+Inputs!$B$22+Inputs!$B$23)+MAX(-AU7,0)*(Inputs!$B$21+Inputs!$B$22+Inputs!$B$23) -> 0 | AW7: =AP6*(M7-AR6*J7)+AP6*AR6*N7/Inputs!$B$16-AV7 -> 0 | AX7: =AW7-IF(AP6<>0,0.75*AR6*(Inputs!$B$13-N7)/Inputs!$B$16,0) -> 0 | AY7: =MAX(AS7,0)*(Inputs!$B$17+Inputs!$B$18+Inputs!$B$19)+MAX(-AS7,0)*(O7+Inputs!$B$18+Inputs!$B$19)+IF(AND(K7=1,AP7<>0),(Inputs!$B$17+Inputs!$B$18+Inputs!$B$19)+(O7+Inputs!$B$18+Inputs!$B$19),0) -> 0 | AZ7: =AP6*M7-AY7 -> 0 | BA7: =BA6+AI7 -> 0 | BB7: =MAX(BB6,BA7) -> 0 | BC7: =BA7-BB7 -> 0 | BD7: =A8-A7 -> 1
A8: 45051 | B8: 18130.1 | C8: 197.89 | D8: =LN(B8) -> 9.8053288 | E8: =LN(C8) -> 5.2877113 | F8: 3 | G8: 20 | H8: =D8-E8 -> 4.5176175 | I8: =D8-D7 -> -0.0086168844 | J8: =E8-E7 -> -0.0074009148 | K8: 0 | L8: 0 | M8: =IF(L8=1,J8-Carry!$B$9/Inputs!$B$16,I8) -> -0.0086168844 | N8: 0.065 | O8: 0.000125 | P8: =D8-('2 Hedge ratio'!$B$6+'2 Hedge ratio'!$B$5*E8) -> -0.00070509802 | Q8: =D8-('5 Re-specification'!$B$7+'5 Re-specification'!$B$5*E8+'5 Re-specification'!$B$6*F8) -> 0.002575675 | R8: =MIN(F8,Inputs!$B$9) -> 3 | S8: =IF(AND(F8>=1,R8>=Inputs!$B$10),INDEX(LINEST(OFFSET(D8,-R8,0,R8,1),OFFSET(E8,-R8,0,R8,2)),1,1),"") | T8: =IF(AND(F8>=1,R8>=Inputs!$B$10),INDEX(LINEST(OFFSET(D8,-R8,0,R8,1),OFFSET(E8,-R8,0,R8,2)),1,2),"") | U8: =IF(AND(F8>=1,R8>=Inputs!$B$10),INDEX(LINEST(OFFSET(D8,-R8,0,R8,1),OFFSET(E8,-R8,0,R8,2)),1,3),"") | V8: =IF(AND(F8>=1,R8>=Inputs!$B$10),SQRT(SUMPRODUCT((OFFSET(D8,-R8,0,R8,1)-U8-T8*OFFSET(E8,-R8,0,R8,1)-S8*OFFSET(F8,-R8,0,R8,1))^2)/(R8-3)),"") | W8: =IF(AND(F8>=1,R8>=Inputs!$B$10),(D8-U8-T8*E8-S8*F8)/V8,"") | X8: =IF(AB7<>0,AC7+1,0) -> 0 | Y8: =IF(W8="",0,IF(AND(AB7<>0,OR(ABS(W8)>Inputs!$B$7,X8>=Inputs!$B$8,ABS(W8)<Inputs!$B$6)),1,0)) -> 0 | Z8: =IF(Y8=1,0,AB7) -> 0 | AA8: =IF(W8="",0,IF(AND(Z8=0,ABS(W8)>Inputs!$B$5,ABS(W8)<=Inputs!$B$7),1,0)) -> 0 | AB8: =IF(W8="",0,IF(AA8=1,-SIGN(W8),Z8)) -> 0 | AC8: =IF(W8="",0,IF(AA8=1,0,IF(Y8=1,0,X8))) -> 0 | AD8: =IF(AB8=0,0,IF(AB7=AB8,AD7,T8)) -> 0 | AE8: =AB8-AB7 -> 0 | AF8: =-AD8*AB8 -> 0 | AG8: =AF8-AF7 -> 0 | AH8: =MAX(AE8,0)*(Inputs!$B$17+Inputs!$B$18+Inputs!$B$19)+MAX(-AE8,0)*(O8+Inputs!$B$18+Inputs!$B$19)+IF(AND(K8=1,AB8<>0),(Inputs!$B$17+Inputs!$B$18+Inputs!$B$19)+(O8+Inputs!$B$18+Inputs!$B$19),0)+MAX(AG8,0)*(Inputs!$B$20+Inputs!$B$22+Inputs!$B$23)+MAX(-AG8,0)*(Inputs!$B$21+Inputs!$B$22+Inputs!$B$23) -> 0 | AI8: =AB7*(M8-AD7*J8)+AB7*AD7*N8/Inputs!$B$16-AH8 -> 0 | AJ8: =MAX(AE8,0)*(Inputs!$B$17+Inputs!$B$24+Inputs!$B$25)+MAX(-AE8,0)*(O8+Inputs!$B$24+Inputs!$B$25)+IF(AND(K8=1,AB8<>0),(Inputs!$B$17+Inputs!$B$24+Inputs!$B$25)+(O8+Inputs!$B$24+Inputs!$B$25),0)+MAX(AG8,0)*(Inputs!$B$20+Inputs!$B$26+Inputs!$B$27)+MAX(-AG8,0)*(Inputs!$B$21+Inputs!$B$26+Inputs!$B$27) -> 0 | AK8: =AB7*(M8-AD7*J8)+AB7*AD7*(N8+Inputs!$B$14)/Inputs!$B$16-AJ8 -> 0 | AL8: =IF(AP7<>0,AQ7+1,0) -> 0 | AM8: =IF(W8="",0,IF(AND(AP7<>0,OR(ABS(W8)>Inputs!$B$7,AL8>=Inputs!$B$8,ABS(W8)<Inputs!$B$6)),1,0)) -> 0 | AN8: =IF(AM8=1,0,AP7) -> 0 | AO8: =IF(W8="",0,IF(AND(AN8=0,ABS(W8)>Inputs!$B$5,ABS(W8)<=Inputs!$B$7,W8>0),1,0)) -> 0 | AP8: =IF(W8="",0,IF(AO8=1,-SIGN(W8),AN8)) -> 0 | AQ8: =IF(W8="",0,IF(AO8=1,0,IF(AM8=1,0,AL8))) -> 0 | AR8: =IF(AP8=0,0,IF(AP7=AP8,AR7,T8)) -> 0 | AS8: =AP8-AP7 -> 0 | AT8: =-AR8*AP8 -> 0 | AU8: =AT8-AT7 -> 0 | AV8: =MAX(AS8,0)*(Inputs!$B$17+Inputs!$B$18+Inputs!$B$19)+MAX(-AS8,0)*(O8+Inputs!$B$18+Inputs!$B$19)+IF(AND(K8=1,AP8<>0),(Inputs!$B$17+Inputs!$B$18+Inputs!$B$19)+(O8+Inputs!$B$18+Inputs!$B$19),0)+MAX(AU8,0)*(Inputs!$B$20+Inputs!$B$22+Inputs!$B$23)+MAX(-AU8,0)*(Inputs!$B$21+Inputs!$B$22+Inputs!$B$23) -> 0 | AW8: =AP7*(M8-AR7*J8)+AP7*AR7*N8/Inputs!$B$16-AV8 -> 0 | AX8: =AW8-IF(AP7<>0,0.75*AR7*(Inputs!$B$13-N8)/Inputs!$B$16,0) -> 0 | AY8: =MAX(AS8,0)*(Inputs!$B$17+Inputs!$B$18+Inputs!$B$19)+MAX(-AS8,0)*(O8+Inputs!$B$18+Inputs!$B$19)+IF(AND(K8=1,AP8<>0),(Inputs!$B$17+Inputs!$B$18+Inputs!$B$19)+(O8+Inputs!$B$18+Inputs!$B$19),0) -> 0 | AZ8: =AP7*M8-AY8 -> 0 | BA8: =BA7+AI8 -> 0 | BB8: =MAX(BB7,BA8) -> 0 | BC8: =BA8-BB8 -> 0 | BD8: =A9-A8 -> 3
A9: 45054 | B9: 18317.5 | C9: 199.9 | D9: =LN(B9) -> 9.8156122 | E9: =LN(C9) -> 5.2978172 | F9: 4 | G9: 17 | H9: =D9-E9 -> 4.5177949 | I9: =D9-D8 -> 0.010283347 | J9: =E9-E8 -> 0.010105921 | K9: 0 | L9: 0 | M9: =IF(L9=1,J9-Carry!$B$9/Inputs!$B$16,I9) -> 0.010283347 | N9: 0.065 | O9: 0.000125 | P9: =D9-('2 Hedge ratio'!$B$6+'2 Hedge ratio'!$B$5*E9) -> 0.00031994414 | Q9: =D9-('5 Re-specification'!$B$7+'5 Re-specification'!$B$5*E9+'5 Re-specification'!$B$6*F9) -> 0.0028286561 | R9: =MIN(F9,Inputs!$B$9) -> 4 | S9: =IF(AND(F9>=1,R9>=Inputs!$B$10),INDEX(LINEST(OFFSET(D9,-R9,0,R9,1),OFFSET(E9,-R9,0,R9,2)),1,1),"") | T9: =IF(AND(F9>=1,R9>=Inputs!$B$10),INDEX(LINEST(OFFSET(D9,-R9,0,R9,1),OFFSET(E9,-R9,0,R9,2)),1,2),"") | U9: =IF(AND(F9>=1,R9>=Inputs!$B$10),INDEX(LINEST(OFFSET(D9,-R9,0,R9,1),OFFSET(E9,-R9,0,R9,2)),1,3),"") | V9: =IF(AND(F9>=1,R9>=Inputs!$B$10),SQRT(SUMPRODUCT((OFFSET(D9,-R9,0,R9,1)-U9-T9*OFFSET(E9,-R9,0,R9,1)-S9*OFFSET(F9,-R9,0,R9,1))^2)/(R9-3)),"") | W9: =IF(AND(F9>=1,R9>=Inputs!$B$10),(D9-U9-T9*E9-S9*F9)/V9,"") | X9: =IF(AB8<>0,AC8+1,0) -> 0 | Y9: =IF(W9="",0,IF(AND(AB8<>0,OR(ABS(W9)>Inputs!$B$7,X9>=Inputs!$B$8,ABS(W9)<Inputs!$B$6)),1,0)) -> 0 | Z9: =IF(Y9=1,0,AB8) -> 0 | AA9: =IF(W9="",0,IF(AND(Z9=0,ABS(W9)>Inputs!$B$5,ABS(W9)<=Inputs!$B$7),1,0)) -> 0 | AB9: =IF(W9="",0,IF(AA9=1,-SIGN(W9),Z9)) -> 0 | AC9: =IF(W9="",0,IF(AA9=1,0,IF(Y9=1,0,X9))) -> 0 | AD9: =IF(AB9=0,0,IF(AB8=AB9,AD8,T9)) -> 0 | AE9: =AB9-AB8 -> 0 | AF9: =-AD9*AB9 -> 0 | AG9: =AF9-AF8 -> 0 | AH9: =MAX(AE9,0)*(Inputs!$B$17+Inputs!$B$18+Inputs!$B$19)+MAX(-AE9,0)*(O9+Inputs!$B$18+Inputs!$B$19)+IF(AND(K9=1,AB9<>0),(Inputs!$B$17+Inputs!$B$18+Inputs!$B$19)+(O9+Inputs!$B$18+Inputs!$B$19),0)+MAX(AG9,0)*(Inputs!$B$20+Inputs!$B$22+Inputs!$B$23)+MAX(-AG9,0)*(Inputs!$B$21+Inputs!$B$22+Inputs!$B$23) -> 0 | AI9: =AB8*(M9-AD8*J9)+AB8*AD8*N9/Inputs!$B$16-AH9 -> 0 | AJ9: =MAX(AE9,0)*(Inputs!$B$17+Inputs!$B$24+Inputs!$B$25)+MAX(-AE9,0)*(O9+Inputs!$B$24+Inputs!$B$25)+IF(AND(K9=1,AB9<>0),(Inputs!$B$17+Inputs!$B$24+Inputs!$B$25)+(O9+Inputs!$B$24+Inputs!$B$25),0)+MAX(AG9,0)*(Inputs!$B$20+Inputs!$B$26+Inputs!$B$27)+MAX(-AG9,0)*(Inputs!$B$21+Inputs!$B$26+Inputs!$B$27) -> 0 | AK9: =AB8*(M9-AD8*J9)+AB8*AD8*(N9+Inputs!$B$14)/Inputs!$B$16-AJ9 -> 0 | AL9: =IF(AP8<>0,AQ8+1,0) -> 0 | AM9: =IF(W9="",0,IF(AND(AP8<>0,OR(ABS(W9)>Inputs!$B$7,AL9>=Inputs!$B$8,ABS(W9)<Inputs!$B$6)),1,0)) -> 0 | AN9: =IF(AM9=1,0,AP8) -> 0 | AO9: =IF(W9="",0,IF(AND(AN9=0,ABS(W9)>Inputs!$B$5,ABS(W9)<=Inputs!$B$7,W9>0),1,0)) -> 0 | AP9: =IF(W9="",0,IF(AO9=1,-SIGN(W9),AN9)) -> 0 | AQ9: =IF(W9="",0,IF(AO9=1,0,IF(AM9=1,0,AL9))) -> 0 | AR9: =IF(AP9=0,0,IF(AP8=AP9,AR8,T9)) -> 0 | AS9: =AP9-AP8 -> 0 | AT9: =-AR9*AP9 -> 0 | AU9: =AT9-AT8 -> 0 | AV9: =MAX(AS9,0)*(Inputs!$B$17+Inputs!$B$18+Inputs!$B$19)+MAX(-AS9,0)*(O9+Inputs!$B$18+Inputs!$B$19)+IF(AND(K9=1,AP9<>0),(Inputs!$B$17+Inputs!$B$18+Inputs!$B$19)+(O9+Inputs!$B$18+Inputs!$B$19),0)+MAX(AU9,0)*(Inputs!$B$20+Inputs!$B$22+Inputs!$B$23)+MAX(-AU9,0)*(Inputs!$B$21+Inputs!$B$22+Inputs!$B$23) -> 0 | AW9: =AP8*(M9-AR8*J9)+AP8*AR8*N9/Inputs!$B$16-AV9 -> 0 | AX9: =AW9-IF(AP8<>0,0.75*AR8*(Inputs!$B$13-N9)/Inputs!$B$16,0) -> 0 | AY9: =MAX(AS9,0)*(Inputs!$B$17+Inputs!$B$18+Inputs!$B$19)+MAX(-AS9,0)*(O9+Inputs!$B$18+Inputs!$B$19)+IF(AND(K9=1,AP9<>0),(Inputs!$B$17+Inputs!$B$18+Inputs!$B$19)+(O9+Inputs!$B$18+Inputs!$B$19),0) -> 0 | AZ9: =AP8*M9-AY9 -> 0 | BA9: =BA8+AI9 -> 0 | BB9: =MAX(BB8,BA9) -> 0 | BC9: =BA9-BB9 -> 0 | BD9: =A10-A9 -> 1
A10: 45055 | B10: 18303.8 | C10: 199.75 | D10: =LN(B10) -> 9.814864 | E10: =LN(C10) -> 5.2970666 | F10: 5 | G10: 16 | H10: =D10-E10 -> 4.5177974 | I10: =D10-D9 -> -0.00074819849 | J10: =E10-E9 -> -0.00075065686 | K10: 0 | L10: 0 | M10: =IF(L10=1,J10-Carry!$B$9/Inputs!$B$16,I10) -> -0.00074819849 | N10: 0.065 | O10: 0.000125 | P10: =D10-('2 Hedge ratio'!$B$6+'2 Hedge ratio'!$B$5*E10) -> 0.00025944249 | Q10: =D10-('5 Re-specification'!$B$7+'5 Re-specification'!$B$5*E10+'5 Re-specification'!$B$6*F10) -> 0.0028737689 | R10: =MIN(F10,Inputs!$B$9) -> 5 | S10: =IF(AND(F10>=1,R10>=Inputs!$B$10),INDEX(LINEST(OFFSET(D10,-R10,0,R10,1),OFFSET(E10,-R10,0,R10,2)),1,1),"") | T10: =IF(AND(F10>=1,R10>=Inputs!$B$10),INDEX(LINEST(OFFSET(D10,-R10,0,R10,1),OFFSET(E10,-R10,0,R10,2)),1,2),"") | U10: =IF(AND(F10>=1,R10>=Inputs!$B$10),INDEX(LINEST(OFFSET(D10,-R10,0,R10,1),OFFSET(E10,-R10,0,R10,2)),1,3),"") | V10: =IF(AND(F10>=1,R10>=Inputs!$B$10),SQRT(SUMPRODUCT((OFFSET(D10,-R10,0,R10,1)-U10-T10*OFFSET(E10,-R10,0,R10,1)-S10*OFFSET(F10,-R10,0,R10,1))^2)/(R10-3)),"") | W10: =IF(AND(F10>=1,R10>=Inputs!$B$10),(D10-U10-T10*E10-S10*F10)/V10,"") | X10: =IF(AB9<>0,AC9+1,0) -> 0 | Y10: =IF(W10="",0,IF(AND(AB9<>0,OR(ABS(W10)>Inputs!$B$7,X10>=Inputs!$B$8,ABS(W10)<Inputs!$B$6)),1,0)) -> 0 | Z10: =IF(Y10=1,0,AB9) -> 0 | AA10: =IF(W10="",0,IF(AND(Z10=0,ABS(W10)>Inputs!$B$5,ABS(W10)<=Inputs!$B$7),1,0)) -> 0 | AB10: =IF(W10="",0,IF(AA10=1,-SIGN(W10),Z10)) -> 0 | AC10: =IF(W10="",0,IF(AA10=1,0,IF(Y10=1,0,X10))) -> 0 | AD10: =IF(AB10=0,0,IF(AB9=AB10,AD9,T10)) -> 0 | AE10: =AB10-AB9 -> 0 | AF10: =-AD10*AB10 -> 0 | AG10: =AF10-AF9 -> 0 | AH10: =MAX(AE10,0)*(Inputs!$B$17+Inputs!$B$18+Inputs!$B$19)+MAX(-AE10,0)*(O10+Inputs!$B$18+Inputs!$B$19)+IF(AND(K10=1,AB10<>0),(Inputs!$B$17+Inputs!$B$18+Inputs!$B$19)+(O10+Inputs!$B$18+Inputs!$B$19),0)+MAX(AG10,0)*(Inputs!$B$20+Inputs!$B$22+Inputs!$B$23)+MAX(-AG10,0)*(Inputs!$B$21+Inputs!$B$22+Inputs!$B$23) -> 0 | AI10: =AB9*(M10-AD9*J10)+AB9*AD9*N10/Inputs!$B$16-AH10 -> 0 | AJ10: =MAX(AE10,0)*(Inputs!$B$17+Inputs!$B$24+Inputs!$B$25)+MAX(-AE10,0)*(O10+Inputs!$B$24+Inputs!$B$25)+IF(AND(K10=1,AB10<>0),(Inputs!$B$17+Inputs!$B$24+Inputs!$B$25)+(O10+Inputs!$B$24+Inputs!$B$25),0)+MAX(AG10,0)*(Inputs!$B$20+Inputs!$B$26+Inputs!$B$27)+MAX(-AG10,0)*(Inputs!$B$21+Inputs!$B$26+Inputs!$B$27) -> 0 | AK10: =AB9*(M10-AD9*J10)+AB9*AD9*(N10+Inputs!$B$14)/Inputs!$B$16-AJ10 -> 0 | AL10: =IF(AP9<>0,AQ9+1,0) -> 0 | AM10: =IF(W10="",0,IF(AND(AP9<>0,OR(ABS(W10)>Inputs!$B$7,AL10>=Inputs!$B$8,ABS(W10)<Inputs!$B$6)),1,0)) -> 0 | AN10: =IF(AM10=1,0,AP9) -> 0 | AO10: =IF(W10="",0,IF(AND(AN10=0,ABS(W10)>Inputs!$B$5,ABS(W10)<=Inputs!$B$7,W10>0),1,0)) -> 0 | AP10: =IF(W10="",0,IF(AO10=1,-SIGN(W10),AN10)) -> 0 | AQ10: =IF(W10="",0,IF(AO10=1,0,IF(AM10=1,0,AL10))) -> 0 | AR10: =IF(AP10=0,0,IF(AP9=AP10,AR9,T10)) -> 0 | AS10: =AP10-AP9 -> 0 | AT10: =-AR10*AP10 -> 0 | AU10: =AT10-AT9 -> 0 | AV10: =MAX(AS10,0)*(Inputs!$B$17+Inputs!$B$18+Inputs!$B$19)+MAX(-AS10,0)*(O10+Inputs!$B$18+Inputs!$B$19)+IF(AND(K10=1,AP10<>0),(Inputs!$B$17+Inputs!$B$18+Inputs!$B$19)+(O10+Inputs!$B$18+Inputs!$B$19),0)+MAX(AU10,0)*(Inputs!$B$20+Inputs!$B$22+Inputs!$B$23)+MAX(-AU10,0)*(Inputs!$B$21+Inputs!$B$22+Inputs!$B$23) -> 0 | AW10: =AP9*(M10-AR9*J10)+AP9*AR9*N10/Inputs!$B$16-AV10 -> 0 | AX10: =AW10-IF(AP9<>0,0.75*AR9*(Inputs!$B$13-N10)/Inputs!$B$16,0) -> 0 | AY10: =MAX(AS10,0)*(Inputs!$B$17+Inputs!$B$18+Inputs!$B$19)+MAX(-AS10,0)*(O10+Inputs!$B$18+Inputs!$B$19)+IF(AND(K10=1,AP10<>0),(Inputs!$B$17+Inputs!$B$18+Inputs!$B$19)+(O10+Inputs!$B$18+Inputs!$B$19),0) -> 0 | AZ10: =AP9*M10-AY10 -> 0 | BA10: =BA9+AI10 -> 0 | BB10: =MAX(BB9,BA10) -> 0 | BC10: =BA10-BB10 -> 0 | BD10: =A11-A10 -> 1
A11: 45056 | B11: 18343 | C11: 200.21 | D11: =LN(B11) -> 9.8170033 | E11: =LN(C11) -> 5.2993668 | F11: 6 | G11: 15 | H11: =D11-E11 -> 4.5176365 | I11: =D11-D10 -> 0.0021393418 | J11: =E11-E10 -> 0.002300231 | K11: 0 | L11: 0 | M11: =IF(L11=1,J11-Carry!$B$9/Inputs!$B$16,I11) -> 0.0021393418 | N11: 0.065 | O11: 0.000125 | P11: =D11-('2 Hedge ratio'!$B$6+'2 Hedge ratio'!$B$5*E11) -> 0.00029148105 | Q11: =D11-('5 Re-specification'!$B$7+'5 Re-specification'!$B$5*E11+'5 Re-specification'!$B$6*F11) -> 0.0027647798 | R11: =MIN(F11,Inputs!$B$9) -> 6 | S11: =IF(AND(F11>=1,R11>=Inputs!$B$10),INDEX(LINEST(OFFSET(D11,-R11,0,R11,1),OFFSET(E11,-R11,0,R11,2)),1,1),"") | T11: =IF(AND(F11>=1,R11>=Inputs!$B$10),INDEX(LINEST(OFFSET(D11,-R11,0,R11,1),OFFSET(E11,-R11,0,R11,2)),1,2),"") | U11: =IF(AND(F11>=1,R11>=Inputs!$B$10),INDEX(LINEST(OFFSET(D11,-R11,0,R11,1),OFFSET(E11,-R11,0,R11,2)),1,3),"") | V11: =IF(AND(F11>=1,R11>=Inputs!$B$10),SQRT(SUMPRODUCT((OFFSET(D11,-R11,0,R11,1)-U11-T11*OFFSET(E11,-R11,0,R11,1)-S11*OFFSET(F11,-R11,0,R11,1))^2)/(R11-3)),"") | W11: =IF(AND(F11>=1,R11>=Inputs!$B$10),(D11-U11-T11*E11-S11*F11)/V11,"") | X11: =IF(AB10<>0,AC10+1,0) -> 0 | Y11: =IF(W11="",0,IF(AND(AB10<>0,OR(ABS(W11)>Inputs!$B$7,X11>=Inputs!$B$8,ABS(W11)<Inputs!$B$6)),1,0)) -> 0 | Z11: =IF(Y11=1,0,AB10) -> 0 | AA11: =IF(W11="",0,IF(AND(Z11=0,ABS(W11)>Inputs!$B$5,ABS(W11)<=Inputs!$B$7),1,0)) -> 0 | AB11: =IF(W11="",0,IF(AA11=1,-SIGN(W11),Z11)) -> 0 | AC11: =IF(W11="",0,IF(AA11=1,0,IF(Y11=1,0,X11))) -> 0 | AD11: =IF(AB11=0,0,IF(AB10=AB11,AD10,T11)) -> 0 | AE11: =AB11-AB10 -> 0 | AF11: =-AD11*AB11 -> 0 | AG11: =AF11-AF10 -> 0 | AH11: =MAX(AE11,0)*(Inputs!$B$17+Inputs!$B$18+Inputs!$B$19)+MAX(-AE11,0)*(O11+Inputs!$B$18+Inputs!$B$19)+IF(AND(K11=1,AB11<>0),(Inputs!$B$17+Inputs!$B$18+Inputs!$B$19)+(O11+Inputs!$B$18+Inputs!$B$19),0)+MAX(AG11,0)*(Inputs!$B$20+Inputs!$B$22+Inputs!$B$23)+MAX(-AG11,0)*(Inputs!$B$21+Inputs!$B$22+Inputs!$B$23) -> 0 | AI11: =AB10*(M11-AD10*J11)+AB10*AD10*N11/Inputs!$B$16-AH11 -> 0 | AJ11: =MAX(AE11,0)*(Inputs!$B$17+Inputs!$B$24+Inputs!$B$25)+MAX(-AE11,0)*(O11+Inputs!$B$24+Inputs!$B$25)+IF(AND(K11=1,AB11<>0),(Inputs!$B$17+Inputs!$B$24+Inputs!$B$25)+(O11+Inputs!$B$24+Inputs!$B$25),0)+MAX(AG11,0)*(Inputs!$B$20+Inputs!$B$26+Inputs!$B$27)+MAX(-AG11,0)*(Inputs!$B$21+Inputs!$B$26+Inputs!$B$27) -> 0 | AK11: =AB10*(M11-AD10*J11)+AB10*AD10*(N11+Inputs!$B$14)/Inputs!$B$16-AJ11 -> 0 | AL11: =IF(AP10<>0,AQ10+1,0) -> 0 | AM11: =IF(W11="",0,IF(AND(AP10<>0,OR(ABS(W11)>Inputs!$B$7,AL11>=Inputs!$B$8,ABS(W11)<Inputs!$B$6)),1,0)) -> 0 | AN11: =IF(AM11=1,0,AP10) -> 0 | AO11: =IF(W11="",0,IF(AND(AN11=0,ABS(W11)>Inputs!$B$5,ABS(W11)<=Inputs!$B$7,W11>0),1,0)) -> 0 | AP11: =IF(W11="",0,IF(AO11=1,-SIGN(W11),AN11)) -> 0 | AQ11: =IF(W11="",0,IF(AO11=1,0,IF(AM11=1,0,AL11))) -> 0 | AR11: =IF(AP11=0,0,IF(AP10=AP11,AR10,T11)) -> 0 | AS11: =AP11-AP10 -> 0 | AT11: =-AR11*AP11 -> 0 | AU11: =AT11-AT10 -> 0 | AV11: =MAX(AS11,0)*(Inputs!$B$17+Inputs!$B$18+Inputs!$B$19)+MAX(-AS11,0)*(O11+Inputs!$B$18+Inputs!$B$19)+IF(AND(K11=1,AP11<>0),(Inputs!$B$17+Inputs!$B$18+Inputs!$B$19)+(O11+Inputs!$B$18+Inputs!$B$19),0)+MAX(AU11,0)*(Inputs!$B$20+Inputs!$B$22+Inputs!$B$23)+MAX(-AU11,0)*(Inputs!$B$21+Inputs!$B$22+Inputs!$B$23) -> 0 | AW11: =AP10*(M11-AR10*J11)+AP10*AR10*N11/Inputs!$B$16-AV11 -> 0 | AX11: =AW11-IF(AP10<>0,0.75*AR10*(Inputs!$B$13-N11)/Inputs!$B$16,0) -> 0 | AY11: =MAX(AS11,0)*(Inputs!$B$17+Inputs!$B$18+Inputs!$B$19)+MAX(-AS11,0)*(O11+Inputs!$B$18+Inputs!$B$19)+IF(AND(K11=1,AP11<>0),(Inputs!$B$17+Inputs!$B$18+Inputs!$B$19)+(O11+Inputs!$B$18+Inputs!$B$19),0) -> 0 | AZ11: =AP10*M11-AY11 -> 0 | BA11: =BA10+AI11 -> 0 | BB11: =MAX(BB10,BA11) -> 0 | BC11: =BA11-BB11 -> 0 | BD11: =A12-A11 -> 1
A12: 45057 | B12: 18359 | C12: 200.4 | D12: =LN(B12) -> 9.8178752 | E12: =LN(C12) -> 5.3003154 | F12: 7 | G12: 14 | H12: =D12-E12 -> 4.5175598 | I12: =D12-D11 -> 0.00087188715 | J12: =E12-E11 -> 0.00094855353 | K12: 0 | L12: 0 | M12: =IF(L12=1,J12-Carry!$B$9/Inputs!$B$16,I12) -> 0.00087188715 | N12: 0.065 | O12: 0.000125 | P12: =D12-('2 Hedge ratio'!$B$6+'2 Hedge ratio'!$B$5*E12) -> 0.00029437293 | Q12: =D12-('5 Re-specification'!$B$7+'5 Re-specification'!$B$5*E12+'5 Re-specification'!$B$6*F12) -> 0.0027359174 | R12: =MIN(F12,Inputs!$B$9) -> 7 | S12: =IF(AND(F12>=1,R12>=Inputs!$B$10),INDEX(LINEST(OFFSET(D12,-R12,0,R12,1),OFFSET(E12,-R12,0,R12,2)),1,1),"") | T12: =IF(AND(F12>=1,R12>=Inputs!$B$10),INDEX(LINEST(OFFSET(D12,-R12,0,R12,1),OFFSET(E12,-R12,0,R12,2)),1,2),"") | U12: =IF(AND(F12>=1,R12>=Inputs!$B$10),INDEX(LINEST(OFFSET(D12,-R12,0,R12,1),OFFSET(E12,-R12,0,R12,2)),1,3),"") | V12: =IF(AND(F12>=1,R12>=Inputs!$B$10),SQRT(SUMPRODUCT((OFFSET(D12,-R12,0,R12,1)-U12-T12*OFFSET(E12,-R12,0,R12,1)-S12*OFFSET(F12,-R12,0,R12,1))^2)/(R12-3)),"") | W12: =IF(AND(F12>=1,R12>=Inputs!$B$10),(D12-U12-T12*E12-S12*F12)/V12,"") | X12: =IF(AB11<>0,AC11+1,0) -> 0 | Y12: =IF(W12="",0,IF(AND(AB11<>0,OR(ABS(W12)>Inputs!$B$7,X12>=Inputs!$B$8,ABS(W12)<Inputs!$B$6)),1,0)) -> 0 | Z12: =IF(Y12=1,0,AB11) -> 0 | AA12: =IF(W12="",0,IF(AND(Z12=0,ABS(W12)>Inputs!$B$5,ABS(W12)<=Inputs!$B$7),1,0)) -> 0 | AB12: =IF(W12="",0,IF(AA12=1,-SIGN(W12),Z12)) -> 0 | AC12: =IF(W12="",0,IF(AA12=1,0,IF(Y12=1,0,X12))) -> 0 | AD12: =IF(AB12=0,0,IF(AB11=AB12,AD11,T12)) -> 0 | AE12: =AB12-AB11 -> 0 | AF12: =-AD12*AB12 -> 0 | AG12: =AF12-AF11 -> 0 | AH12: =MAX(AE12,0)*(Inputs!$B$17+Inputs!$B$18+Inputs!$B$19)+MAX(-AE12,0)*(O12+Inputs!$B$18+Inputs!$B$19)+IF(AND(K12=1,AB12<>0),(Inputs!$B$17+Inputs!$B$18+Inputs!$B$19)+(O12+Inputs!$B$18+Inputs!$B$19),0)+MAX(AG12,0)*(Inputs!$B$20+Inputs!$B$22+Inputs!$B$23)+MAX(-AG12,0)*(Inputs!$B$21+Inputs!$B$22+Inputs!$B$23) -> 0 | AI12: =AB11*(M12-AD11*J12)+AB11*AD11*N12/Inputs!$B$16-AH12 -> 0 | AJ12: =MAX(AE12,0)*(Inputs!$B$17+Inputs!$B$24+Inputs!$B$25)+MAX(-AE12,0)*(O12+Inputs!$B$24+Inputs!$B$25)+IF(AND(K12=1,AB12<>0),(Inputs!$B$17+Inputs!$B$24+Inputs!$B$25)+(O12+Inputs!$B$24+Inputs!$B$25),0)+MAX(AG12,0)*(Inputs!$B$20+Inputs!$B$26+Inputs!$B$27)+MAX(-AG12,0)*(Inputs!$B$21+Inputs!$B$26+Inputs!$B$27) -> 0 | AK12: =AB11*(M12-AD11*J12)+AB11*AD11*(N12+Inputs!$B$14)/Inputs!$B$16-AJ12 -> 0 | AL12: =IF(AP11<>0,AQ11+1,0) -> 0 | AM12: =IF(W12="",0,IF(AND(AP11<>0,OR(ABS(W12)>Inputs!$B$7,AL12>=Inputs!$B$8,ABS(W12)<Inputs!$B$6)),1,0)) -> 0 | AN12: =IF(AM12=1,0,AP11) -> 0 | AO12: =IF(W12="",0,IF(AND(AN12=0,ABS(W12)>Inputs!$B$5,ABS(W12)<=Inputs!$B$7,W12>0),1,0)) -> 0 | AP12: =IF(W12="",0,IF(AO12=1,-SIGN(W12),AN12)) -> 0 | AQ12: =IF(W12="",0,IF(AO12=1,0,IF(AM12=1,0,AL12))) -> 0 | AR12: =IF(AP12=0,0,IF(AP11=AP12,AR11,T12)) -> 0 | AS12: =AP12-AP11 -> 0 | AT12: =-AR12*AP12 -> 0 | AU12: =AT12-AT11 -> 0 | AV12: =MAX(AS12,0)*(Inputs!$B$17+Inputs!$B$18+Inputs!$B$19)+MAX(-AS12,0)*(O12+Inputs!$B$18+Inputs!$B$19)+IF(AND(K12=1,AP12<>0),(Inputs!$B$17+Inputs!$B$18+Inputs!$B$19)+(O12+Inputs!$B$18+Inputs!$B$19),0)+MAX(AU12,0)*(Inputs!$B$20+Inputs!$B$22+Inputs!$B$23)+MAX(-AU12,0)*(Inputs!$B$21+Inputs!$B$22+Inputs!$B$23) -> 0 | AW12: =AP11*(M12-AR11*J12)+AP11*AR11*N12/Inputs!$B$16-AV12 -> 0 | AX12: =AW12-IF(AP11<>0,0.75*AR11*(Inputs!$B$13-N12)/Inputs!$B$16,0) -> 0 | AY12: =MAX(AS12,0)*(Inputs!$B$17+Inputs!$B$18+Inputs!$B$19)+MAX(-AS12,0)*(O12+Inputs!$B$18+Inputs!$B$19)+IF(AND(K12=1,AP12<>0),(Inputs!$B$17+Inputs!$B$18+Inputs!$B$19)+(O12+Inputs!$B$18+Inputs!$B$19),0) -> 0 | AZ12: =AP11*M12-AY12 -> 0 | BA12: =BA11+AI12 -> 0 | BB12: =MAX(BB11,BA12) -> 0 | BC12: =BA12-BB12 -> 0 | BD12: =A13-A12 -> 1
A13: 45058 | B13: 18334 | C13: 200.1 | D13: =LN(B13) -> 9.8165125 | E13: =LN(C13) -> 5.2988172 | F13: 8 | G13: 13 | H13: =D13-E13 -> 4.5176953 | I13: =D13-D12 -> -0.0013626579 | J13: =E13-E12 -> -0.0014981276 | K13: 0 | L13: 0 | M13: =IF(L13=1,J13-Carry!$B$9/Inputs!$B$16,I13) -> -0.0013626579 | N13: 0.065 | O13: 0.000125 | P13: =D13-('2 Hedge ratio'!$B$6+'2 Hedge ratio'!$B$5*E13) -> 0.0003041898 | Q13: =D13-('5 Re-specification'!$B$7+'5 Re-specification'!$B$5*E13+'5 Re-specification'!$B$6*F13) -> 0.0029117763 | R13: =MIN(F13,Inputs!$B$9) -> 8 | S13: =IF(AND(F13>=1,R13>=Inputs!$B$10),INDEX(LINEST(OFFSET(D13,-R13,0,R13,1),OFFSET(E13,-R13,0,R13,2)),1,1),"") | T13: =IF(AND(F13>=1,R13>=Inputs!$B$10),INDEX(LINEST(OFFSET(D13,-R13,0,R13,1),OFFSET(E13,-R13,0,R13,2)),1,2),"") | U13: =IF(AND(F13>=1,R13>=Inputs!$B$10),INDEX(LINEST(OFFSET(D13,-R13,0,R13,1),OFFSET(E13,-R13,0,R13,2)),1,3),"") | V13: =IF(AND(F13>=1,R13>=Inputs!$B$10),SQRT(SUMPRODUCT((OFFSET(D13,-R13,0,R13,1)-U13-T13*OFFSET(E13,-R13,0,R13,1)-S13*OFFSET(F13,-R13,0,R13,1))^2)/(R13-3)),"") | W13: =IF(AND(F13>=1,R13>=Inputs!$B$10),(D13-U13-T13*E13-S13*F13)/V13,"") | X13: =IF(AB12<>0,AC12+1,0) -> 0 | Y13: =IF(W13="",0,IF(AND(AB12<>0,OR(ABS(W13)>Inputs!$B$7,X13>=Inputs!$B$8,ABS(W13)<Inputs!$B$6)),1,0)) -> 0 | Z13: =IF(Y13=1,0,AB12) -> 0 | AA13: =IF(W13="",0,IF(AND(Z13=0,ABS(W13)>Inputs!$B$5,ABS(W13)<=Inputs!$B$7),1,0)) -> 0 | AB13: =IF(W13="",0,IF(AA13=1,-SIGN(W13),Z13)) -> 0 | AC13: =IF(W13="",0,IF(AA13=1,0,IF(Y13=1,0,X13))) -> 0 | AD13: =IF(AB13=0,0,IF(AB12=AB13,AD12,T13)) -> 0 | AE13: =AB13-AB12 -> 0 | AF13: =-AD13*AB13 -> 0 | AG13: =AF13-AF12 -> 0 | AH13: =MAX(AE13,0)*(Inputs!$B$17+Inputs!$B$18+Inputs!$B$19)+MAX(-AE13,0)*(O13+Inputs!$B$18+Inputs!$B$19)+IF(AND(K13=1,AB13<>0),(Inputs!$B$17+Inputs!$B$18+Inputs!$B$19)+(O13+Inputs!$B$18+Inputs!$B$19),0)+MAX(AG13,0)*(Inputs!$B$20+Inputs!$B$22+Inputs!$B$23)+MAX(-AG13,0)*(Inputs!$B$21+Inputs!$B$22+Inputs!$B$23) -> 0 | AI13: =AB12*(M13-AD12*J13)+AB12*AD12*N13/Inputs!$B$16-AH13 -> 0 | AJ13: =MAX(AE13,0)*(Inputs!$B$17+Inputs!$B$24+Inputs!$B$25)+MAX(-AE13,0)*(O13+Inputs!$B$24+Inputs!$B$25)+IF(AND(K13=1,AB13<>0),(Inputs!$B$17+Inputs!$B$24+Inputs!$B$25)+(O13+Inputs!$B$24+Inputs!$B$25),0)+MAX(AG13,0)*(Inputs!$B$20+Inputs!$B$26+Inputs!$B$27)+MAX(-AG13,0)*(Inputs!$B$21+Inputs!$B$26+Inputs!$B$27) -> 0 | AK13: =AB12*(M13-AD12*J13)+AB12*AD12*(N13+Inputs!$B$14)/Inputs!$B$16-AJ13 -> 0 | AL13: =IF(AP12<>0,AQ12+1,0) -> 0 | AM13: =IF(W13="",0,IF(AND(AP12<>0,OR(ABS(W13)>Inputs!$B$7,AL13>=Inputs!$B$8,ABS(W13)<Inputs!$B$6)),1,0)) -> 0 | AN13: =IF(AM13=1,0,AP12) -> 0 | AO13: =IF(W13="",0,IF(AND(AN13=0,ABS(W13)>Inputs!$B$5,ABS(W13)<=Inputs!$B$7,W13>0),1,0)) -> 0 | AP13: =IF(W13="",0,IF(AO13=1,-SIGN(W13),AN13)) -> 0 | AQ13: =IF(W13="",0,IF(AO13=1,0,IF(AM13=1,0,AL13))) -> 0 | AR13: =IF(AP13=0,0,IF(AP12=AP13,AR12,T13)) -> 0 | AS13: =AP13-AP12 -> 0 | AT13: =-AR13*AP13 -> 0 | AU13: =AT13-AT12 -> 0 | AV13: =MAX(AS13,0)*(Inputs!$B$17+Inputs!$B$18+Inputs!$B$19)+MAX(-AS13,0)*(O13+Inputs!$B$18+Inputs!$B$19)+IF(AND(K13=1,AP13<>0),(Inputs!$B$17+Inputs!$B$18+Inputs!$B$19)+(O13+Inputs!$B$18+Inputs!$B$19),0)+MAX(AU13,0)*(Inputs!$B$20+Inputs!$B$22+Inputs!$B$23)+MAX(-AU13,0)*(Inputs!$B$21+Inputs!$B$22+Inputs!$B$23) -> 0 | AW13: =AP12*(M13-AR12*J13)+AP12*AR12*N13/Inputs!$B$16-AV13 -> 0 | AX13: =AW13-IF(AP12<>0,0.75*AR12*(Inputs!$B$13-N13)/Inputs!$B$16,0) -> 0 | AY13: =MAX(AS13,0)*(Inputs!$B$17+Inputs!$B$18+Inputs!$B$19)+MAX(-AS13,0)*(O13+Inputs!$B$18+Inputs!$B$19)+IF(AND(K13=1,AP13<>0),(Inputs!$B$17+Inputs!$B$18+Inputs!$B$19)+(O13+Inputs!$B$18+Inputs!$B$19),0) -> 0 | AZ13: =AP12*M13-AY13 -> 0 | BA13: =BA12+AI13 -> 0 | BB13: =MAX(BB12,BA13) -> 0 | BC13: =BA13-BB13 -> 0 | BD13: =A14-A13 -> 3
A14: 45061 | B14: 18408 | C14: 201.38 | D14: =LN(B14) -> 9.8205406 | E14: =LN(C14) -> 5.3051937 | F14: 9 | G14: 10 | H14: =D14-E14 -> 4.515347 | I14: =D14-D13 -> 0.0040280932 | J14: =E14-E13 -> 0.0063764289 | K14: 0 | L14: 0 | M14: =IF(L14=1,J14-Carry!$B$9/Inputs!$B$16,I14) -> 0.0040280932 | N14: 0.065 | O14: 0.000125 | P14: =D14-('2 Hedge ratio'!$B$6+'2 Hedge ratio'!$B$5*E14) -> -0.0015093342 | Q14: =D14-('5 Re-specification'!$B$7+'5 Re-specification'!$B$5*E14+'5 Re-specification'!$B$6*F14) -> 0.00062769367 | R14: =MIN(F14,Inputs!$B$9) -> 9 | S14: =IF(AND(F14>=1,R14>=Inputs!$B$10),INDEX(LINEST(OFFSET(D14,-R14,0,R14,1),OFFSET(E14,-R14,0,R14,2)),1,1),"") | T14: =IF(AND(F14>=1,R14>=Inputs!$B$10),INDEX(LINEST(OFFSET(D14,-R14,0,R14,1),OFFSET(E14,-R14,0,R14,2)),1,2),"") | U14: =IF(AND(F14>=1,R14>=Inputs!$B$10),INDEX(LINEST(OFFSET(D14,-R14,0,R14,1),OFFSET(E14,-R14,0,R14,2)),1,3),"") | V14: =IF(AND(F14>=1,R14>=Inputs!$B$10),SQRT(SUMPRODUCT((OFFSET(D14,-R14,0,R14,1)-U14-T14*OFFSET(E14,-R14,0,R14,1)-S14*OFFSET(F14,-R14,0,R14,1))^2)/(R14-3)),"") | W14: =IF(AND(F14>=1,R14>=Inputs!$B$10),(D14-U14-T14*E14-S14*F14)/V14,"") | X14: =IF(AB13<>0,AC13+1,0) -> 0 | Y14: =IF(W14="",0,IF(AND(AB13<>0,OR(ABS(W14)>Inputs!$B$7,X14>=Inputs!$B$8,ABS(W14)<Inputs!$B$6)),1,0)) -> 0 | Z14: =IF(Y14=1,0,AB13) -> 0 | AA14: =IF(W14="",0,IF(AND(Z14=0,ABS(W14)>Inputs!$B$5,ABS(W14)<=Inputs!$B$7),1,0)) -> 0 | AB14: =IF(W14="",0,IF(AA14=1,-SIGN(W14),Z14)) -> 0 | AC14: =IF(W14="",0,IF(AA14=1,0,IF(Y14=1,0,X14))) -> 0 | AD14: =IF(AB14=0,0,IF(AB13=AB14,AD13,T14)) -> 0 | AE14: =AB14-AB13 -> 0 | AF14: =-AD14*AB14 -> 0 | AG14: =AF14-AF13 -> 0 | AH14: =MAX(AE14,0)*(Inputs!$B$17+Inputs!$B$18+Inputs!$B$19)+MAX(-AE14,0)*(O14+Inputs!$B$18+Inputs!$B$19)+IF(AND(K14=1,AB14<>0),(Inputs!$B$17+Inputs!$B$18+Inputs!$B$19)+(O14+Inputs!$B$18+Inputs!$B$19),0)+MAX(AG14,0)*(Inputs!$B$20+Inputs!$B$22+Inputs!$B$23)+MAX(-AG14,0)*(Inputs!$B$21+Inputs!$B$22+Inputs!$B$23) -> 0 | AI14: =AB13*(M14-AD13*J14)+AB13*AD13*N14/Inputs!$B$16-AH14 -> 0 | AJ14: =MAX(AE14,0)*(Inputs!$B$17+Inputs!$B$24+Inputs!$B$25)+MAX(-AE14,0)*(O14+Inputs!$B$24+Inputs!$B$25)+IF(AND(K14=1,AB14<>0),(Inputs!$B$17+Inputs!$B$24+Inputs!$B$25)+(O14+Inputs!$B$24+Inputs!$B$25),0)+MAX(AG14,0)*(Inputs!$B$20+Inputs!$B$26+Inputs!$B$27)+MAX(-AG14,0)*(Inputs!$B$21+Inputs!$B$26+Inputs!$B$27) -> 0 | AK14: =AB13*(M14-AD13*J14)+AB13*AD13*(N14+Inputs!$B$14)/Inputs!$B$16-AJ14 -> 0 | AL14: =IF(AP13<>0,AQ13+1,0) -> 0 | AM14: =IF(W14="",0,IF(AND(AP13<>0,OR(ABS(W14)>Inputs!$B$7,AL14>=Inputs!$B$8,ABS(W14)<Inputs!$B$6)),1,0)) -> 0 | AN14: =IF(AM14=1,0,AP13) -> 0 | AO14: =IF(W14="",0,IF(AND(AN14=0,ABS(W14)>Inputs!$B$5,ABS(W14)<=Inputs!$B$7,W14>0),1,0)) -> 0 | AP14: =IF(W14="",0,IF(AO14=1,-SIGN(W14),AN14)) -> 0 | AQ14: =IF(W14="",0,IF(AO14=1,0,IF(AM14=1,0,AL14))) -> 0 | AR14: =IF(AP14=0,0,IF(AP13=AP14,AR13,T14)) -> 0 | AS14: =AP14-AP13 -> 0 | AT14: =-AR14*AP14 -> 0 | AU14: =AT14-AT13 -> 0 | AV14: =MAX(AS14,0)*(Inputs!$B$17+Inputs!$B$18+Inputs!$B$19)+MAX(-AS14,0)*(O14+Inputs!$B$18+Inputs!$B$19)+IF(AND(K14=1,AP14<>0),(Inputs!$B$17+Inputs!$B$18+Inputs!$B$19)+(O14+Inputs!$B$18+Inputs!$B$19),0)+MAX(AU14,0)*(Inputs!$B$20+Inputs!$B$22+Inputs!$B$23)+MAX(-AU14,0)*(Inputs!$B$21+Inputs!$B$22+Inputs!$B$23) -> 0 | AW14: =AP13*(M14-AR13*J14)+AP13*AR13*N14/Inputs!$B$16-AV14 -> 0 | AX14: =AW14-IF(AP13<>0,0.75*AR13*(Inputs!$B$13-N14)/Inputs!$B$16,0) -> 0 | AY14: =MAX(AS14,0)*(Inputs!$B$17+Inputs!$B$18+Inputs!$B$19)+MAX(-AS14,0)*(O14+Inputs!$B$18+Inputs!$B$19)+IF(AND(K14=1,AP14<>0),(Inputs!$B$17+Inputs!$B$18+Inputs!$B$19)+(O14+Inputs!$B$18+Inputs!$B$19),0) -> 0 | AZ14: =AP13*M14-AY14 -> 0 | BA14: =BA13+AI14 -> 0 | BB14: =MAX(BB13,BA14) -> 0 | BC14: =BA14-BB14 -> 0 | BD14: =A15-A14 -> 1
A15: 45062 | B15: 18326.1 | C15: 200.5 | D15: =LN(B15) -> 9.8160816 | E15: =LN(C15) -> 5.3008142 | F15: 10 | G15: 9 | H15: =D15-E15 -> 4.5152673 | I15: =D15-D14 -> -0.0044590795 | J15: =E15-E14 -> -0.0043794237 | K15: 0 | L15: 0 | M15: =IF(L15=1,J15-Carry!$B$9/Inputs!$B$16,I15) -> -0.0044590795 | N15: 0.065 | O15: 0.000125 | P15: =D15-('2 Hedge ratio'!$B$6+'2 Hedge ratio'!$B$5*E15) -> -0.0019563064 | Q15: =D15-('5 Re-specification'!$B$7+'5 Re-specification'!$B$5*E15+'5 Re-specification'!$B$6*F15) -> 0.00057969541 | R15: =MIN(F15,Inputs!$B$9) -> 10 | S15: =IF(AND(F15>=1,R15>=Inputs!$B$10),INDEX(LINEST(OFFSET(D15,-R15,0,R15,1),OFFSET(E15,-R15,0,R15,2)),1,1),"") | T15: =IF(AND(F15>=1,R15>=Inputs!$B$10),INDEX(LINEST(OFFSET(D15,-R15,0,R15,1),OFFSET(E15,-R15,0,R15,2)),1,2),"") | U15: =IF(AND(F15>=1,R15>=Inputs!$B$10),INDEX(LINEST(OFFSET(D15,-R15,0,R15,1),OFFSET(E15,-R15,0,R15,2)),1,3),"") | V15: =IF(AND(F15>=1,R15>=Inputs!$B$10),SQRT(SUMPRODUCT((OFFSET(D15,-R15,0,R15,1)-U15-T15*OFFSET(E15,-R15,0,R15,1)-S15*OFFSET(F15,-R15,0,R15,1))^2)/(R15-3)),"") | W15: =IF(AND(F15>=1,R15>=Inputs!$B$10),(D15-U15-T15*E15-S15*F15)/V15,"") | X15: =IF(AB14<>0,AC14+1,0) -> 0 | Y15: =IF(W15="",0,IF(AND(AB14<>0,OR(ABS(W15)>Inputs!$B$7,X15>=Inputs!$B$8,ABS(W15)<Inputs!$B$6)),1,0)) -> 0 | Z15: =IF(Y15=1,0,AB14) -> 0 | AA15: =IF(W15="",0,IF(AND(Z15=0,ABS(W15)>Inputs!$B$5,ABS(W15)<=Inputs!$B$7),1,0)) -> 0 | AB15: =IF(W15="",0,IF(AA15=1,-SIGN(W15),Z15)) -> 0 | AC15: =IF(W15="",0,IF(AA15=1,0,IF(Y15=1,0,X15))) -> 0 | AD15: =IF(AB15=0,0,IF(AB14=AB15,AD14,T15)) -> 0 | AE15: =AB15-AB14 -> 0 | AF15: =-AD15*AB15 -> 0 | AG15: =AF15-AF14 -> 0 | AH15: =MAX(AE15,0)*(Inputs!$B$17+Inputs!$B$18+Inputs!$B$19)+MAX(-AE15,0)*(O15+Inputs!$B$18+Inputs!$B$19)+IF(AND(K15=1,AB15<>0),(Inputs!$B$17+Inputs!$B$18+Inputs!$B$19)+(O15+Inputs!$B$18+Inputs!$B$19),0)+MAX(AG15,0)*(Inputs!$B$20+Inputs!$B$22+Inputs!$B$23)+MAX(-AG15,0)*(Inputs!$B$21+Inputs!$B$22+Inputs!$B$23) -> 0 | AI15: =AB14*(M15-AD14*J15)+AB14*AD14*N15/Inputs!$B$16-AH15 -> 0 | AJ15: =MAX(AE15,0)*(Inputs!$B$17+Inputs!$B$24+Inputs!$B$25)+MAX(-AE15,0)*(O15+Inputs!$B$24+Inputs!$B$25)+IF(AND(K15=1,AB15<>0),(Inputs!$B$17+Inputs!$B$24+Inputs!$B$25)+(O15+Inputs!$B$24+Inputs!$B$25),0)+MAX(AG15,0)*(Inputs!$B$20+Inputs!$B$26+Inputs!$B$27)+MAX(-AG15,0)*(Inputs!$B$21+Inputs!$B$26+Inputs!$B$27) -> 0 | AK15: =AB14*(M15-AD14*J15)+AB14*AD14*(N15+Inputs!$B$14)/Inputs!$B$16-AJ15 -> 0 | AL15: =IF(AP14<>0,AQ14+1,0) -> 0 | AM15: =IF(W15="",0,IF(AND(AP14<>0,OR(ABS(W15)>Inputs!$B$7,AL15>=Inputs!$B$8,ABS(W15)<Inputs!$B$6)),1,0)) -> 0 | AN15: =IF(AM15=1,0,AP14) -> 0 | AO15: =IF(W15="",0,IF(AND(AN15=0,ABS(W15)>Inputs!$B$5,ABS(W15)<=Inputs!$B$7,W15>0),1,0)) -> 0 | AP15: =IF(W15="",0,IF(AO15=1,-SIGN(W15),AN15)) -> 0 | AQ15: =IF(W15="",0,IF(AO15=1,0,IF(AM15=1,0,AL15))) -> 0 | AR15: =IF(AP15=0,0,IF(AP14=AP15,AR14,T15)) -> 0 | AS15: =AP15-AP14 -> 0 | AT15: =-AR15*AP15 -> 0 | AU15: =AT15-AT14 -> 0 | AV15: =MAX(AS15,0)*(Inputs!$B$17+Inputs!$B$18+Inputs!$B$19)+MAX(-AS15,0)*(O15+Inputs!$B$18+Inputs!$B$19)+IF(AND(K15=1,AP15<>0),(Inputs!$B$17+Inputs!$B$18+Inputs!$B$19)+(O15+Inputs!$B$18+Inputs!$B$19),0)+MAX(AU15,0)*(Inputs!$B$20+Inputs!$B$22+Inputs!$B$23)+MAX(-AU15,0)*(Inputs!$B$21+Inputs!$B$22+Inputs!$B$23) -> 0 | AW15: =AP14*(M15-AR14*J15)+AP14*AR14*N15/Inputs!$B$16-AV15 -> 0 | AX15: =AW15-IF(AP14<>0,0.75*AR14*(Inputs!$B$13-N15)/Inputs!$B$16,0) -> 0 | AY15: =MAX(AS15,0)*(Inputs!$B$17+Inputs!$B$18+Inputs!$B$19)+MAX(-AS15,0)*(O15+Inputs!$B$18+Inputs!$B$19)+IF(AND(K15=1,AP15<>0),(Inputs!$B$17+Inputs!$B$18+Inputs!$B$19)+(O15+Inputs!$B$18+Inputs!$B$19),0) -> 0 | AZ15: =AP14*M15-AY15 -> 0 | BA15: =BA14+AI15 -> 0 | BB15: =MAX(BB14,BA15) -> 0 | BC15: =BA15-BB15 -> 0 | BD15: =A16-A15 -> 1
A16: 45063 | B16: 18231.95 | C16: 199.9 | D16: =LN(B16) -> 9.8109308 | E16: =LN(C16) -> 5.2978172 | F16: 11 | G16: 8 | H16: =D16-E16 -> 4.5131136 | I16: =D16-D15 -> -0.0051507237 | J16: =E16-E15 -> -0.0029970052 | K16: 0 | L16: 0 | M16: =IF(L16=1,J16-Carry!$B$9/Inputs!$B$16,I16) -> -0.0051507237 | N16: 0.065 | O16: 0.000125 | P16: =D16-('2 Hedge ratio'!$B$6+'2 Hedge ratio'!$B$5*E16) -> -0.0043613934 | Q16: =D16-('5 Re-specification'!$B$7+'5 Re-specification'!$B$5*E16+'5 Re-specification'!$B$6*F16) -> -0.0015381762 | R16: =MIN(F16,Inputs!$B$9) -> 11 | S16: =IF(AND(F16>=1,R16>=Inputs!$B$10),INDEX(LINEST(OFFSET(D16,-R16,0,R16,1),OFFSET(E16,-R16,0,R16,2)),1,1),"") | T16: =IF(AND(F16>=1,R16>=Inputs!$B$10),INDEX(LINEST(OFFSET(D16,-R16,0,R16,1),OFFSET(E16,-R16,0,R16,2)),1,2),"") | U16: =IF(AND(F16>=1,R16>=Inputs!$B$10),INDEX(LINEST(OFFSET(D16,-R16,0,R16,1),OFFSET(E16,-R16,0,R16,2)),1,3),"") | V16: =IF(AND(F16>=1,R16>=Inputs!$B$10),SQRT(SUMPRODUCT((OFFSET(D16,-R16,0,R16,1)-U16-T16*OFFSET(E16,-R16,0,R16,1)-S16*OFFSET(F16,-R16,0,R16,1))^2)/(R16-3)),"") | W16: =IF(AND(F16>=1,R16>=Inputs!$B$10),(D16-U16-T16*E16-S16*F16)/V16,"") | X16: =IF(AB15<>0,AC15+1,0) -> 0 | Y16: =IF(W16="",0,IF(AND(AB15<>0,OR(ABS(W16)>Inputs!$B$7,X16>=Inputs!$B$8,ABS(W16)<Inputs!$B$6)),1,0)) -> 0 | Z16: =IF(Y16=1,0,AB15) -> 0 | AA16: =IF(W16="",0,IF(AND(Z16=0,ABS(W16)>Inputs!$B$5,ABS(W16)<=Inputs!$B$7),1,0)) -> 0 | AB16: =IF(W16="",0,IF(AA16=1,-SIGN(W16),Z16)) -> 0 | AC16: =IF(W16="",0,IF(AA16=1,0,IF(Y16=1,0,X16))) -> 0 | AD16: =IF(AB16=0,0,IF(AB15=AB16,AD15,T16)) -> 0 | AE16: =AB16-AB15 -> 0 | AF16: =-AD16*AB16 -> 0 | AG16: =AF16-AF15 -> 0 | AH16: =MAX(AE16,0)*(Inputs!$B$17+Inputs!$B$18+Inputs!$B$19)+MAX(-AE16,0)*(O16+Inputs!$B$18+Inputs!$B$19)+IF(AND(K16=1,AB16<>0),(Inputs!$B$17+Inputs!$B$18+Inputs!$B$19)+(O16+Inputs!$B$18+Inputs!$B$19),0)+MAX(AG16,0)*(Inputs!$B$20+Inputs!$B$22+Inputs!$B$23)+MAX(-AG16,0)*(Inputs!$B$21+Inputs!$B$22+Inputs!$B$23) -> 0 | AI16: =AB15*(M16-AD15*J16)+AB15*AD15*N16/Inputs!$B$16-AH16 -> 0 | AJ16: =MAX(AE16,0)*(Inputs!$B$17+Inputs!$B$24+Inputs!$B$25)+MAX(-AE16,0)*(O16+Inputs!$B$24+Inputs!$B$25)+IF(AND(K16=1,AB16<>0),(Inputs!$B$17+Inputs!$B$24+Inputs!$B$25)+(O16+Inputs!$B$24+Inputs!$B$25),0)+MAX(AG16,0)*(Inputs!$B$20+Inputs!$B$26+Inputs!$B$27)+MAX(-AG16,0)*(Inputs!$B$21+Inputs!$B$26+Inputs!$B$27) -> 0 | AK16: =AB15*(M16-AD15*J16)+AB15*AD15*(N16+Inputs!$B$14)/Inputs!$B$16-AJ16 -> 0 | AL16: =IF(AP15<>0,AQ15+1,0) -> 0 | AM16: =IF(W16="",0,IF(AND(AP15<>0,OR(ABS(W16)>Inputs!$B$7,AL16>=Inputs!$B$8,ABS(W16)<Inputs!$B$6)),1,0)) -> 0 | AN16: =IF(AM16=1,0,AP15) -> 0 | AO16: =IF(W16="",0,IF(AND(AN16=0,ABS(W16)>Inputs!$B$5,ABS(W16)<=Inputs!$B$7,W16>0),1,0)) -> 0 | AP16: =IF(W16="",0,IF(AO16=1,-SIGN(W16),AN16)) -> 0 | AQ16: =IF(W16="",0,IF(AO16=1,0,IF(AM16=1,0,AL16))) -> 0 | AR16: =IF(AP16=0,0,IF(AP15=AP16,AR15,T16)) -> 0 | AS16: =AP16-AP15 -> 0 | AT16: =-AR16*AP16 -> 0 | AU16: =AT16-AT15 -> 0 | AV16: =MAX(AS16,0)*(Inputs!$B$17+Inputs!$B$18+Inputs!$B$19)+MAX(-AS16,0)*(O16+Inputs!$B$18+Inputs!$B$19)+IF(AND(K16=1,AP16<>0),(Inputs!$B$17+Inputs!$B$18+Inputs!$B$19)+(O16+Inputs!$B$18+Inputs!$B$19),0)+MAX(AU16,0)*(Inputs!$B$20+Inputs!$B$22+Inputs!$B$23)+MAX(-AU16,0)*(Inputs!$B$21+Inputs!$B$22+Inputs!$B$23) -> 0 | AW16: =AP15*(M16-AR15*J16)+AP15*AR15*N16/Inputs!$B$16-AV16 -> 0 | AX16: =AW16-IF(AP15<>0,0.75*AR15*(Inputs!$B$13-N16)/Inputs!$B$16,0) -> 0 | AY16: =MAX(AS16,0)*(Inputs!$B$17+Inputs!$B$18+Inputs!$B$19)+MAX(-AS16,0)*(O16+Inputs!$B$18+Inputs!$B$19)+IF(AND(K16=1,AP16<>0),(Inputs!$B$17+Inputs!$B$18+Inputs!$B$19)+(O16+Inputs!$B$18+Inputs!$B$19),0) -> 0 | AZ16: =AP15*M16-AY16 -> 0 | BA16: =BA15+AI16 -> 0 | BB16: =MAX(BB15,BA16) -> 0 | BC16: =BA16-BB16 -> 0 | BD16: =A17-A16 -> 1
A17: 45064 | B17: 18180 | C17: 199.19 | D17: =LN(B17) -> 9.8080774 | E17: =LN(C17) -> 5.2942591 | F17: 12 | G17: 7 | H17: =D17-E17 -> 4.5138182 | I17: =D17-D16 -> -0.0028534608 | J17: =E17-E16 -> -0.0035580984 | K17: 0 | L17: 0 | M17: =IF(L17=1,J17-Carry!$B$9/Inputs!$B$16,I17) -> -0.0028534608 | N17: 0.065 | O17: 0.000125 | P17: =D17-('2 Hedge ratio'!$B$6+'2 Hedge ratio'!$B$5*E17) -> -0.003955185 | Q17: =D17-('5 Re-specification'!$B$7+'5 Re-specification'!$B$5*E17+'5 Re-specification'!$B$6*F17) -> -0.00079939204 | R17: =MIN(F17,Inputs!$B$9) -> 12 | S17: =IF(AND(F17>=1,R17>=Inputs!$B$10),INDEX(LINEST(OFFSET(D17,-R17,0,R17,1),OFFSET(E17,-R17,0,R17,2)),1,1),"") | T17: =IF(AND(F17>=1,R17>=Inputs!$B$10),INDEX(LINEST(OFFSET(D17,-R17,0,R17,1),OFFSET(E17,-R17,0,R17,2)),1,2),"") | U17: =IF(AND(F17>=1,R17>=Inputs!$B$10),INDEX(LINEST(OFFSET(D17,-R17,0,R17,1),OFFSET(E17,-R17,0,R17,2)),1,3),"") | V17: =IF(AND(F17>=1,R17>=Inputs!$B$10),SQRT(SUMPRODUCT((OFFSET(D17,-R17,0,R17,1)-U17-T17*OFFSET(E17,-R17,0,R17,1)-S17*OFFSET(F17,-R17,0,R17,1))^2)/(R17-3)),"") | W17: =IF(AND(F17>=1,R17>=Inputs!$B$10),(D17-U17-T17*E17-S17*F17)/V17,"") | X17: =IF(AB16<>0,AC16+1,0) -> 0 | Y17: =IF(W17="",0,IF(AND(AB16<>0,OR(ABS(W17)>Inputs!$B$7,X17>=Inputs!$B$8,ABS(W17)<Inputs!$B$6)),1,0)) -> 0 | Z17: =IF(Y17=1,0,AB16) -> 0 | AA17: =IF(W17="",0,IF(AND(Z17=0,ABS(W17)>Inputs!$B$5,ABS(W17)<=Inputs!$B$7),1,0)) -> 0 | AB17: =IF(W17="",0,IF(AA17=1,-SIGN(W17),Z17)) -> 0 | AC17: =IF(W17="",0,IF(AA17=1,0,IF(Y17=1,0,X17))) -> 0 | AD17: =IF(AB17=0,0,IF(AB16=AB17,AD16,T17)) -> 0 | AE17: =AB17-AB16 -> 0 | AF17: =-AD17*AB17 -> 0 | AG17: =AF17-AF16 -> 0 | AH17: =MAX(AE17,0)*(Inputs!$B$17+Inputs!$B$18+Inputs!$B$19)+MAX(-AE17,0)*(O17+Inputs!$B$18+Inputs!$B$19)+IF(AND(K17=1,AB17<>0),(Inputs!$B$17+Inputs!$B$18+Inputs!$B$19)+(O17+Inputs!$B$18+Inputs!$B$19),0)+MAX(AG17,0)*(Inputs!$B$20+Inputs!$B$22+Inputs!$B$23)+MAX(-AG17,0)*(Inputs!$B$21+Inputs!$B$22+Inputs!$B$23) -> 0 | AI17: =AB16*(M17-AD16*J17)+AB16*AD16*N17/Inputs!$B$16-AH17 -> 0 | AJ17: =MAX(AE17,0)*(Inputs!$B$17+Inputs!$B$24+Inputs!$B$25)+MAX(-AE17,0)*(O17+Inputs!$B$24+Inputs!$B$25)+IF(AND(K17=1,AB17<>0),(Inputs!$B$17+Inputs!$B$24+Inputs!$B$25)+(O17+Inputs!$B$24+Inputs!$B$25),0)+MAX(AG17,0)*(Inputs!$B$20+Inputs!$B$26+Inputs!$B$27)+MAX(-AG17,0)*(Inputs!$B$21+Inputs!$B$26+Inputs!$B$27) -> 0 | AK17: =AB16*(M17-AD16*J17)+AB16*AD16*(N17+Inputs!$B$14)/Inputs!$B$16-AJ17 -> 0 | AL17: =IF(AP16<>0,AQ16+1,0) -> 0 | AM17: =IF(W17="",0,IF(AND(AP16<>0,OR(ABS(W17)>Inputs!$B$7,AL17>=Inputs!$B$8,ABS(W17)<Inputs!$B$6)),1,0)) -> 0 | AN17: =IF(AM17=1,0,AP16) -> 0 | AO17: =IF(W17="",0,IF(AND(AN17=0,ABS(W17)>Inputs!$B$5,ABS(W17)<=Inputs!$B$7,W17>0),1,0)) -> 0 | AP17: =IF(W17="",0,IF(AO17=1,-SIGN(W17),AN17)) -> 0 | AQ17: =IF(W17="",0,IF(AO17=1,0,IF(AM17=1,0,AL17))) -> 0 | AR17: =IF(AP17=0,0,IF(AP16=AP17,AR16,T17)) -> 0 | AS17: =AP17-AP16 -> 0 | AT17: =-AR17*AP17 -> 0 | AU17: =AT17-AT16 -> 0 | AV17: =MAX(AS17,0)*(Inputs!$B$17+Inputs!$B$18+Inputs!$B$19)+MAX(-AS17,0)*(O17+Inputs!$B$18+Inputs!$B$19)+IF(AND(K17=1,AP17<>0),(Inputs!$B$17+Inputs!$B$18+Inputs!$B$19)+(O17+Inputs!$B$18+Inputs!$B$19),0)+MAX(AU17,0)*(Inputs!$B$20+Inputs!$B$22+Inputs!$B$23)+MAX(-AU17,0)*(Inputs!$B$21+Inputs!$B$22+Inputs!$B$23) -> 0 | AW17: =AP16*(M17-AR16*J17)+AP16*AR16*N17/Inputs!$B$16-AV17 -> 0 | AX17: =AW17-IF(AP16<>0,0.75*AR16*(Inputs!$B$13-N17)/Inputs!$B$16,0) -> 0 | AY17: =MAX(AS17,0)*(Inputs!$B$17+Inputs!$B$18+Inputs!$B$19)+MAX(-AS17,0)*(O17+Inputs!$B$18+Inputs!$B$19)+IF(AND(K17=1,AP17<>0),(Inputs!$B$17+Inputs!$B$18+Inputs!$B$19)+(O17+Inputs!$B$18+Inputs!$B$19),0) -> 0 | AZ17: =AP16*M17-AY17 -> 0 | BA17: =BA16+AI17 -> 0 | BB17: =MAX(BB16,BA17) -> 0 | BC17: =BA17-BB17 -> 0 | BD17: =A18-A17 -> 1
... A814: 46240 | B814: 24745 | C814: 280.5 | D814: =LN(B814) -> 10.116379 | E814: =LN(C814) -> 5.6365737 | F814: 809 | G814: 19 | H814: =D814-E814 -> 4.479805 | I814: =D814-D813 -> 0.0038465479 | J814: =E814-E813 -> 0.0017841218 | K814: 0 | L814: 0 | M814: =IF(L814=1,J814-Carry!$B$9/Inputs!$B$16,I814) -> 0.0038465479 | N814: 0.0525 | O814: 0.0005 | P814: =D814-('2 Hedge ratio'!$B$6+'2 Hedge ratio'!$B$5*E814) -> -0.0092573739 | Q814: =D814-('5 Re-specification'!$B$7+'5 Re-specification'!$B$5*E814+'5 Re-specification'!$B$6*F814) -> 0.0020334366 | R814: =MIN(F814,Inputs!$B$9) -> 250 | S814: =IF(AND(F814>=1,R814>=Inputs!$B$10),INDEX(LINEST(OFFSET(D814,-R814,0,R814,1),OFFSET(E814,-R814,0,R814,2)),1,1),"") -> -3.4288913e-05 | T814: =IF(AND(F814>=1,R814>=Inputs!$B$10),INDEX(LINEST(OFFSET(D814,-R814,0,R814,1),OFFSET(E814,-R814,0,R814,2)),1,2),"") -> 1.0180785 | U814: =IF(AND(F814>=1,R814>=Inputs!$B$10),INDEX(LINEST(OFFSET(D814,-R814,0,R814,1),OFFSET(E814,-R814,0,R814,2)),1,3),"") -> 4.4047353 | V814: =IF(AND(F814>=1,R814>=Inputs!$B$10),SQRT(SUMPRODUCT((OFFSET(D814,-R814,0,R814,1)-U814-T814*OFFSET(E814,-R814,0,R814,1)-S814*OFFSET(F814,-R814,0,R814,1))^2)/(R814-3)),"") -> 0.0023337437 | W814: =IF(AND(F814>=1,R814>=Inputs!$B$10),(D814-U814-T814*E814-S814*F814)/V814,"") -> 0.38935859 | X814: =IF(AB813<>0,AC813+1,0) -> 0 | Y814: =IF(W814="",0,IF(AND(AB813<>0,OR(ABS(W814)>Inputs!$B$7,X814>=Inputs!$B$8,ABS(W814)<Inputs!$B$6)),1,0)) -> 0 | Z814: =IF(Y814=1,0,AB813) -> 0 | AA814: =IF(W814="",0,IF(AND(Z814=0,ABS(W814)>Inputs!$B$5,ABS(W814)<=Inputs!$B$7),1,0)) -> 0 | AB814: =IF(W814="",0,IF(AA814=1,-SIGN(W814),Z814)) -> 0 | AC814: =IF(W814="",0,IF(AA814=1,0,IF(Y814=1,0,X814))) -> 0 | AD814: =IF(AB814=0,0,IF(AB813=AB814,AD813,T814)) -> 0 | AE814: =AB814-AB813 -> 0 | AF814: =-AD814*AB814 -> 0 | AG814: =AF814-AF813 -> 0 | AH814: =MAX(AE814,0)*(Inputs!$B$17+Inputs!$B$18+Inputs!$B$19)+MAX(-AE814,0)*(O814+Inputs!$B$18+Inputs!$B$19)+IF(AND(K814=1,AB814<>0),(Inputs!$B$17+Inputs!$B$18+Inputs!$B$19)+(O814+Inputs!$B$18+Inputs!$B$19),0)+MAX(AG814,0)*(Inputs!$B$20+Inputs!$B$22+Inputs!$B$23)+MAX(-AG814,0)*(Inputs!$B$21+Inputs!$B$22+Inputs!$B$23) -> 0 | AI814: =AB813*(M814-AD813*J814)+AB813*AD813*N814/Inputs!$B$16-AH814 -> 0 | AJ814: =MAX(AE814,0)*(Inputs!$B$17+Inputs!$B$24+Inputs!$B$25)+MAX(-AE814,0)*(O814+Inputs!$B$24+Inputs!$B$25)+IF(AND(K814=1,AB814<>0),(Inputs!$B$17+Inputs!$B$24+Inputs!$B$25)+(O814+Inputs!$B$24+Inputs!$B$25),0)+MAX(AG814,0)*(Inputs!$B$20+Inputs!$B$26+Inputs!$B$27)+MAX(-AG814,0)*(Inputs!$B$21+Inputs!$B$26+Inputs!$B$27) -> 0 | AK814: =AB813*(M814-AD813*J814)+AB813*AD813*(N814+Inputs!$B$14)/Inputs!$B$16-AJ814 -> 0 | AL814: =IF(AP813<>0,AQ813+1,0) -> 0 | AM814: =IF(W814="",0,IF(AND(AP813<>0,OR(ABS(W814)>Inputs!$B$7,AL814>=Inputs!$B$8,ABS(W814)<Inputs!$B$6)),1,0)) -> 0 | AN814: =IF(AM814=1,0,AP813) -> 0 | AO814: =IF(W814="",0,IF(AND(AN814=0,ABS(W814)>Inputs!$B$5,ABS(W814)<=Inputs!$B$7,W814>0),1,0)) -> 0 | AP814: =IF(W814="",0,IF(AO814=1,-SIGN(W814),AN814)) -> 0 | AQ814: =IF(W814="",0,IF(AO814=1,0,IF(AM814=1,0,AL814))) -> 0 | AR814: =IF(AP814=0,0,IF(AP813=AP814,AR813,T814)) -> 0 | AS814: =AP814-AP813 -> 0 | AT814: =-AR814*AP814 -> 0 | AU814: =AT814-AT813 -> 0 | AV814: =MAX(AS814,0)*(Inputs!$B$17+Inputs!$B$18+Inputs!$B$19)+MAX(-AS814,0)*(O814+Inputs!$B$18+Inputs!$B$19)+IF(AND(K814=1,AP814<>0),(Inputs!$B$17+Inputs!$B$18+Inputs!$B$19)+(O814+Inputs!$B$18+Inputs!$B$19),0)+MAX(AU814,0)*(Inputs!$B$20+Inputs!$B$22+Inputs!$B$23)+MAX(-AU814,0)*(Inputs!$B$21+Inputs!$B$22+Inputs!$B$23) -> 0 | AW814: =AP813*(M814-AR813*J814)+AP813*AR813*N814/Inputs!$B$16-AV814 -> 0 | AX814: =AW814-IF(AP813<>0,0.75*AR813*(Inputs!$B$13-N814)/Inputs!$B$16,0) -> 0 | AY814: =MAX(AS814,0)*(Inputs!$B$17+Inputs!$B$18+Inputs!$B$19)+MAX(-AS814,0)*(O814+Inputs!$B$18+Inputs!$B$19)+IF(AND(K814=1,AP814<>0),(Inputs!$B$17+Inputs!$B$18+Inputs!$B$19)+(O814+Inputs!$B$18+Inputs!$B$19),0) -> 0 | AZ814: =AP813*M814-AY814 -> 0 | BA814: =BA813+AI814 -> 0.016564417 | BB814: =MAX(BB813,BA814) -> 0.026172619 | BC814: =BA814-BB814 -> -0.0096082021 | BD814: =A815-A814 -> 1
A815: 46241 | B815: 24655.7 | C815: 279.7 | D815: =LN(B815) -> 10.112763 | E815: =LN(C815) -> 5.6337176 | F815: 810 | G815: 18 | H815: =D815-E815 -> 4.4790458 | I815: =D815-D814 -> -0.0036153373 | J815: =E815-E814 -> -0.0028561248 | K815: 0 | L815: 0 | M815: =IF(L815=1,J815-Carry!$B$9/Inputs!$B$16,I815) -> -0.0036153373 | N815: 0.0525 | O815: 0.0005 | P815: =D815-('2 Hedge ratio'!$B$6+'2 Hedge ratio'!$B$5*E815) -> -0.010256139 | Q815: =D815-('5 Re-specification'!$B$7+'5 Re-specification'!$B$5*E815+'5 Re-specification'!$B$6*F815) -> 0.0013104979 | R815: =MIN(F815,Inputs!$B$9) -> 250 | S815: =IF(AND(F815>=1,R815>=Inputs!$B$10),INDEX(LINEST(OFFSET(D815,-R815,0,R815,1),OFFSET(E815,-R815,0,R815,2)),1,1),"") -> -3.4527175e-05 | T815: =IF(AND(F815>=1,R815>=Inputs!$B$10),INDEX(LINEST(OFFSET(D815,-R815,0,R815,1),OFFSET(E815,-R815,0,R815,2)),1,2),"") -> 1.0177938 | U815: =IF(AND(F815>=1,R815>=Inputs!$B$10),INDEX(LINEST(OFFSET(D815,-R815,0,R815,1),OFFSET(E815,-R815,0,R815,2)),1,3),"") -> 4.4065168 | V815: =IF(AND(F815>=1,R815>=Inputs!$B$10),SQRT(SUMPRODUCT((OFFSET(D815,-R815,0,R815,1)-U815-T815*OFFSET(E815,-R815,0,R815,1)-S815*OFFSET(F815,-R815,0,R815,1))^2)/(R815-3)),"") -> 0.0023286642 | W815: =IF(AND(F815>=1,R815>=Inputs!$B$10),(D815-U815-T815*E815-S815*F815)/V815,"") -> 0.10757894 | X815: =IF(AB814<>0,AC814+1,0) -> 0 | Y815: =IF(W815="",0,IF(AND(AB814<>0,OR(ABS(W815)>Inputs!$B$7,X815>=Inputs!$B$8,ABS(W815)<Inputs!$B$6)),1,0)) -> 0 | Z815: =IF(Y815=1,0,AB814) -> 0 | AA815: =IF(W815="",0,IF(AND(Z815=0,ABS(W815)>Inputs!$B$5,ABS(W815)<=Inputs!$B$7),1,0)) -> 0 | AB815: =IF(W815="",0,IF(AA815=1,-SIGN(W815),Z815)) -> 0 | AC815: =IF(W815="",0,IF(AA815=1,0,IF(Y815=1,0,X815))) -> 0 | AD815: =IF(AB815=0,0,IF(AB814=AB815,AD814,T815)) -> 0 | AE815: =AB815-AB814 -> 0 | AF815: =-AD815*AB815 -> 0 | AG815: =AF815-AF814 -> 0 | AH815: =MAX(AE815,0)*(Inputs!$B$17+Inputs!$B$18+Inputs!$B$19)+MAX(-AE815,0)*(O815+Inputs!$B$18+Inputs!$B$19)+IF(AND(K815=1,AB815<>0),(Inputs!$B$17+Inputs!$B$18+Inputs!$B$19)+(O815+Inputs!$B$18+Inputs!$B$19),0)+MAX(AG815,0)*(Inputs!$B$20+Inputs!$B$22+Inputs!$B$23)+MAX(-AG815,0)*(Inputs!$B$21+Inputs!$B$22+Inputs!$B$23) -> 0 | AI815: =AB814*(M815-AD814*J815)+AB814*AD814*N815/Inputs!$B$16-AH815 -> 0 | AJ815: =MAX(AE815,0)*(Inputs!$B$17+Inputs!$B$24+Inputs!$B$25)+MAX(-AE815,0)*(O815+Inputs!$B$24+Inputs!$B$25)+IF(AND(K815=1,AB815<>0),(Inputs!$B$17+Inputs!$B$24+Inputs!$B$25)+(O815+Inputs!$B$24+Inputs!$B$25),0)+MAX(AG815,0)*(Inputs!$B$20+Inputs!$B$26+Inputs!$B$27)+MAX(-AG815,0)*(Inputs!$B$21+Inputs!$B$26+Inputs!$B$27) -> 0 | AK815: =AB814*(M815-AD814*J815)+AB814*AD814*(N815+Inputs!$B$14)/Inputs!$B$16-AJ815 -> 0 | AL815: =IF(AP814<>0,AQ814+1,0) -> 0 | AM815: =IF(W815="",0,IF(AND(AP814<>0,OR(ABS(W815)>Inputs!$B$7,AL815>=Inputs!$B$8,ABS(W815)<Inputs!$B$6)),1,0)) -> 0 | AN815: =IF(AM815=1,0,AP814) -> 0 | AO815: =IF(W815="",0,IF(AND(AN815=0,ABS(W815)>Inputs!$B$5,ABS(W815)<=Inputs!$B$7,W815>0),1,0)) -> 0 | AP815: =IF(W815="",0,IF(AO815=1,-SIGN(W815),AN815)) -> 0 | AQ815: =IF(W815="",0,IF(AO815=1,0,IF(AM815=1,0,AL815))) -> 0 | AR815: =IF(AP815=0,0,IF(AP814=AP815,AR814,T815)) -> 0 | AS815: =AP815-AP814 -> 0 | AT815: =-AR815*AP815 -> 0 | AU815: =AT815-AT814 -> 0 | AV815: =MAX(AS815,0)*(Inputs!$B$17+Inputs!$B$18+Inputs!$B$19)+MAX(-AS815,0)*(O815+Inputs!$B$18+Inputs!$B$19)+IF(AND(K815=1,AP815<>0),(Inputs!$B$17+Inputs!$B$18+Inputs!$B$19)+(O815+Inputs!$B$18+Inputs!$B$19),0)+MAX(AU815,0)*(Inputs!$B$20+Inputs!$B$22+Inputs!$B$23)+MAX(-AU815,0)*(Inputs!$B$21+Inputs!$B$22+Inputs!$B$23) -> 0 | AW815: =AP814*(M815-AR814*J815)+AP814*AR814*N815/Inputs!$B$16-AV815 -> 0 | AX815: =AW815-IF(AP814<>0,0.75*AR814*(Inputs!$B$13-N815)/Inputs!$B$16,0) -> 0 | AY815: =MAX(AS815,0)*(Inputs!$B$17+Inputs!$B$18+Inputs!$B$19)+MAX(-AS815,0)*(O815+Inputs!$B$18+Inputs!$B$19)+IF(AND(K815=1,AP815<>0),(Inputs!$B$17+Inputs!$B$18+Inputs!$B$19)+(O815+Inputs!$B$18+Inputs!$B$19),0) -> 0 | AZ815: =AP814*M815-AY815 -> 0 | BA815: =BA814+AI815 -> 0.016564417 | BB815: =MAX(BB814,BA815) -> 0.026172619 | BC815: =BA815-BB815 -> -0.0096082021 | BD815: 1

Sheet 1 ADF
A1: Step 1 · Augmented Dickey–Fuller test, built by hand with LINEST
A2: Δy(t) = α + γ·y(t−1) + Σ δi·Δy(t−i) + ε(t). ADF statistic = γ̂ / se(γ̂). H0: γ = 0 (unit root). Lags k chosen by AIC in Python.
A4: Why: cointegration is only defined for series that are individually I(1). Both levels must fail to reject; their differences must reject.
A5: Excel cannot compute the MacKinnon p-value; compare the statistic with the critical value instead. p-values come from Python.
A12: ln F (level) — k = 5 lagged differences
A13: Observations used | B13: =ROWS(C32:C836) -> 805
A14: γ̂ (coefficient on y(t−1)) | B14: =INDEX(LINEST(C32:C836,D32:I836,TRUE(),TRUE()),1,6) -> -0.0070022591
A15: se(γ̂) | B15: =INDEX(LINEST(C32:C836,D32:I836,TRUE(),TRUE()),2,6) -> 0.0030324506
A16: ADF statistic = γ̂ / se(γ̂) | B16: =B14/B15 -> -2.309109 | C16: Python (statsmodels): -2.309
A17: 5% critical value (MacKinnon) | B17: -2.865
A18: Decision | B18: =IF(B16<B17,"Reject H0 → stationary","Fail to reject H0 → unit root") -> Fail to reject H0 → unit root
A22: ln B (level) — k = 0 lagged differences
A23: Observations used | B23: =ROWS(L32:L841) -> 810
A24: γ̂ (coefficient on y(t−1)) | B24: =INDEX(LINEST(L32:L841,M32:M841,TRUE(),TRUE()),1,1) -> -0.0054688291
A25: se(γ̂) | B25: =INDEX(LINEST(L32:L841,M32:M841,TRUE(),TRUE()),2,1) -> 0.0023103072
A26: ADF statistic = γ̂ / se(γ̂) | B26: =B24/B25 -> -2.3671437 | C26: Python (statsmodels): -2.367
A27: 5% critical value (MacKinnon) | B27: -2.865
A28: Decision | B28: =IF(B26<B27,"Reject H0 → stationary","Fail to reject H0 → unit root") -> Fail to reject H0 → unit root
C30: Design matrix: ln F (level) | L30: Design matrix: ln B (level)
C31: Δy(t) | D31: y(t−1) | E31: Δy(t−1) | F31: Δy(t−2) | G31: Δy(t−3) | H31: Δy(t−4) | I31: Δy(t−5) | L31: Δy(t) | M31: y(t−1)
C32: =Panel!D11-Panel!D10 -> 0.0021393418 | D32: =Panel!D10 -> 9.814864 | E32: =Panel!D10-Panel!D9 -> -0.00074819849 | F32: =Panel!D9-Panel!D8 -> 0.010283347 | G32: =Panel!D8-Panel!D7 -> -0.0086168844 | H32: =Panel!D7-Panel!D6 -> 0.0076686356 | I32: =Panel!D6-Panel!D5 -> -0.0030096888 | L32: =Panel!E6-Panel!E5 -> -0.0031330563 | M32: =Panel!E5 -> 5.2892766
C33: =Panel!D12-Panel!D11 -> 0.00087188715 | D33: =Panel!D11 -> 9.8170033 | E33: =Panel!D11-Panel!D10 -> 0.0021393418 | F33: =Panel!D10-Panel!D9 -> -0.00074819849 | G33: =Panel!D9-Panel!D8 -> 0.010283347 | H33: =Panel!D8-Panel!D7 -> -0.0086168844 | I33: =Panel!D7-Panel!D6 -> 0.0076686356 | L33: =Panel!E7-Panel!E6 -> 0.00896867 | M33: =Panel!E6 -> 5.2861436
C34: =Panel!D13-Panel!D12 -> -0.0013626579 | D34: =Panel!D12 -> 9.8178752 | E34: =Panel!D12-Panel!D11 -> 0.00087188715 | F34: =Panel!D11-Panel!D10 -> 0.0021393418 | G34: =Panel!D10-Panel!D9 -> -0.00074819849 | H34: =Panel!D9-Panel!D8 -> 0.010283347 | I34: =Panel!D8-Panel!D7 -> -0.0086168844 | L34: =Panel!E8-Panel!E7 -> -0.0074009148 | M34: =Panel!E7 -> 5.2951122
C35: =Panel!D14-Panel!D13 -> 0.0040280932 | D35: =Panel!D13 -> 9.8165125 | E35: =Panel!D13-Panel!D12 -> -0.0013626579 | F35: =Panel!D12-Panel!D11 -> 0.00087188715 | G35: =Panel!D11-Panel!D10 -> 0.0021393418 | H35: =Panel!D10-Panel!D9 -> -0.00074819849 | I35: =Panel!D9-Panel!D8 -> 0.010283347 | L35: =Panel!E9-Panel!E8 -> 0.010105921 | M35: =Panel!E8 -> 5.2877113
C36: =Panel!D15-Panel!D14 -> -0.0044590795 | D36: =Panel!D14 -> 9.8205406 | E36: =Panel!D14-Panel!D13 -> 0.0040280932 | F36: =Panel!D13-Panel!D12 -> -0.0013626579 | G36: =Panel!D12-Panel!D11 -> 0.00087188715 | H36: =Panel!D11-Panel!D10 -> 0.0021393418 | I36: =Panel!D10-Panel!D9 -> -0.00074819849 | L36: =Panel!E10-Panel!E9 -> -0.00075065686 | M36: =Panel!E9 -> 5.2978172
C37: =Panel!D16-Panel!D15 -> -0.0051507237 | D37: =Panel!D15 -> 9.8160816 | E37: =Panel!D15-Panel!D14 -> -0.0044590795 | F37: =Panel!D14-Panel!D13 -> 0.0040280932 | G37: =Panel!D13-Panel!D12 -> -0.0013626579 | H37: =Panel!D12-Panel!D11 -> 0.00087188715 | I37: =Panel!D11-Panel!D10 -> 0.0021393418 | L37: =Panel!E11-Panel!E10 -> 0.002300231 | M37: =Panel!E10 -> 5.2970666
C38: =Panel!D17-Panel!D16 -> -0.0028534608 | D38: =Panel!D16 -> 9.8109308 | E38: =Panel!D16-Panel!D15 -> -0.0051507237 | F38: =Panel!D15-Panel!D14 -> -0.0044590795 | G38: =Panel!D14-Panel!D13 -> 0.0040280932 | H38: =Panel!D13-Panel!D12 -> -0.0013626579 | I38: =Panel!D12-Panel!D11 -> 0.00087188715 | L38: =Panel!E12-Panel!E11 -> 0.00094855353 | M38: =Panel!E11 -> 5.2993668
C39: =Panel!D18-Panel!D17 -> 0.0028013531 | D39: =Panel!D17 -> 9.8080774 | E39: =Panel!D17-Panel!D16 -> -0.0028534608 | F39: =Panel!D16-Panel!D15 -> -0.0051507237 | G39: =Panel!D15-Panel!D14 -> -0.0044590795 | H39: =Panel!D14-Panel!D13 -> 0.0040280932 | I39: =Panel!D13-Panel!D12 -> -0.0013626579 | L39: =Panel!E13-Panel!E12 -> -0.0014981276 | M39: =Panel!E12 -> 5.3003154
C40: =Panel!D19-Panel!D18 -> 0.0051373489 | D40: =Panel!D18 -> 9.8108787 | E40: =Panel!D18-Panel!D17 -> 0.0028013531 | F40: =Panel!D17-Panel!D16 -> -0.0028534608 | G40: =Panel!D16-Panel!D15 -> -0.0051507237 | H40: =Panel!D15-Panel!D14 -> -0.0044590795 | I40: =Panel!D14-Panel!D13 -> 0.0040280932 | L40: =Panel!E14-Panel!E13 -> 0.0063764289 | M40: =Panel!E13 -> 5.2988172
C41: =Panel!D20-Panel!D19 -> 0.0018101033 | D41: =Panel!D19 -> 9.8160161 | E41: =Panel!D19-Panel!D18 -> 0.0051373489 | F41: =Panel!D18-Panel!D17 -> 0.0028013531 | G41: =Panel!D17-Panel!D16 -> -0.0028534608 | H41: =Panel!D16-Panel!D15 -> -0.0051507237 | I41: =Panel!D15-Panel!D14 -> -0.0044590795 | L41: =Panel!E15-Panel!E14 -> -0.0043794237 | M41: =Panel!E14 -> 5.3051937
C42: =Panel!D21-Panel!D20 -> -0.0031151908 | D42: =Panel!D20 -> 9.8178262 | E42: =Panel!D20-Panel!D19 -> 0.0018101033 | F42: =Panel!D19-Panel!D18 -> 0.0051373489 | G42: =Panel!D18-Panel!D17 -> 0.0028013531 | H42: =Panel!D17-Panel!D16 -> -0.0028534608 | I42: =Panel!D16-Panel!D15 -> -0.0051507237 | L42: =Panel!E16-Panel!E15 -> -0.0029970052 | M42: =Panel!E15 -> 5.3008142
C43: =Panel!D22-Panel!D21 -> 0.0013050876 | D43: =Panel!D21 -> 9.814711 | E43: =Panel!D21-Panel!D20 -> -0.0031151908 | F43: =Panel!D20-Panel!D19 -> 0.0018101033 | G43: =Panel!D19-Panel!D18 -> 0.0051373489 | H43: =Panel!D18-Panel!D17 -> 0.0028013531 | I43: =Panel!D17-Panel!D16 -> -0.0028534608 | L43: =Panel!E17-Panel!E16 -> -0.0035580984 | M43: =Panel!E16 -> 5.2978172
... C836: =Panel!D815-Panel!D814 -> -0.0036153373 | D836: =Panel!D814 -> 10.116379 | E836: =Panel!D814-Panel!D813 -> 0.0038465479 | F836: =Panel!D813-Panel!D812 -> 0.0034135274 | G836: =Panel!D812-Panel!D811 -> -0.0032512424 | H836: =Panel!D811-Panel!D810 -> 0.0088027302 | I836: =Panel!D810-Panel!D809 -> 0.002980286 | L836: =Panel!E810-Panel!E809 -> 0.0032502737 | M836: =Panel!E809 -> 5.62203
L837: =Panel!E811-Panel!E810 -> 0.0094736417 | M837: =Panel!E810 -> 5.6252802
L838: =Panel!E812-Panel!E811 -> -0.0042592094 | M838: =Panel!E811 -> 5.6347539
L839: =Panel!E813-Panel!E812 -> 0.0042949243 | M839: =Panel!E812 -> 5.6304947
L840: =Panel!E814-Panel!E813 -> 0.0017841218 | M840: =Panel!E813 -> 5.6347896
L841: =Panel!E815-Panel!E814 -> -0.0028561248 | M841: =Panel!E814 -> 5.6365737

Sheet 2 Hedge ratio
A1: Step 2 · Hedge ratio by OLS (Engle–Granger stage 1)
A2: ln F = α + β · ln B + ε
A5: β (hedge ratio) | B5: =INDEX(LINEST(Panel!$D$5:$D$815,Panel!$E$5:$E$815,TRUE(),TRUE()),1,1) -> 0.91612676 | C5: Python: 0.91613
A6: α (intercept) | B6: =INDEX(LINEST(Panel!$D$5:$D$815,Panel!$E$5:$E$815,TRUE(),TRUE()),1,2) -> 4.9618201 | C6: Python: 4.96182
A7: se(β) | B7: =INDEX(LINEST(Panel!$D$5:$D$815,Panel!$E$5:$E$815,TRUE(),TRUE()),2,1) -> 0.0021325147 | C7: Python: 0.00213
A8: R² | B8: =INDEX(LINEST(Panel!$D$5:$D$815,Panel!$E$5:$E$815,TRUE(),TRUE()),3,1) -> 0.99563563 | C8: Python: 0.99564
A9: Mean price ratio F / B | B9: =SUMPRODUCT(Panel!$B$5:$B$815/Panel!$C$5:$C$815)/COUNT(Panel!$B$5:$B$815) -> 89.679532 | C9: Contract sizes 65 : 6500 imply 100.0
A10: Error in the assumed ratio | B10: =100/B9-1 -> 0.11508164
A11: Correlation of daily log returns (raw) | B11: =CORREL(Panel!I6:I815,Panel!J6:J815) -> 0.94586744 | C11: Python: 0.9459
A12: …with contract switches removed | B12: =CORREL(Panel!M6:M815,Panel!J6:J815) -> 0.95587499 | C12: Python: 0.9559

Sheet 3 Cointegration
A1: Step 3 · Engle–Granger residual test (constant only)
A2: Δε̂(t) = ρ·ε̂(t−1) + Σ φi·Δε̂(t−i) + u(t), no constant. H0: ρ = 0 (no cointegration). Residuals from sheet 2 (Panel column P).
A5: ρ̂ (coefficient on ε(t−1)) | B5: =INDEX(LINEST(C14:C820,D14:G820,FALSE(),TRUE()),1,4) -> -0.048794575
A6: se(ρ̂) | B6: =INDEX(LINEST(C14:C820,D14:G820,FALSE(),TRUE()),2,4) -> 0.015759886
A7: Engle–Granger statistic | B7: =B5/B6 -> -3.096125 | C7: Python: -3.096
A8: 5% critical value (MacKinnon, 2 variables) | B8: -3.344 | C8: Not the ordinary ADF value: β was estimated
A9: Decision | B9: =IF(B7<B8,"Reject H0 → cointegrated","Fail to reject H0 → no cointegration") -> Fail to reject H0 → no cointegration
C13: Δε(t) | D13: ε(t−1) | E13: Δε(t−1) | F13: Δε(t−2) | G13: Δε(t−3)
C14: =Panel!P9-Panel!P8 -> 0.0010250422 | D14: =Panel!P8 -> -0.00070509802 | E14: =Panel!P8-Panel!P7 -> -0.0018367083 | F14: =Panel!P7-Panel!P6 -> -0.00054780299 | G14: =Panel!P6-Panel!P5 -> -0.00013941214
C15: =Panel!P10-Panel!P9 -> -6.0501651e-05 | D15: =Panel!P9 -> 0.00031994414 | E15: =Panel!P9-Panel!P8 -> 0.0010250422 | F15: =Panel!P8-Panel!P7 -> -0.0018367083 | G15: =Panel!P7-Panel!P6 -> -0.00054780299
C16: =Panel!P11-Panel!P10 -> 3.2038562e-05 | D16: =Panel!P10 -> 0.00025944249 | E16: =Panel!P10-Panel!P9 -> -6.0501651e-05 | F16: =Panel!P9-Panel!P8 -> 0.0010250422 | G16: =Panel!P8-Panel!P7 -> -0.0018367083
C17: =Panel!P12-Panel!P11 -> 2.8918771e-06 | D17: =Panel!P11 -> 0.00029148105 | E17: =Panel!P11-Panel!P10 -> 3.2038562e-05 | F17: =Panel!P10-Panel!P9 -> -6.0501651e-05 | G17: =Panel!P9-Panel!P8 -> 0.0010250422
C18: =Panel!P13-Panel!P12 -> 9.8168639e-06 | D18: =Panel!P12 -> 0.00029437293 | E18: =Panel!P12-Panel!P11 -> 2.8918771e-06 | F18: =Panel!P11-Panel!P10 -> 3.2038562e-05 | G18: =Panel!P10-Panel!P9 -> -6.0501651e-05
C19: =Panel!P14-Panel!P13 -> -0.0018135239 | D19: =Panel!P13 -> 0.0003041898 | E19: =Panel!P13-Panel!P12 -> 9.8168639e-06 | F19: =Panel!P12-Panel!P11 -> 2.8918771e-06 | G19: =Panel!P11-Panel!P10 -> 3.2038562e-05
C20: =Panel!P15-Panel!P14 -> -0.0004469722 | D20: =Panel!P14 -> -0.0015093342 | E20: =Panel!P14-Panel!P13 -> -0.0018135239 | F20: =Panel!P13-Panel!P12 -> 9.8168639e-06 | G20: =Panel!P12-Panel!P11 -> 2.8918771e-06
C21: =Panel!P16-Panel!P15 -> -0.002405087 | D21: =Panel!P15 -> -0.0019563064 | E21: =Panel!P15-Panel!P14 -> -0.0004469722 | F21: =Panel!P14-Panel!P13 -> -0.0018135239 | G21: =Panel!P13-Panel!P12 -> 9.8168639e-06
C22: =Panel!P17-Panel!P16 -> 0.00040620841 | D22: =Panel!P16 -> -0.0043613934 | E22: =Panel!P16-Panel!P15 -> -0.002405087 | F22: =Panel!P15-Panel!P14 -> -0.0004469722 | G22: =Panel!P14-Panel!P13 -> -0.0018135239
C23: =Panel!P18-Panel!P17 -> 0.00068813225 | D23: =Panel!P17 -> -0.003955185 | E23: =Panel!P17-Panel!P16 -> 0.00040620841 | F23: =Panel!P16-Panel!P15 -> -0.002405087 | G23: =Panel!P15-Panel!P14 -> -0.0004469722
C24: =Panel!P19-Panel!P18 -> 0.00033187718 | D24: =Panel!P18 -> -0.0032670527 | E24: =Panel!P18-Panel!P17 -> 0.00068813225 | F24: =Panel!P17-Panel!P16 -> 0.00040620841 | G24: =Panel!P16-Panel!P15 -> -0.002405087
C25: =Panel!P20-Panel!P19 -> 0.00089762634 | D25: =Panel!P19 -> -0.0029351756 | E25: =Panel!P19-Panel!P18 -> 0.00033187718 | F25: =Panel!P18-Panel!P17 -> 0.00068813225 | G25: =Panel!P17-Panel!P16 -> 0.00040620841
... C820: =Panel!P815-Panel!P814 -> -0.00099876501 | D820: =Panel!P814 -> -0.0092573739 | E820: =Panel!P814-Panel!P813 -> 0.0022120662 | F820: =Panel!P813-Panel!P812 -> -0.00052116769 | G820: =Panel!P812-Panel!P811 -> 0.00065073327

Sheet Carry
A1: Step 4 · Diagnosis and cost-of-carry decomposition
A2: ln(F/B) = c + a·DTE + b·t → r − q = 365a, q = −252b, r = (r − q) + q
A4: Trend in ln(F/B) per trading day (b, trend only) | B4: =INDEX(LINEST(Panel!$H$5:$H$815,Panel!$F$5:$F$815,TRUE(),TRUE()),1,1) -> -4.6087524e-05
A5: …annualised (× 252) | B5: =B4*Inputs!$B$16 -> -0.011614056 | C5: Python: -1.161%
A6: R² of the trend-only regression | B6: =INDEX(LINEST(Panel!$H$5:$H$815,Panel!$F$5:$F$815,TRUE(),TRUE()),3,1) -> 0.9333944 | C6: Python: 0.9334
A7: Annualised basis r − q (= 365 × DTE coefficient) | B7: =INDEX(LINEST(Panel!$H$5:$H$815,Panel!$F$5:$G$815,TRUE(),TRUE()),1,1)*365 -> 0.053745893 | C7: Python: 5.37%
A8: Dividend drift q (= −252 × t coefficient) | B8: =-INDEX(LINEST(Panel!$H$5:$H$815,Panel!$F$5:$G$815,TRUE(),TRUE()),1,2)*Inputs!$B$16 -> 0.011637568 | C8: Python: 1.16%
A9: Implied financing rate r | B9: =B7+B8 -> 0.065383462 | C9: Python: 6.54% — used to neutralise the 39 contract switches
A10: R² of the carry regression | B10: =INDEX(LINEST(Panel!$H$5:$H$815,Panel!$F$5:$G$815,TRUE(),TRUE()),3,1) -> 0.94760241 | C10: Python: 0.9476
A11: Average RBI repo over the sample | B11: =AVERAGE(Panel!$N$5:$N$815) -> 0.06054254 | C11: Python: 6.054%

Sheet 5 Re-specification
A1: Step 5 · Trend-augmented cointegrating regression
A2: ln F = α + β·ln B + δ·t + ε. Theory predicts β → 1 and δ → −q.
A5: β | B5: =INDEX(LINEST(Panel!$D$5:$D$815,Panel!$E$5:$F$815,TRUE(),TRUE()),1,2) -> 0.9969695 | C5: Python: 0.99697
A6: δ (per trading day) | B6: =INDEX(LINEST(Panel!$D$5:$D$815,Panel!$E$5:$F$815,TRUE(),TRUE()),1,1) -> -4.4929318e-05 | C6: Python: -4.4929e-05
A7: α | B7: =INDEX(LINEST(Panel!$D$5:$D$815,Panel!$E$5:$F$815,TRUE(),TRUE()),1,3) -> 4.531201 | C7: Python: 4.5312
A8: δ annualised | B8: =B6*Inputs!$B$16 -> -0.011322188 | C8: Python: -1.13%
A9: R² | B9: =INDEX(LINEST(Panel!$D$5:$D$815,Panel!$E$5:$F$815,TRUE(),TRUE()),3,1) -> 0.99915687 | C9: Python: 0.99916

Sheet 5b EG with trend
A1: Step 5 · Engle–Granger test on the trend-augmented residual
A2: Residuals from sheet 5 (Panel column Q). Critical value for constant + trend.
A5: ρ̂ (coefficient on ε(t−1)) | B5: =INDEX(LINEST(C14:C820,D14:G820,FALSE(),TRUE()),1,4) -> -0.31396094
A6: se(ρ̂) | B6: =INDEX(LINEST(C14:C820,D14:G820,FALSE(),TRUE()),2,4) -> 0.038950917
A7: Engle–Granger statistic | B7: =B5/B6 -> -8.0604248 | C7: Python: -8.06
A8: 5% critical value (MacKinnon, 2 variables) | B8: -3.792 | C8: Not the ordinary ADF value: β was estimated
A9: Decision | B9: =IF(B7<B8,"Reject H0 → cointegrated","Fail to reject H0 → no cointegration") -> Reject H0 → cointegrated
C13: Δε(t) | D13: ε(t−1) | E13: Δε(t−1) | F13: Δε(t−2) | G13: Δε(t−3)
C14: =Panel!Q9-Panel!Q8 -> 0.00025298115 | D14: =Panel!Q8 -> 0.002575675 | E14: =Panel!Q8-Panel!Q7 -> -0.0011934687 | F14: =Panel!Q7-Panel!Q6 -> -0.0012279255 | G14: =Panel!Q6-Panel!Q5 -> 0.00015880203
C15: =Panel!Q10-Panel!Q9 -> 4.5112825e-05 | D15: =Panel!Q9 -> 0.0028286561 | E15: =Panel!Q9-Panel!Q8 -> 0.00025298115 | F15: =Panel!Q8-Panel!Q7 -> -0.0011934687 | G15: =Panel!Q7-Panel!Q6 -> -0.0012279255
C16: =Panel!Q11-Panel!Q10 -> -0.0001089891 | D16: =Panel!Q10 -> 0.0028737689 | E16: =Panel!Q10-Panel!Q9 -> 4.5112825e-05 | F16: =Panel!Q9-Panel!Q8 -> 0.00025298115 | G16: =Panel!Q8-Panel!Q7 -> -0.0011934687
C17: =Panel!Q12-Panel!Q11 -> -2.8862472e-05 | D17: =Panel!Q11 -> 0.0027647798 | E17: =Panel!Q11-Panel!Q10 -> -0.0001089891 | F17: =Panel!Q10-Panel!Q9 -> 4.5112825e-05 | G17: =Panel!Q9-Panel!Q8 -> 0.00025298115
C18: =Panel!Q13-Panel!Q12 -> 0.00017585892 | D18: =Panel!Q12 -> 0.0027359174 | E18: =Panel!Q12-Panel!Q11 -> -2.8862472e-05 | F18: =Panel!Q11-Panel!Q10 -> -0.0001089891 | G18: =Panel!Q10-Panel!Q9 -> 4.5112825e-05
C19: =Panel!Q14-Panel!Q13 -> -0.0022840826 | D19: =Panel!Q13 -> 0.0029117763 | E19: =Panel!Q13-Panel!Q12 -> 0.00017585892 | F19: =Panel!Q12-Panel!Q11 -> -2.8862472e-05 | G19: =Panel!Q11-Panel!Q10 -> -0.0001089891
C20: =Panel!Q15-Panel!Q14 -> -4.7998262e-05 | D20: =Panel!Q14 -> 0.00062769367 | E20: =Panel!Q14-Panel!Q13 -> -0.0022840826 | F20: =Panel!Q13-Panel!Q12 -> 0.00017585892 | G20: =Panel!Q12-Panel!Q11 -> -2.8862472e-05
C21: =Panel!Q16-Panel!Q15 -> -0.0021178716 | D21: =Panel!Q15 -> 0.00057969541 | E21: =Panel!Q15-Panel!Q14 -> -4.7998262e-05 | F21: =Panel!Q14-Panel!Q13 -> -0.0022840826 | G21: =Panel!Q13-Panel!Q12 -> 0.00017585892
C22: =Panel!Q17-Panel!Q16 -> 0.00073878416 | D22: =Panel!Q16 -> -0.0015381762 | E22: =Panel!Q16-Panel!Q15 -> -0.0021178716 | F22: =Panel!Q15-Panel!Q14 -> -4.7998262e-05 | G22: =Panel!Q14-Panel!Q13 -> -0.0022840826
C23: =Panel!Q18-Panel!Q17 -> 0.00054658239 | D23: =Panel!Q17 -> -0.00079939204 | E23: =Panel!Q17-Panel!Q16 -> 0.00073878416 | F23: =Panel!Q16-Panel!Q15 -> -0.0021178716 | G23: =Panel!Q15-Panel!Q14 -> -4.7998262e-05
C24: =Panel!Q19-Panel!Q18 -> -4.7247812e-05 | D24: =Panel!Q18 -> -0.00025280965 | E24: =Panel!Q18-Panel!Q17 -> 0.00054658239 | F24: =Panel!Q17-Panel!Q16 -> 0.00073878416 | G24: =Panel!Q16-Panel!Q15 -> -0.0021178716
C25: =Panel!Q20-Panel!Q19 -> 0.00086203499 | D25: =Panel!Q19 -> -0.00030005746 | E25: =Panel!Q19-Panel!Q18 -> -4.7247812e-05 | F25: =Panel!Q18-Panel!Q17 -> 0.00054658239 | G25: =Panel!Q17-Panel!Q16 -> 0.00073878416
... C820: =Panel!Q815-Panel!Q814 -> -0.00072293874 | D820: =Panel!Q814 -> 0.0020334366 | E820: =Panel!Q814-Panel!Q813 -> 0.0021127622 | F820: =Panel!Q813-Panel!Q812 -> -0.00082345182 | G820: =Panel!Q812-Panel!Q811 -> 0.0010399887

Sheet 6 ECM
A1: Step 6 · Error-correction model
A2: Δln F(t) = c + γ·ε̂(t−1) + u(t)
A5: γ (speed of adjustment) | B5: =INDEX(LINEST(Panel!I6:I815,Panel!Q5:Q814,TRUE(),TRUE()),1,1) -> -0.48320184 | C5: Python: -0.4832
A6: se(γ), ordinary OLS | B6: =INDEX(LINEST(Panel!I6:I815,Panel!Q5:Q814,TRUE(),TRUE()),2,1) -> 0.10190958
A7: t-statistic, ordinary OLS | B7: =B5/B6 -> -4.7414761 | C7: Python OLS: -4.741 · Python HAC (reported): -3.302
A8: Half-life = ln 2 / |γ| (sessions) | B8: =LN(2)/-B5 -> 1.4344879 | C8: Python: 1.43
A9: Exact discrete half-life = ln 0.5 / ln(1+γ) | B9: =LN(0.5)/LN(1+B5) -> 1.0500593 | C9: Python: 1.05
A11: Excel has no Newey–West estimator, so it reproduces γ and the ordinary t; the HAC t-statistic in the deck comes from Python.

Sheet 7 Signal backtest
A1: Step 7 · Walk-forward backtest — the signal's own quality
A2: x(t) = p(t−1)·[Δln F adj − βh·Δln B + βh·repo/252] − cost(t). Both directions, retail costs. Panel columns S–AI.
A5: Trades (entries) | B5: =SUM(Panel!$AA$5:$AA$815) -> 29 | C5: Python: 29
A6: Annual excess return (mean × 252) | B6: =AVERAGE(Panel!$AI$5:$AI$815)*Inputs!$B$16 -> 0.0051470199 | C6: Python: 0.515%
A7: Annual volatility | B7: =STDEV(Panel!$AI$5:$AI$815)*SQRT(Inputs!$B$16) -> 0.01328388 | C7: Python: 1.328%
A8: Sharpe ratio = mean / sd × √252 | B8: =AVERAGE(Panel!$AI$5:$AI$815)/STDEV(Panel!$AI$5:$AI$815)*SQRT(Inputs!$B$16) -> 0.3874636 | C8: Python: 0.39
A9: Maximum drawdown | B9: =MIN(Panel!$BC$5:$BC$815) -> -0.012796394 | C9: Python: -1.28%
A10: Share of sessions holding a position | B10: =COUNTIF(Panel!$AB$5:$AB$815,"<>0")/COUNT(Panel!$AB$5:$AB$815) -> 0.2108508 | C10: Python: 21.1%
A11: Total costs paid, % of notional | B11: =SUM(Panel!$AH$5:$AH$815) -> 0.035033618

Sheet 7a Trade walkthrough
A1: Step 7 · One trade, session by session (first signal in the sample)
A2: Every cell links to the Panel sheet. Long spread = buy futures, sell ₹β of ETF per ₹1 of futures. x = p(t−1)·[Δln F adj − βh·Δln B + βh·repo/252] − cost
A4: Date | B4: z-score | C4: Entry | D4: Exit | E4: Position | F4: β at entry | G4: Δ ln F adj | H4: Δ ln B | I4: Repo | J4: Cost | K4: Daily excess P&L | L4: Cumulative
A5: =Panel!A63 -> 45131 | B5: =Panel!W63 | C5: =Panel!AA63 -> 0 | D5: =Panel!Y63 -> 0 | E5: =Panel!AB63 -> 0 | F5: =Panel!AD63 -> 0 | G5: =Panel!M63 -> -0.0063030978 | H5: =Panel!J63 -> -0.004557914 | I5: =Panel!N63 -> 0.065 | J5: =Panel!AH63 -> 0 | K5: =Panel!AI63 -> 0 | L5: =K5 -> 0
A6: =Panel!A64 -> 45132 | B6: =Panel!W64 | C6: =Panel!AA64 -> 0 | D6: =Panel!Y64 -> 0 | E6: =Panel!AB64 -> 0 | F6: =Panel!AD64 -> 0 | G6: =Panel!M64 -> 0.00065520317 | H6: =Panel!J64 -> 0.00013842427 | I6: =Panel!N64 -> 0.065 | J6: =Panel!AH64 -> 0 | K6: =Panel!AI64 -> 0 | L6: =L5+K6 -> 0
A7: =Panel!A65 -> 45133 | B7: =Panel!W65 -> -2.3907929 | C7: =Panel!AA65 -> 1 | D7: =Panel!Y65 -> 0 | E7: =Panel!AB65 -> 1 | F7: =Panel!AD65 -> 1.0558996 | G7: =Panel!M65 -> 0.003901999 | H7: =Panel!J65 -> 0.004878732 | I7: =Panel!N65 -> 0.065 | J7: =Panel!AH65 -> 0.00037673891 | K7: =Panel!AI65 -> -0.00037673891 | L7: =L6+K7 -> -0.00037673891
A8: =Panel!A66 -> 45134 | B8: =Panel!W66 -> -3.3079103 | C8: =Panel!AA66 -> 0 | D8: =Panel!Y66 -> 0 | E8: =Panel!AB66 -> 1 | F8: =Panel!AD66 -> 1.0558996 | G8: =Panel!M66 -> -0.0057722414 | H8: =Panel!J66 -> -0.0035876953 | I8: =Panel!N66 -> 0.065 | J8: =Panel!AH66 -> 0.000415 | K8: =Panel!AI66 -> -0.0021266403 | L8: =L7+K8 -> -0.0025033792
A9: =Panel!A67 -> 45135 | B9: =Panel!W67 -> 1.4531479 | C9: =Panel!AA67 -> 0 | D9: =Panel!Y67 -> 0 | E9: =Panel!AB67 -> 1 | F9: =Panel!AD67 -> 1.0558996 | G9: =Panel!M67 -> -0.0033515067 | H9: =Panel!J67 -> -0.0030920485 | I9: =Panel!N67 -> 0.065 | J9: =Panel!AH67 -> 0 | K9: =Panel!AI67 -> 0.00018574113 | L9: =L8+K9 -> -0.0023176381
A10: =Panel!A68 -> 45138 | B10: =Panel!W68 -> 1.1013428 | C10: =Panel!AA68 -> 0 | D10: =Panel!Y68 -> 0 | E10: =Panel!AB68 -> 1 | F10: =Panel!AD68 -> 1.0558996 | G10: =Panel!M68 -> 0.0052135904 | H10: =Panel!J68 -> 0.0055312425 | I10: =Panel!N68 -> 0.065 | J10: =Panel!AH68 -> 0 | K10: =Panel!AI68 -> -0.00035449129 | L10: =L9+K10 -> -0.0026721294
A11: =Panel!A69 -> 45139 | B11: =Panel!W69 -> 1.1553349 | C11: =Panel!AA69 -> 0 | D11: =Panel!Y69 -> 0 | E11: =Panel!AB69 -> 1 | F11: =Panel!AD69 -> 1.0558996 | G11: =Panel!M69 -> -0.0011853901 | H11: =Panel!J69 -> -0.0011498219 | I11: =Panel!N69 -> 0.065 | J11: =Panel!AH69 -> 0 | K11: =Panel!AI69 -> 0.00030106146 | L11: =L10+K11 -> -0.0023710679
A12: =Panel!A70 -> 45140 | B12: =Panel!W70 -> 0.39752961 | C12: =Panel!AA70 -> 0 | D12: =Panel!Y70 -> 1 | E12: =Panel!AB70 -> 0 | F12: =Panel!AD70 -> 0 | G12: =Panel!M70 -> -0.011507975 | H12: =Panel!J70 -> -0.009711059 | I12: =Panel!N70 -> 0.065 | J12: =Panel!AH70 -> 0.00062956486 | K12: =Panel!AI70 -> -0.0016112814 | L12: =L11+K12 -> -0.0039823494
A13: =Panel!A71 -> 45141 | B13: =Panel!W71 -> 1.2348345 | C13: =Panel!AA71 -> 0 | D13: =Panel!Y71 -> 0 | E13: =Panel!AB71 -> 0 | F13: =Panel!AD71 -> 0 | G13: =Panel!M71 -> -0.0060043324 | H13: =Panel!J71 -> -0.006994666 | I13: =Panel!N71 -> 0.065 | J13: =Panel!AH71 -> 0 | K13: =Panel!AI71 -> 0 | L13: =L12+K13 -> -0.0039823494
A14: =Panel!A72 -> 45142 | B14: =Panel!W72 -> 0.36996208 | C14: =Panel!AA72 -> 0 | D14: =Panel!Y72 -> 0 | E14: =Panel!AB72 -> 0 | F14: =Panel!AD72 -> 0 | G14: =Panel!M72 -> 0.0053378266 | H14: =Panel!J72 -> 0.0063903942 | I14: =Panel!N72 -> 0.065 | J14: =Panel!AH72 -> 0 | K14: =Panel!AI72 -> 0 | L14: =L13+K14 -> -0.0039823494
A15: =Panel!A73 -> 45145 | B15: =Panel!W73 -> 0.61075925 | C15: =Panel!AA73 -> 0 | D15: =Panel!Y73 -> 0 | E15: =Panel!AB73 -> 0 | F15: =Panel!AD73 -> 0 | G15: =Panel!M73 -> 0.0046282692 | H15: =Panel!J73 -> 0.0041759526 | I15: =Panel!N73 -> 0.065 | J15: =Panel!AH73 -> 0 | K15: =Panel!AI73 -> 0 | L15: =L14+K15 -> -0.0039823494
A17: Reading it: z falls below −2 → enter long spread (futures cheap). z rises back inside ±0.5 → exit. Costs are charged on entry, exit, and the expiry roll (27-Jul-23).
A19: From β to lots and units (entry day, today's lot of 65)
A20: Units per futures lot | B20: =Inputs!$B$11 -> 65
A21: Futures price at entry (F) | B21: =Panel!B65 -> 19772
A22: NIFTYBEES price at entry (B) | B22: =Panel!C65 -> 217.8
A23: β at entry (rupee hedge ratio) | B23: =Panel!AD65 -> 1.0558996
A24: Futures notional = lot × F | B24: =B20*B21 -> 1285180
A25: ETF notional = β × futures notional | B25: =B23*B24 -> 1357021
A26: NIFTYBEES units = ETF notional ÷ B | B26: =ROUND(B25/B22,0) -> 6231 | C26: i.e. units = β × 65 × F ÷ B
A27: Rounding error, % of notional | B27: =ABS(B26*B22-B25)/B24 -> 7.0619219e-05
A28: β comes from a log–log regression, so it is a ratio of rupee exposures, not of units. Prices convert it to units.

Sheet 8 Four people
A1: Step 7 · Same signal, four balance sheets
A2: Return above the risk-free rate on the capital each person must commit. Profit = Σx / years × N.
A4: Notional N = lot × last futures price | B4: =Inputs!$B$11*Panel!B815 -> 1602620.5
A5: Years in sample (sessions / 252) | B5: =COUNT(Panel!$B$5:$B$815)/Inputs!$B$16 -> 3.218254
B7: Aarav | C7: Meera | D7: Rohan | E7: Kavya | F7: How the capital is defined
A8: Σ daily excess P&L, per ₹1 of notional | B8: =SUM(Panel!$AW$5:$AW$815) -> 0.0068871584 | C8: =SUM(Panel!$AX$5:$AX$815) -> -0.020151933 | D8: =SUM(Panel!$AZ$5:$AZ$815) -> -0.096200054 | E8: =SUM(Panel!$AK$5:$AK$815) -> 0.025850872
A9: Annual excess profit (₹) | B9: =B8/$B$5*$B$4 -> 3429.6552 | C9: =C8/$B$5*$B$4 -> -10035.224 | D9: =D8/$B$5*$B$4 -> -47905.535 | E9: =E8/$B$5*$B$4 -> 12873.172
A10: Capital committed (₹) | B10: =(1+Inputs!$B$12)*$B$4 -> 1810961.2 | C10: =(0.25+Inputs!$B$12)*$B$4 -> 608995.79 | D10: =(0.5*Inputs!$B$12)*$B$4 -> 104170.33 | E10: =(Inputs!$B$12*(1-Inputs!$B$15))*$B$4 -> 62502.2
A11: Return above risk-free on capital | B11: =B9/B10 -> 0.0018938314 | C11: =C9/C10 -> -0.016478315 | D11: =D9/D10 -> -0.45987695 | E11: =E9/E10 -> 0.20596351
B12: Python: 0.19% | C12: Python: -1.65% | D12: Python: -45.99% | E12: Python: 20.6%
A14: Aarav: ETF bought in cash (1.00) + futures margin
A15: Meera: 25% of ETF own money (75% MTF) + margin
A16: Rohan: Only the 50% cash part of margin; he already owns the ETF
A17: Kavya: Margin after cross-margin relief; inventory already held

Sheet 9 Trades 15-min
A1: Step 7 · Every 15-minute trade, recomputed with formulas
A2: z at the signal bar uses Excel's own rolling regression (Panel S–V). Price P&L, option and ETF costs and financing are all formulas.
A4: Who | B4: Side | C4: Signal bar | D4: Day t | E4: ln F | F4: ln B | G4: α | H4: β | I4: δ | J4: σ | K4: z | L4: Entry |z| > | M4: Signal? | N4: Entry bar | O4: t entry | P4: F entry | Q4: B entry | R4: Exit bar | S4: t exit | T4: F exit | U4: B exit | V4: Exit | W4: Price P&L | X4: Entry cost | Y4: Exit cost | Z4: Financing | AA4: Net (Excel) | AB4: Net (Python) | AC4: Difference
A5: signal | B5: 1 | C5: 2023-07-26 14:00 | D5: 60 | E5: 9.8934094 | F5: 5.3848161 | G5: =INDEX(Panel!$U$5:$U$815,D5+1) -> 4.2225218 | H5: =INDEX(Panel!$T$5:$T$815,D5+1) -> 1.0558996 | I5: =INDEX(Panel!$S$5:$S$815,D5+1) -> -0.00019031048 | J5: =INDEX(Panel!$V$5:$V$815,D5+1) -> 0.001504979 | K5: =(E5-G5-H5*F5-I5*D5)/J5 -> -2.338162 | L5: 2 | M5: =IF(ABS(K5)>L5,"Yes","No") -> Yes | N5: 2023-07-26 14:15 | O5: 60 | P5: 19825.65 | Q5: 218.36 | R5: 2023-07-27 15:15 | S5: 61 | T5: 19658.2 | U5: 217.02 | V5: expiry | W5: =B5*((LN(T5)-LN(P5))-(LN(U5)-LN(Q5))) -> -0.0023264381 | X5: =IF(INDEX(Panel!$A$5:$A$815,O5+1)<=DATE(2024,9,30),0.000625,IF(INDEX(Panel!$A$5:$A$815,O5+1)<=DATE(2026,3,31),0.001,0.0015))*(0.3989*Inputs!$B$28*SQRT(MAX(INDEX(Panel!$G$5:$G$815,O5+1),0)/365))+2*Inputs!$B$29+Inputs!$B$19+0.00003*(0.3989*Inputs!$B$28*SQRT(MAX(INDEX(Panel!$G$5:$G$815,O5+1),0)/365))+IF(B5<0,(Inputs!$B$20+Inputs!$B$22+Inputs!$B$23),(Inputs!$B$21+Inputs!$B$22+Inputs!$B$23)) -> 0.00031691464 | Y5: =IF(V5="expiry",IF(INDEX(Panel!$A$5:$A$815,S5+1)<=DATE(2026,3,31),0.00125,0.0015)*IF(B5<0,MAX(P5-T5,0),MAX(T5-P5,0))/T5,IF(INDEX(Panel!$A$5:$A$815,S5+1)<=DATE(2024,9,30),0.000625,IF(INDEX(Panel!$A$5:$A$815,S5+1)<=DATE(2026,3,31),0.001,0.0015))*(0.3989*Inputs!$B$28*SQRT(MAX(INDEX(Panel!$G$5:$G$815,S5+1),0)/365))+2*Inputs!$B$29+Inputs!$B$19)+IF(B5<0,(Inputs!$B$21+Inputs!$B$22+Inputs!$B$23),(Inputs!$B$20+Inputs!$B$22+Inputs!$B$23)) -> 0.00035 | Z5: =B5*SUMPRODUCT((Panel!$F$5:$F$815>=O5)*(Panel!$F$5:$F$815<S5)*Panel!$N$5:$N$815*Panel!$BD$5:$BD$815)/365 -> 0.00017808219 | AA5: =W5-X5-Y5+Z5 -> -0.0028152705 | AB5: -0.0028152705 | AC5: =AA5-AB5 -> -9.0639302e-17
A6: signal | B6: -1 | C6: 2023-07-28 09:15 | D6: 62 | E6: 9.8899995 | F6: 5.3758801 | G6: =INDEX(Panel!$U$5:$U$815,D6+1) -> 4.2338414 | H6: =INDEX(Panel!$T$5:$T$815,D6+1) -> 1.0538075 | I6: =INDEX(Panel!$S$5:$S$815,D6+1) -> -0.00020051329 | J6: =INDEX(Panel!$V$5:$V$815,D6+1) -> 0.0016779358 | K6: =(E6-G6-H6*F6-I6*D6)/J6 -> 2.0543536 | L6: 2 | M6: =IF(ABS(K6)>L6,"Yes","No") -> Yes | N6: 2023-07-28 09:30 | O6: 62 | P6: 19748 | Q6: 216.35 | R6: 2023-08-31 15:15 | S6: 85 | T6: 19254 | U6: 213.2 | V6: expiry | W6: =B6*((LN(T6)-LN(P6))-(LN(U6)-LN(Q6))) -> 0.010666615 | X6: =IF(INDEX(Panel!$A$5:$A$815,O6+1)<=DATE(2024,9,30),0.000625,IF(INDEX(Panel!$A$5:$A$815,O6+1)<=DATE(2026,3,31),0.001,0.0015))*(0.3989*Inputs!$B$28*SQRT(MAX(INDEX(Panel!$G$5:$G$815,O6+1),0)/365))+2*Inputs!$B$29+Inputs!$B$19+0.00003*(0.3989*Inputs!$B$28*SQRT(MAX(INDEX(Panel!$G$5:$G$815,O6+1),0)/365))+IF(B6<0,(Inputs!$B$20+Inputs!$B$22+Inputs!$B$23),(Inputs!$B$21+Inputs!$B$22+Inputs!$B$23)) -> 0.00046616417 | Y6: =IF(V6="expiry",IF(INDEX(Panel!$A$5:$A$815,S6+1)<=DATE(2026,3,31),0.00125,0.0015)*IF(B6<0,MAX(P6-T6,0),MAX(T6-P6,0))/T6,IF(INDEX(Panel!$A$5:$A$815,S6+1)<=DATE(2024,9,30),0.000625,IF(INDEX(Panel!$A$5:$A$815,S6+1)<=DATE(2026,3,31),0.001,0.0015))*(0.3989*Inputs!$B$28*SQRT(MAX(INDEX(Panel!$G$5:$G$815,S6+1),0)/365))+2*Inputs!$B$29+Inputs!$B$19)+IF(B6<0,(Inputs!$B$21+Inputs!$B$22+Inputs!$B$23),(Inputs!$B$20+Inputs!$B$22+Inputs!$B$23)) -> 0.00024207126 | Z6: =B6*SUMPRODUCT((Panel!$F$5:$F$815>=O6)*(Panel!$F$5:$F$815<S6)*Panel!$N$5:$N$815*Panel!$BD$5:$BD$815)/365 -> -0.0060547945 | AA6: =W6-X6-Y6+Z6 -> 0.0039035847 | AB6: 0.0039035847 | AC6: =AA6-AB6 -> 5.7679556e-17
A7: signal | B7: -1 | C7: 2023-09-01 09:15 | D7: 86 | E7: 9.8724612 | F7: 5.3609165 | G7: =INDEX(Panel!$U$5:$U$815,D7+1) -> 4.2252851 | H7: =INDEX(Panel!$T$5:$T$815,D7+1) -> 1.0553828 | I7: =INDEX(Panel!$S$5:$S$815,D7+1) -> -0.0001905105 | J7: =INDEX(Panel!$V$5:$V$815,D7+1) -> 0.0017694952 | K7: =(E7-G7-H7*F7-I7*D7)/J7 -> 3.2443583 | L7: 2 | M7: =IF(ABS(K7)>L7,"Yes","No") -> Yes | N7: 2023-09-01 09:30 | O7: 86 | P7: 19409 | Q7: 213.19 | R7: 2023-09-28 15:15 | S7: 104 | T7: 19525 | U7: 216.14 | V7: expiry | W7: =B7*((LN(T7)-LN(P7))-(LN(U7)-LN(Q7))) -> 0.0077837393 | X7: =IF(INDEX(Panel!$A$5:$A$815,O7+1)<=DATE(2024,9,30),0.000625,IF(INDEX(Panel!$A$5:$A$815,O7+1)<=DATE(2026,3,31),0.001,0.0015))*(0.3989*Inputs!$B$28*SQRT(MAX(INDEX(Panel!$G$5:$G$815,O7+1),0)/365))+2*Inputs!$B$29+Inputs!$B$19+0.00003*(0.3989*Inputs!$B$28*SQRT(MAX(INDEX(Panel!$G$5:$G$815,O7+1),0)/365))+IF(B7<0,(Inputs!$B$20+Inputs!$B$22+Inputs!$B$23),(Inputs!$B$21+Inputs!$B$22+Inputs!$B$23)) -> 0.00046494876 | Y7: =IF(V7="expiry",IF(INDEX(Panel!$A$5:$A$815,S7+1)<=DATE(2026,3,31),0.00125,0.0015)*IF(B7<0,MAX(P7-T7,0),MAX(T7-P7,0))/T7,IF(INDEX(Panel!$A$5:$A$815,S7+1)<=DATE(2024,9,30),0.000625,IF(INDEX(Panel!$A$5:$A$815,S7+1)<=DATE(2026,3,31),0.001,0.0015))*(0.3989*Inputs!$B$28*SQRT(MAX(INDEX(Panel!$G$5:$G$815,S7+1),0)/365))+2*Inputs!$B$29+Inputs!$B$19)+IF(B7<0,(Inputs!$B$21+Inputs!$B$22+Inputs!$B$23),(Inputs!$B$20+Inputs!$B$22+Inputs!$B$23)) -> 0.00021 | Z7: =B7*SUMPRODUCT((Panel!$F$5:$F$815>=O7)*(Panel!$F$5:$F$815<S7)*Panel!$N$5:$N$815*Panel!$BD$5:$BD$815)/365 -> -0.0048082192 | AA7: =W7-X7-Y7+Z7 -> 0.0023005714 | AB7: 0.0023005714 | AC7: =AA7-AB7 -> 3.3393427e-17
A8: signal | B8: -1 | C8: 2023-09-29 09:30 | D8: 105 | E8: 9.8868143 | F8: 5.3760189 | G8: =INDEX(Panel!$U$5:$U$815,D8+1) -> 4.3423895 | H8: =INDEX(Panel!$T$5:$T$815,D8+1) -> 1.0330804 | I8: =INDEX(Panel!$S$5:$S$815,D8+1) -> -0.00013368028 | J8: =INDEX(Panel!$V$5:$V$815,D8+1) -> 0.0020419793 | K8: =(E8-G8-H8*F8-I8*D8)/J8 -> 2.2533909 | L8: 2 | M8: =IF(ABS(K8)>L8,"Yes","No") -> Yes | N8: 2023-09-29 09:45 | O8: 105 | P8: 19668.7 | Q8: 216.37 | R8: 2023-10-26 15:15 | S8: 122 | T8: 18859 | U8: 208.8 | V8: expiry | W8: =B8*((LN(T8)-LN(P8))-(LN(U8)-LN(Q8))) -> 0.006425237 | X8: =IF(INDEX(Panel!$A$5:$A$815,O8+1)<=DATE(2024,9,30),0.000625,IF(INDEX(Panel!$A$5:$A$815,O8+1)<=DATE(2026,3,31),0.001,0.0015))*(0.3989*Inputs!$B$28*SQRT(MAX(INDEX(Panel!$G$5:$G$815,O8+1),0)/365))+2*Inputs!$B$29+Inputs!$B$19+0.00003*(0.3989*Inputs!$B$28*SQRT(MAX(INDEX(Panel!$G$5:$G$815,O8+1),0)/365))+IF(B8<0,(Inputs!$B$20+Inputs!$B$22+Inputs!$B$23),(Inputs!$B$21+Inputs!$B$22+Inputs!$B$23)) -> 0.00046494876 | Y8: =IF(V8="expiry",IF(INDEX(Panel!$A$5:$A$815,S8+1)<=DATE(2026,3,31),0.00125,0.0015)*IF(B8<0,MAX(P8-T8,0),MAX(T8-P8,0))/T8,IF(INDEX(Panel!$A$5:$A$815,S8+1)<=DATE(2024,9,30),0.000625,IF(INDEX(Panel!$A$5:$A$815,S8+1)<=DATE(2026,3,31),0.001,0.0015))*(0.3989*Inputs!$B$28*SQRT(MAX(INDEX(Panel!$G$5:$G$815,S8+1),0)/365))+2*Inputs!$B$29+Inputs!$B$19)+IF(B8<0,(Inputs!$B$21+Inputs!$B$22+Inputs!$B$23),(Inputs!$B$20+Inputs!$B$22+Inputs!$B$23)) -> 0.00026366801 | Z8: =B8*SUMPRODUCT((Panel!$F$5:$F$815>=O8)*(Panel!$F$5:$F$815<S8)*Panel!$N$5:$N$815*Panel!$BD$5:$BD$815)/365 -> -0.0048082192 | AA8: =W8-X8-Y8+Z8 -> 0.00088840106 | AB8: 0.00088840106 | AC8: =AA8-AB8 -> 9.2157185e-18
A9: signal | B9: -1 | C9: 2023-10-27 09:15 | D9: 123 | E9: 9.8546649 | F9: 5.3460594 | G9: =INDEX(Panel!$U$5:$U$815,D9+1) -> 4.3831546 | H9: =INDEX(Panel!$T$5:$T$815,D9+1) -> 1.025347 | I9: =INDEX(Panel!$S$5:$S$815,D9+1) -> -0.00012000142 | J9: =INDEX(Panel!$V$5:$V$815,D9+1) -> 0.0020221093 | K9: =(E9-G9-H9*F9-I9*D9)/J9 -> 2.32663 | L9: 2 | M9: =IF(ABS(K9)>L9,"Yes","No") -> Yes | N9: 2023-10-27 09:30 | O9: 123 | P9: 19066.4 | Q9: 209.98 | R9: 2023-11-30 15:15 | S9: 145 | T9: 20134 | U9: 222.23 | V9: expiry | W9: =B9*((LN(T9)-LN(P9))-(LN(U9)-LN(Q9))) -> 0.0022182888 | X9: =IF(INDEX(Panel!$A$5:$A$815,O9+1)<=DATE(2024,9,30),0.000625,IF(INDEX(Panel!$A$5:$A$815,O9+1)<=DATE(2026,3,31),0.001,0.0015))*(0.3989*Inputs!$B$28*SQRT(MAX(INDEX(Panel!$G$5:$G$815,O9+1),0)/365))+2*Inputs!$B$29+Inputs!$B$19+0.00003*(0.3989*Inputs!$B$28*SQRT(MAX(INDEX(Panel!$G$5:$G$815,O9+1),0)/365))+IF(B9<0,(Inputs!$B$20+Inputs!$B$22+Inputs!$B$23),(Inputs!$B$21+Inputs!$B$22+Inputs!$B$23)) -> 0.00046616417 | Y9: =IF(V9="expiry",IF(INDEX(Panel!$A$5:$A$815,S9+1)<=DATE(2026,3,31),0.00125,0.0015)*IF(B9<0,MAX(P9-T9,0),MAX(T9-P9,0))/T9,IF(INDEX(Panel!$A$5:$A$815,S9+1)<=DATE(2024,9,30),0.000625,IF(INDEX(Panel!$A$5:$A$815,S9+1)<=DATE(2026,3,31),0.001,0.0015))*(0.3989*Inputs!$B$28*SQRT(MAX(INDEX(Panel!$G$5:$G$815,S9+1),0)/365))+2*Inputs!$B$29+Inputs!$B$19)+IF(B9<0,(Inputs!$B$21+Inputs!$B$22+Inputs!$B$23),(Inputs!$B$20+Inputs!$B$22+Inputs!$B$23)) -> 0.00021 | Z9: =B9*SUMPRODUCT((Panel!$F$5:$F$815>=O9)*(Panel!$F$5:$F$815<S9)*Panel!$N$5:$N$815*Panel!$BD$5:$BD$815)/365 -> -0.0060547945 | AA9: =W9-X9-Y9+Z9 -> -0.0045126699 | AB9: -0.0045126699 | AC9: =AA9-AB9 -> -3.469447e-17
A10: signal | B10: -1 | C10: 2023-12-01 09:15 | D10: 146 | E10: 9.9212268 | F10: 5.4076201 | G10: =INDEX(Panel!$U$5:$U$815,D10+1) -> 4.6018034 | H10: =INDEX(Panel!$T$5:$T$815,D10+1) -> 0.98395675 | I10: =INDEX(Panel!$S$5:$S$815,D10+1) -> -6.5832204e-05 | J10: =INDEX(Panel!$V$5:$V$815,D10+1) -> 0.0023156597 | K10: =(E10-G10-H10*F10-I10*D10)/J10 -> 3.5283871 | L10: 2 | M10: =IF(ABS(K10)>L10,"Yes","No") -> Yes | N10: 2023-12-01 09:30 | O10: 146 | P10: 20346.6 | Q10: 223 | R10: 2023-12-28 15:15 | S10: 164 | T10: 21780.75 | U10: 240.24 | V10: expiry | W10: =B10*((LN(T10)-LN(P10))-(LN(U10)-LN(Q10))) -> 0.0063539218 | X10: =IF(INDEX(Panel!$A$5:$A$815,O10+1)<=DATE(2024,9,30),0.000625,IF(INDEX(Panel!$A$5:$A$815,O10+1)<=DATE(2026,3,31),0.001,0.0015))*(0.3989*Inputs!$B$28*SQRT(MAX(INDEX(Panel!$G$5:$G$815,O10+1),0)/365))+2*Inputs!$B$29+Inputs!$B$19+0.00003*(0.3989*Inputs!$B$28*SQRT(MAX(INDEX(Panel!$G$5:$G$815,O10+1),0)/365))+IF(B10<0,(Inputs!$B$20+Inputs!$B$22+Inputs!$B$23),(Inputs!$B$21+Inputs!$B$22+Inputs!$B$23)) -> 0.00046494876 | Y10: =IF(V10="expiry",IF(INDEX(Panel!$A$5:$A$815,S10+1)<=DATE(2026,3,31),0.00125,0.0015)*IF(B10<0,MAX(P10-T10,0),MAX(T10-P10,0))/T10,IF(INDEX(Panel!$A$5:$A$815,S10+1)<=DATE(2024,9,30),0.000625,IF(INDEX(Panel!$A$5:$A$815,S10+1)<=DATE(2026,3,31),0.001,0.0015))*(0.3989*Inputs!$B$28*SQRT(MAX(INDEX(Panel!$G$5:$G$815,S10+1),0)/365))+2*Inputs!$B$29+Inputs!$B$19)+IF(B10<0,(Inputs!$B$21+Inputs!$B$22+Inputs!$B$23),(Inputs!$B$20+Inputs!$B$22+Inputs!$B$23)) -> 0.00021 | Z10: =B10*SUMPRODUCT((Panel!$F$5:$F$815>=O10)*(Panel!$F$5:$F$815<S10)*Panel!$N$5:$N$815*Panel!$BD$5:$BD$815)/365 -> -0.0048082192 | AA10: =W10-X10-Y10+Z10 -> 0.00087075387 | AB10: 0.00087075387 | AC10: =AA10-AB10 -> 9.3783488e-17
A11: signal | B11: -1 | C11: 2023-12-29 09:15 | D11: 165 | E11: 9.9947418 | F11: 5.4802222 | G11: =INDEX(Panel!$U$5:$U$815,D11+1) -> 4.3928634 | H11: =INDEX(Panel!$T$5:$T$815,D11+1) -> 1.0231243 | I11: =INDEX(Panel!$S$5:$S$815,D11+1) -> -7.2978375e-05 | J11: =INDEX(Panel!$V$5:$V$815,D11+1) -> 0.002675989 | K11: =(E11-G11-H11*F11-I11*D11)/J11 -> 2.6050725 | L11: 2 | M11: =IF(ABS(K11)>L11,"Yes","No") -> Yes | N11: 2023-12-29 09:30 | O11: 165 | P11: 21895.85 | Q11: 239.89 | R11: 2024-01-25 15:15 | S11: 184 | T11: 21351 | U11: 236.7 | V11: expiry | W11: =B11*((LN(T11)-LN(P11))-(LN(U11)-LN(Q11))) -> 0.011811576 | X11: =IF(INDEX(Panel!$A$5:$A$815,O11+1)<=DATE(2024,9,30),0.000625,IF(INDEX(Panel!$A$5:$A$815,O11+1)<=DATE(2026,3,31),0.001,0.0015))*(0.3989*Inputs!$B$28*SQRT(MAX(INDEX(Panel!$G$5:$G$815,O11+1),0)/365))+2*Inputs!$B$29+Inputs!$B$19+0.00003*(0.3989*Inputs!$B$28*SQRT(MAX(INDEX(Panel!$G$5:$G$815,O11+1),0)/365))+IF(B11<0,(Inputs!$B$20+Inputs!$B$22+Inputs!$B$23),(Inputs!$B$21+Inputs!$B$22+Inputs!$B$23)) -> 0.00046494876 | Y11: =IF(V11="expiry",IF(INDEX(Panel!$A$5:$A$815,S11+1)<=DATE(2026,3,31),0.00125,0.0015)*IF(B11<0,MAX(P11-T11,0),MAX(T11-P11,0))/T11,IF(INDEX(Panel!$A$5:$A$815,S11+1)<=DATE(2024,9,30),0.000625,IF(INDEX(Panel!$A$5:$A$815,S11+1)<=DATE(2026,3,31),0.001,0.0015))*(0.3989*Inputs!$B$28*SQRT(MAX(INDEX(Panel!$G$5:$G$815,S11+1),0)/365))+2*Inputs!$B$29+Inputs!$B$19)+IF(B11<0,(Inputs!$B$21+Inputs!$B$22+Inputs!$B$23),(Inputs!$B$20+Inputs!$B$22+Inputs!$B$23)) -> 0.00024189839 | Z11: =B11*SUMPRODUCT((Panel!$F$5:$F$815>=O11)*(Panel!$F$5:$F$815<S11)*Panel!$N$5:$N$815*Panel!$BD$5:$BD$815)/365 -> -0.0048082192 | AA11: =W11-X11-Y11+Z11 -> 0.0062965094 | AB11: 0.0062965094 | AC11: =AA11-AB11 -> 0
A12: signal | B12: -1 | C12: 2024-01-29 09:15 | D12: 185 | E12: 9.9850998 | F12: 5.4734884 | G12: =INDEX(Panel!$U$5:$U$815,D12+1) -> 4.3625945 | H12: =INDEX(Panel!$T$5:$T$815,D12+1) -> 1.0288252 | I12: =INDEX(Panel!$S$5:$S$815,D12+1) -> -7.6640707e-05 | J12: =INDEX(Panel!$V$5:$V$815,D12+1) -> 0.0026490065 | K12: =(E12-G12-H12*F12-I12*D12)/J12 -> 2.0465126 | L12: 2 | M12: =IF(ABS(K12)>L12,"Yes","No") -> Yes | N12: 2024-01-29 09:30 | O12: 185 | P12: 21692.6 | Q12: 238.39 | R12: 2024-02-29 15:15 | S12: 208 | T12: 21985.7 | U12: 243.9 | V12: expiry | W12: =B12*((LN(T12)-LN(P12))-(LN(U12)-LN(Q12))) -> 0.0094292638 | X12: =IF(INDEX(Panel!$A$5:$A$815,O12+1)<=DATE(2024,9,30),0.000625,IF(INDEX(Panel!$A$5:$A$815,O12+1)<=DATE(2026,3,31),0.001,0.0015))*(0.3989*Inputs!$B$28*SQRT(MAX(INDEX(Panel!$G$5:$G$815,O12+1),0)/365))+2*Inputs!$B$29+Inputs!$B$19+0.00003*(0.3989*Inputs!$B$28*SQRT(MAX(INDEX(Panel!$G$5:$G$815,O12+1),0)/365))+IF(B12<0,(Inputs!$B$20+Inputs!$B$22+Inputs!$B$23),(Inputs!$B$21+Inputs!$B$22+Inputs!$B$23)) -> 0.00046566026 | Y12: =IF(V12="expiry",IF(INDEX(Panel!$A$5:$A$815,S12+1)<=DATE(2026,3,31),0.00125,0.0015)*IF(B12<0,MAX(P12-T12,0),MAX(T12-P12,0))/T12,IF(INDEX(Panel!$A$5:$A$815,S12+1)<=DATE(2024,9,30),0.000625,IF(INDEX(Panel!$A$5:$A$815,S12+1)<=DATE(2026,3,31),0.001,0.0015))*(0.3989*Inputs!$B$28*SQRT(MAX(INDEX(Panel!$G$5:$G$815,S12+1),0)/365))+2*Inputs!$B$29+Inputs!$B$19)+IF(B12<0,(Inputs!$B$21+Inputs!$B$22+Inputs!$B$23),(Inputs!$B$20+Inputs!$B$22+Inputs!$B$23)) -> 0.00021 | Z12: =B12*SUMPRODUCT((Panel!$F$5:$F$815>=O12)*(Panel!$F$5:$F$815<S12)*Panel!$N$5:$N$815*Panel!$BD$5:$BD$815)/365 -> -0.0055205479 | AA12: =W12-X12-Y12+Z12 -> 0.0032330556 | AB12: 0.0032330556 | AC12: =AA12-AB12 -> 1.5612511e-17
A13: signal | B13: -1 | C13: 2024-03-01 11:15 | D13: 209 | E13: 10.014935 | F13: 5.5041113 | G13: =INDEX(Panel!$U$5:$U$815,D13+1) -> 4.3539923 | H13: =INDEX(Panel!$T$5:$T$815,D13+1) -> 1.0304329 | I13: =INDEX(Panel!$S$5:$S$815,D13+1) -> -7.6518134e-05 | J13: =INDEX(Panel!$V$5:$V$815,D13+1) -> 0.0026173972 | K13: =(E13-G13-H13*F13-I13*D13)/J13 -> 2.0317083 | L13: 2 | M13: =IF(ABS(K13)>L13,"Yes","No") -> Yes | N13: 2024-03-01 11:30 | O13: 209 | P13: 22392 | Q13: 246.12 | R13: 2024-03-28 15:15 | S13: 227 | T13: 22328.5 | U13: 247.1 | V13: expiry | W13: =B13*((LN(T13)-LN(P13))-(LN(U13)-LN(Q13))) -> 0.0068137539 | X13: =IF(INDEX(Panel!$A$5:$A$815,O13+1)<=DATE(2024,9,30),0.000625,IF(INDEX(Panel!$A$5:$A$815,O13+1)<=DATE(2026,3,31),0.001,0.0015))*(0.3989*Inputs!$B$28*SQRT(MAX(INDEX(Panel!$G$5:$G$815,O13+1),0)/365))+2*Inputs!$B$29+Inputs!$B$19+0.00003*(0.3989*Inputs!$B$28*SQRT(MAX(INDEX(Panel!$G$5:$G$815,O13+1),0)/365))+IF(B13<0,(Inputs!$B$20+Inputs!$B$22+Inputs!$B$23),(Inputs!$B$21+Inputs!$B$22+Inputs!$B$23)) -> 0.00046494876 | Y13: =IF(V13="expiry",IF(INDEX(Panel!$A$5:$A$815,S13+1)<=DATE(2026,3,31),0.00125,0.0015)*IF(B13<0,MAX(P13-T13,0),MAX(T13-P13,0))/T13,IF(INDEX(Panel!$A$5:$A$815,S13+1)<=DATE(2024,9,30),0.000625,IF(INDEX(Panel!$A$5:$A$815,S13+1)<=DATE(2026,3,31),0.001,0.0015))*(0.3989*Inputs!$B$28*SQRT(MAX(INDEX(Panel!$G$5:$G$815,S13+1),0)/365))+2*Inputs!$B$29+Inputs!$B$19)+IF(B13<0,(Inputs!$B$21+Inputs!$B$22+Inputs!$B$23),(Inputs!$B$20+Inputs!$B$22+Inputs!$B$23)) -> 0.00021355487 | Z13: =B13*SUMPRODUCT((Panel!$F$5:$F$815>=O13)*(Panel!$F$5:$F$815<S13)*Panel!$N$5:$N$815*Panel!$BD$5:$BD$815)/365 -> -0.0048082192 | AA13: =W13-X13-Y13+Z13 -> 0.0013270311 | AB13: 0.0013270311 | AC13: =AA13-AB13 -> 4.7704896e-18
A14: signal | B14: -1 | C14: 2024-04-01 11:45 | D14: 228 | E14: 10.026236 | F14: 5.5155233 | G14: =INDEX(Panel!$U$5:$U$815,D14+1) -> 4.3431878 | H14: =INDEX(Panel!$T$5:$T$815,D14+1) -> 1.0324051 | I14: =INDEX(Panel!$S$5:$S$815,D14+1) -> -7.3305293e-05 | J14: =INDEX(Panel!$V$5:$V$815,D14+1) -> 0.0026109863 | K14: =(E14-G14-H14*F14-I14*D14)/J14 -> 2.109289 | L14: 2 | M14: =IF(ABS(K14)>L14,"Yes","No") -> Yes | N14: 2024-04-01 12:00 | O14: 228 | P14: 22596.95 | Q14: 248.36 | R14: 2024-04-25 15:15 | S14: 244 | T14: 22574.7 | U14: 249.38 | V14: expiry | W14: =B14*((LN(T14)-LN(P14))-(LN(U14)-LN(Q14))) -> 0.0050836623 | X14: =IF(INDEX(Panel!$A$5:$A$815,O14+1)<=DATE(2024,9,30),0.000625,IF(INDEX(Panel!$A$5:$A$815,O14+1)<=DATE(2026,3,31),0.001,0.0015))*(0.3989*Inputs!$B$28*SQRT(MAX(INDEX(Panel!$G$5:$G$815,O14+1),0)/365))+2*Inputs!$B$29+Inputs!$B$19+0.00003*(0.3989*Inputs!$B$28*SQRT(MAX(INDEX(Panel!$G$5:$G$815,O14+1),0)/365))+IF(B14<0,(Inputs!$B$20+Inputs!$B$22+Inputs!$B$23),(Inputs!$B$21+Inputs!$B$22+Inputs!$B$23)) -> 0.00046437978 | Y14: =IF(V14="expiry",IF(INDEX(Panel!$A$5:$A$815,S14+1)<=DATE(2026,3,31),0.00125,0.0015)*IF(B14<0,MAX(P14-T14,0),MAX(T14-P14,0))/T14,IF(INDEX(Panel!$A$5:$A$815,S14+1)<=DATE(2024,9,30),0.000625,IF(INDEX(Panel!$A$5:$A$815,S14+1)<=DATE(2026,3,31),0.001,0.0015))*(0.3989*Inputs!$B$28*SQRT(MAX(INDEX(Panel!$G$5:$G$815,S14+1),0)/365))+2*Inputs!$B$29+Inputs!$B$19)+IF(B14<0,(Inputs!$B$21+Inputs!$B$22+Inputs!$B$23),(Inputs!$B$20+Inputs!$B$22+Inputs!$B$23)) -> 0.00021123202 | Z14: =B14*SUMPRODUCT((Panel!$F$5:$F$815>=O14)*(Panel!$F$5:$F$815<S14)*Panel!$N$5:$N$815*Panel!$BD$5:$BD$815)/365 -> -0.0042739726 | AA14: =W14-X14-Y14+Z14 -> 0.00013407791 | AB14: 0.00013407791 | AC14: =AA14-AB14 -> 2.997819e-17
A15: signal | B15: -1 | C15: 2024-04-26 11:15 | D15: 245 | E15: 10.027476 | F15: 5.5180551 | G15: =INDEX(Panel!$U$5:$U$815,D15+1) -> 4.3318274 | H15: =INDEX(Panel!$T$5:$T$815,D15+1) -> 1.0345313 | I15: =INDEX(Panel!$S$5:$S$815,D15+1) -> -7.393455e-05 | J15: =INDEX(Panel!$V$5:$V$815,D15+1) -> 0.0025806215 | K15: =(E15-G15-H15*F15-I15*D15)/J15 -> 2.0000918 | L15: 2 | M15: =IF(ABS(K15)>L15,"Yes","No") -> Yes | N15: 2024-04-26 11:30 | O15: 245 | P15: 22649 | Q15: 249.35 | R15: 2024-05-30 15:15 | S15: 268 | T15: 22487.75 | U15: 251 | V15: expiry | W15: =B15*((LN(T15)-LN(P15))-(LN(U15)-LN(Q15))) -> 0.013740391 | X15: =IF(INDEX(Panel!$A$5:$A$815,O15+1)<=DATE(2024,9,30),0.000625,IF(INDEX(Panel!$A$5:$A$815,O15+1)<=DATE(2026,3,31),0.001,0.0015))*(0.3989*Inputs!$B$28*SQRT(MAX(INDEX(Panel!$G$5:$G$815,O15+1),0)/365))+2*Inputs!$B$29+Inputs!$B$19+0.00003*(0.3989*Inputs!$B$28*SQRT(MAX(INDEX(Panel!$G$5:$G$815,O15+1),0)/365))+IF(B15<0,(Inputs!$B$20+Inputs!$B$22+Inputs!$B$23),(Inputs!$B$21+Inputs!$B$22+Inputs!$B$23)) -> 0.00046616417 | Y15: =IF(V15="expiry",IF(INDEX(Panel!$A$5:$A$815,S15+1)<=DATE(2026,3,31),0.00125,0.0015)*IF(B15<0,MAX(P15-T15,0),MAX(T15-P15,0))/T15,IF(INDEX(Panel!$A$5:$A$815,S15+1)<=DATE(2024,9,30),0.000625,IF(INDEX(Panel!$A$5:$A$815,S15+1)<=DATE(2026,3,31),0.001,0.0015))*(0.3989*Inputs!$B$28*SQRT(MAX(INDEX(Panel!$G$5:$G$815,S15+1),0)/365))+2*Inputs!$B$29+Inputs!$B$19)+IF(B15<0,(Inputs!$B$21+Inputs!$B$22+Inputs!$B$23),(Inputs!$B$20+Inputs!$B$22+Inputs!$B$23)) -> 0.00021896321 | Z15: =B15*SUMPRODUCT((Panel!$F$5:$F$815>=O15)*(Panel!$F$5:$F$815<S15)*Panel!$N$5:$N$815*Panel!$BD$5:$BD$815)/365 -> -0.0060547945 | AA15: =W15-X15-Y15+Z15 -> 0.0070004696 | AB15: 0.0070004696 | AC15: =AA15-AB15 -> 0
A16: signal | B16: 1 | C16: 2024-06-04 10:45 | D16: 271 | E16: 10.017048 | F16: 5.5194188 | G16: =INDEX(Panel!$U$5:$U$815,D16+1) -> 4.3271796 | H16: =INDEX(Panel!$T$5:$T$815,D16+1) -> 1.0351848 | I16: =INDEX(Panel!$S$5:$S$815,D16+1) -> -6.6531627e-05 | J16: =INDEX(Panel!$V$5:$V$815,D16+1) -> 0.0025584547 | K16: =(E16-G16-H16*F16-I16*D16)/J16 -> -2.2356965 | L16: 2 | M16: =IF(ABS(K16)>L16,"Yes","No") -> Yes | N16: 2024-06-04 11:00 | O16: 271 | P16: 22162.7 | Q16: 249.06 | R16: 2024-06-27 15:15 | S16: 287 | T16: 24047.1 | U16: 266.95 | V16: expiry | W16: =B16*((LN(T16)-LN(P16))-(LN(U16)-LN(Q16))) -> 0.012236168 | X16: =IF(INDEX(Panel!$A$5:$A$815,O16+1)<=DATE(2024,9,30),0.000625,IF(INDEX(Panel!$A$5:$A$815,O16+1)<=DATE(2026,3,31),0.001,0.0015))*(0.3989*Inputs!$B$28*SQRT(MAX(INDEX(Panel!$G$5:$G$815,O16+1),0)/365))+2*Inputs!$B$29+Inputs!$B$19+0.00003*(0.3989*Inputs!$B$28*SQRT(MAX(INDEX(Panel!$G$5:$G$815,O16+1),0)/365))+IF(B16<0,(Inputs!$B$20+Inputs!$B$22+Inputs!$B$23),(Inputs!$B$21+Inputs!$B$22+Inputs!$B$23)) -> 0.00032418229 | Y16: =IF(V16="expiry",IF(INDEX(Panel!$A$5:$A$815,S16+1)<=DATE(2026,3,31),0.00125,0.0015)*IF(B16<0,MAX(P16-T16,0),MAX(T16-P16,0))/T16,IF(INDEX(Panel!$A$5:$A$815,S16+1)<=DATE(2024,9,30),0.000625,IF(INDEX(Panel!$A$5:$A$815,S16+1)<=DATE(2026,3,31),0.001,0.0015))*(0.3989*Inputs!$B$28*SQRT(MAX(INDEX(Panel!$G$5:$G$815,S16+1),0)/365))+2*Inputs!$B$29+Inputs!$B$19)+IF(B16<0,(Inputs!$B$21+Inputs!$B$22+Inputs!$B$23),(Inputs!$B$20+Inputs!$B$22+Inputs!$B$23)) -> 0.0004479536 | Z16: =B16*SUMPRODUCT((Panel!$F$5:$F$815>=O16)*(Panel!$F$5:$F$815<S16)*Panel!$N$5:$N$815*Panel!$BD$5:$BD$815)/365 -> 0.0040958904 | AA16: =W16-X16-Y16+Z16 -> 0.015559922 | AB16: 0.015559922 | AC16: =AA16-AB16 -> 0
... A33: signal | B33: 1 | C33: 2026-07-20 09:45 | D33: 796 | E33: 10.093194 | F33: 5.6181883 | G33: =INDEX(Panel!$U$5:$U$815,D33+1) -> 4.3911888 | H33: =INDEX(Panel!$T$5:$T$815,D33+1) -> 1.0200356 | I33: =INDEX(Panel!$S$5:$S$815,D33+1) -> -3.0401227e-05 | J33: =INDEX(Panel!$V$5:$V$815,D33+1) -> 0.0022380783 | K33: =(E33-G33-H33*F33-I33*D33)/J33 -> -2.0316586 | L33: 2 | M33: =IF(ABS(K33)>L33,"Yes","No") -> Yes | N33: 2026-07-20 10:00 | O33: 796 | P33: 24190 | Q33: 275.6 | R33: 2026-07-28 15:15 | S33: 802 | T33: 23983.2 | U33: 273.81 | V33: expiry | W33: =B33*((LN(T33)-LN(P33))-(LN(U33)-LN(Q33))) -> -0.0020696354 | X33: =IF(INDEX(Panel!$A$5:$A$815,O33+1)<=DATE(2024,9,30),0.000625,IF(INDEX(Panel!$A$5:$A$815,O33+1)<=DATE(2026,3,31),0.001,0.0015))*(0.3989*Inputs!$B$28*SQRT(MAX(INDEX(Panel!$G$5:$G$815,O33+1),0)/365))+2*Inputs!$B$29+Inputs!$B$19+0.00003*(0.3989*Inputs!$B$28*SQRT(MAX(INDEX(Panel!$G$5:$G$815,O33+1),0)/365))+IF(B33<0,(Inputs!$B$20+Inputs!$B$22+Inputs!$B$23),(Inputs!$B$21+Inputs!$B$22+Inputs!$B$23)) -> 0.00032764975 | Y33: =IF(V33="expiry",IF(INDEX(Panel!$A$5:$A$815,S33+1)<=DATE(2026,3,31),0.00125,0.0015)*IF(B33<0,MAX(P33-T33,0),MAX(T33-P33,0))/T33,IF(INDEX(Panel!$A$5:$A$815,S33+1)<=DATE(2024,9,30),0.000625,IF(INDEX(Panel!$A$5:$A$815,S33+1)<=DATE(2026,3,31),0.001,0.0015))*(0.3989*Inputs!$B$28*SQRT(MAX(INDEX(Panel!$G$5:$G$815,S33+1),0)/365))+2*Inputs!$B$29+Inputs!$B$19)+IF(B33<0,(Inputs!$B$21+Inputs!$B$22+Inputs!$B$23),(Inputs!$B$20+Inputs!$B$22+Inputs!$B$23)) -> 0.00035 | Z33: =B33*SUMPRODUCT((Panel!$F$5:$F$815>=O33)*(Panel!$F$5:$F$815<S33)*Panel!$N$5:$N$815*Panel!$BD$5:$BD$815)/365 -> 0.0011506849 | AA33: =W33-X33-Y33+Z33 -> -0.0015966003 | AB33: -0.0015966003 | AC33: =AA33-AB33 -> -5.2475385e-17
A34: aarav | B34: -1 | C34: 2023-07-28 09:15 | D34: 62 | E34: 9.8899995 | F34: 5.3758801 | G34: =INDEX(Panel!$U$5:$U$815,D34+1) -> 4.2338414 | H34: =INDEX(Panel!$T$5:$T$815,D34+1) -> 1.0538075 | I34: =INDEX(Panel!$S$5:$S$815,D34+1) -> -0.00020051329 | J34: =INDEX(Panel!$V$5:$V$815,D34+1) -> 0.0016779358 | K34: =(E34-G34-H34*F34-I34*D34)/J34 -> 2.0543536 | L34: 1.5 | M34: =IF(ABS(K34)>L34,"Yes","No") -> Yes | N34: 2023-07-28 09:30 | O34: 62 | P34: 19748 | Q34: 216.35 | R34: 2023-08-31 15:15 | S34: 85 | T34: 19254 | U34: 213.2 | V34: expiry | W34: =B34*((LN(T34)-LN(P34))-(LN(U34)-LN(Q34))) -> 0.010666615 | X34: =IF(INDEX(Panel!$A$5:$A$815,O34+1)<=DATE(2024,9,30),0.000625,IF(INDEX(Panel!$A$5:$A$815,O34+1)<=DATE(2026,3,31),0.001,0.0015))*(0.3989*Inputs!$B$28*SQRT(MAX(INDEX(Panel!$G$5:$G$815,O34+1),0)/365))+2*Inputs!$B$29+Inputs!$B$19+0.00003*(0.3989*Inputs!$B$28*SQRT(MAX(INDEX(Panel!$G$5:$G$815,O34+1),0)/365))+IF(B34<0,(Inputs!$B$20+Inputs!$B$22+Inputs!$B$23),(Inputs!$B$21+Inputs!$B$22+Inputs!$B$23)) -> 0.00046616417 | Y34: =IF(V34="expiry",IF(INDEX(Panel!$A$5:$A$815,S34+1)<=DATE(2026,3,31),0.00125,0.0015)*IF(B34<0,MAX(P34-T34,0),MAX(T34-P34,0))/T34,IF(INDEX(Panel!$A$5:$A$815,S34+1)<=DATE(2024,9,30),0.000625,IF(INDEX(Panel!$A$5:$A$815,S34+1)<=DATE(2026,3,31),0.001,0.0015))*(0.3989*Inputs!$B$28*SQRT(MAX(INDEX(Panel!$G$5:$G$815,S34+1),0)/365))+2*Inputs!$B$29+Inputs!$B$19)+IF(B34<0,(Inputs!$B$21+Inputs!$B$22+Inputs!$B$23),(Inputs!$B$20+Inputs!$B$22+Inputs!$B$23)) -> 0.00024207126 | Z34: =-SUMPRODUCT((Panel!$F$5:$F$815>=O34)*(Panel!$F$5:$F$815<S34)*Panel!$N$5:$N$815*Panel!$BD$5:$BD$815)/365 -> -0.0060547945 | AA34: =W34-X34-Y34+Z34 -> 0.0039035847 | AB34: 0.0039035847 | AC34: =AA34-AB34 -> 5.7679556e-17
A35: aarav | B35: -1 | C35: 2023-09-01 09:15 | D35: 86 | E35: 9.8724612 | F35: 5.3609165 | G35: =INDEX(Panel!$U$5:$U$815,D35+1) -> 4.2252851 | H35: =INDEX(Panel!$T$5:$T$815,D35+1) -> 1.0553828 | I35: =INDEX(Panel!$S$5:$S$815,D35+1) -> -0.0001905105 | J35: =INDEX(Panel!$V$5:$V$815,D35+1) -> 0.0017694952 | K35: =(E35-G35-H35*F35-I35*D35)/J35 -> 3.2443583 | L35: 1.5 | M35: =IF(ABS(K35)>L35,"Yes","No") -> Yes | N35: 2023-09-01 09:30 | O35: 86 | P35: 19409 | Q35: 213.19 | R35: 2023-09-28 15:15 | S35: 104 | T35: 19525 | U35: 216.14 | V35: expiry | W35: =B35*((LN(T35)-LN(P35))-(LN(U35)-LN(Q35))) -> 0.0077837393 | X35: =IF(INDEX(Panel!$A$5:$A$815,O35+1)<=DATE(2024,9,30),0.000625,IF(INDEX(Panel!$A$5:$A$815,O35+1)<=DATE(2026,3,31),0.001,0.0015))*(0.3989*Inputs!$B$28*SQRT(MAX(INDEX(Panel!$G$5:$G$815,O35+1),0)/365))+2*Inputs!$B$29+Inputs!$B$19+0.00003*(0.3989*Inputs!$B$28*SQRT(MAX(INDEX(Panel!$G$5:$G$815,O35+1),0)/365))+IF(B35<0,(Inputs!$B$20+Inputs!$B$22+Inputs!$B$23),(Inputs!$B$21+Inputs!$B$22+Inputs!$B$23)) -> 0.00046494876 | Y35: =IF(V35="expiry",IF(INDEX(Panel!$A$5:$A$815,S35+1)<=DATE(2026,3,31),0.00125,0.0015)*IF(B35<0,MAX(P35-T35,0),MAX(T35-P35,0))/T35,IF(INDEX(Panel!$A$5:$A$815,S35+1)<=DATE(2024,9,30),0.000625,IF(INDEX(Panel!$A$5:$A$815,S35+1)<=DATE(2026,3,31),0.001,0.0015))*(0.3989*Inputs!$B$28*SQRT(MAX(INDEX(Panel!$G$5:$G$815,S35+1),0)/365))+2*Inputs!$B$29+Inputs!$B$19)+IF(B35<0,(Inputs!$B$21+Inputs!$B$22+Inputs!$B$23),(Inputs!$B$20+Inputs!$B$22+Inputs!$B$23)) -> 0.00021 | Z35: =-SUMPRODUCT((Panel!$F$5:$F$815>=O35)*(Panel!$F$5:$F$815<S35)*Panel!$N$5:$N$815*Panel!$BD$5:$BD$815)/365 -> -0.0048082192 | AA35: =W35-X35-Y35+Z35 -> 0.0023005714 | AB35: 0.0023005714 | AC35: =AA35-AB35 -> 3.3393427e-17
A36: aarav | B36: -1 | C36: 2023-09-29 09:15 | D36: 105 | E36: 9.8859853 | F36: 5.3759726 | G36: =INDEX(Panel!$U$5:$U$815,D36+1) -> 4.3423895 | H36: =INDEX(Panel!$T$5:$T$815,D36+1) -> 1.0330804 | I36: =INDEX(Panel!$S$5:$S$815,D36+1) -> -0.00013368028 | J36: =INDEX(Panel!$V$5:$V$815,D36+1) -> 0.0020419793 | K36: =(E36-G36-H36*F36-I36*D36)/J36 -> 1.8707951 | L36: 1.5 | M36: =IF(ABS(K36)>L36,"Yes","No") -> Yes | N36: 2023-09-29 09:30 | O36: 105 | P36: 19669.3 | Q36: 216.16 | R36: 2023-10-26 15:15 | S36: 122 | T36: 18859 | U36: 208.8 | V36: expiry | W36: =B36*((LN(T36)-LN(P36))-(LN(U36)-LN(Q36))) -> 0.0074267728 | X36: =IF(INDEX(Panel!$A$5:$A$815,O36+1)<=DATE(2024,9,30),0.000625,IF(INDEX(Panel!$A$5:$A$815,O36+1)<=DATE(2026,3,31),0.001,0.0015))*(0.3989*Inputs!$B$28*SQRT(MAX(INDEX(Panel!$G$5:$G$815,O36+1),0)/365))+2*Inputs!$B$29+Inputs!$B$19+0.00003*(0.3989*Inputs!$B$28*SQRT(MAX(INDEX(Panel!$G$5:$G$815,O36+1),0)/365))+IF(B36<0,(Inputs!$B$20+Inputs!$B$22+Inputs!$B$23),(Inputs!$B$21+Inputs!$B$22+Inputs!$B$23)) -> 0.00046494876 | Y36: =IF(V36="expiry",IF(INDEX(Panel!$A$5:$A$815,S36+1)<=DATE(2026,3,31),0.00125,0.0015)*IF(B36<0,MAX(P36-T36,0),MAX(T36-P36,0))/T36,IF(INDEX(Panel!$A$5:$A$815,S36+1)<=DATE(2024,9,30),0.000625,IF(INDEX(Panel!$A$5:$A$815,S36+1)<=DATE(2026,3,31),0.001,0.0015))*(0.3989*Inputs!$B$28*SQRT(MAX(INDEX(Panel!$G$5:$G$815,S36+1),0)/365))+2*Inputs!$B$29+Inputs!$B$19)+IF(B36<0,(Inputs!$B$21+Inputs!$B$22+Inputs!$B$23),(Inputs!$B$20+Inputs!$B$22+Inputs!$B$23)) -> 0.00026370778 | Z36: =-SUMPRODUCT((Panel!$F$5:$F$815>=O36)*(Panel!$F$5:$F$815<S36)*Panel!$N$5:$N$815*Panel!$BD$5:$BD$815)/365 -> -0.0048082192 | AA36: =W36-X36-Y36+Z36 -> 0.0018898971 | AB36: 0.0018898971 | AC36: =AA36-AB36 -> 9.4325589e-17
A37: aarav | B37: -1 | C37: 2023-10-27 09:15 | D37: 123 | E37: 9.8546649 | F37: 5.3460594 | G37: =INDEX(Panel!$U$5:$U$815,D37+1) -> 4.3831546 | H37: =INDEX(Panel!$T$5:$T$815,D37+1) -> 1.025347 | I37: =INDEX(Panel!$S$5:$S$815,D37+1) -> -0.00012000142 | J37: =INDEX(Panel!$V$5:$V$815,D37+1) -> 0.0020221093 | K37: =(E37-G37-H37*F37-I37*D37)/J37 -> 2.32663 | L37: 1.5 | M37: =IF(ABS(K37)>L37,"Yes","No") -> Yes | N37: 2023-10-27 09:30 | O37: 123 | P37: 19066.4 | Q37: 209.98 | R37: 2023-11-30 15:15 | S37: 145 | T37: 20134 | U37: 222.23 | V37: expiry | W37: =B37*((LN(T37)-LN(P37))-(LN(U37)-LN(Q37))) -> 0.0022182888 | X37: =IF(INDEX(Panel!$A$5:$A$815,O37+1)<=DATE(2024,9,30),0.000625,IF(INDEX(Panel!$A$5:$A$815,O37+1)<=DATE(2026,3,31),0.001,0.0015))*(0.3989*Inputs!$B$28*SQRT(MAX(INDEX(Panel!$G$5:$G$815,O37+1),0)/365))+2*Inputs!$B$29+Inputs!$B$19+0.00003*(0.3989*Inputs!$B$28*SQRT(MAX(INDEX(Panel!$G$5:$G$815,O37+1),0)/365))+IF(B37<0,(Inputs!$B$20+Inputs!$B$22+Inputs!$B$23),(Inputs!$B$21+Inputs!$B$22+Inputs!$B$23)) -> 0.00046616417 | Y37: =IF(V37="expiry",IF(INDEX(Panel!$A$5:$A$815,S37+1)<=DATE(2026,3,31),0.00125,0.0015)*IF(B37<0,MAX(P37-T37,0),MAX(T37-P37,0))/T37,IF(INDEX(Panel!$A$5:$A$815,S37+1)<=DATE(2024,9,30),0.000625,IF(INDEX(Panel!$A$5:$A$815,S37+1)<=DATE(2026,3,31),0.001,0.0015))*(0.3989*Inputs!$B$28*SQRT(MAX(INDEX(Panel!$G$5:$G$815,S37+1),0)/365))+2*Inputs!$B$29+Inputs!$B$19)+IF(B37<0,(Inputs!$B$21+Inputs!$B$22+Inputs!$B$23),(Inputs!$B$20+Inputs!$B$22+Inputs!$B$23)) -> 0.00021 | Z37: =-SUMPRODUCT((Panel!$F$5:$F$815>=O37)*(Panel!$F$5:$F$815<S37)*Panel!$N$5:$N$815*Panel!$BD$5:$BD$815)/365 -> -0.0060547945 | AA37: =W37-X37-Y37+Z37 -> -0.0045126699 | AB37: -0.0045126699 | AC37: =AA37-AB37 -> -3.469447e-17
A38: aarav | B38: -1 | C38: 2023-12-01 09:15 | D38: 146 | E38: 9.9212268 | F38: 5.4076201 | G38: =INDEX(Panel!$U$5:$U$815,D38+1) -> 4.6018034 | H38: =INDEX(Panel!$T$5:$T$815,D38+1) -> 0.98395675 | I38: =INDEX(Panel!$S$5:$S$815,D38+1) -> -6.5832204e-05 | J38: =INDEX(Panel!$V$5:$V$815,D38+1) -> 0.0023156597 | K38: =(E38-G38-H38*F38-I38*D38)/J38 -> 3.5283871 | L38: 1.5 | M38: =IF(ABS(K38)>L38,"Yes","No") -> Yes | N38: 2023-12-01 09:30 | O38: 146 | P38: 20346.6 | Q38: 223 | R38: 2023-12-28 15:15 | S38: 164 | T38: 21780.75 | U38: 240.24 | V38: expiry | W38: =B38*((LN(T38)-LN(P38))-(LN(U38)-LN(Q38))) -> 0.0063539218 | X38: =IF(INDEX(Panel!$A$5:$A$815,O38+1)<=DATE(2024,9,30),0.000625,IF(INDEX(Panel!$A$5:$A$815,O38+1)<=DATE(2026,3,31),0.001,0.0015))*(0.3989*Inputs!$B$28*SQRT(MAX(INDEX(Panel!$G$5:$G$815,O38+1),0)/365))+2*Inputs!$B$29+Inputs!$B$19+0.00003*(0.3989*Inputs!$B$28*SQRT(MAX(INDEX(Panel!$G$5:$G$815,O38+1),0)/365))+IF(B38<0,(Inputs!$B$20+Inputs!$B$22+Inputs!$B$23),(Inputs!$B$21+Inputs!$B$22+Inputs!$B$23)) -> 0.00046494876 | Y38: =IF(V38="expiry",IF(INDEX(Panel!$A$5:$A$815,S38+1)<=DATE(2026,3,31),0.00125,0.0015)*IF(B38<0,MAX(P38-T38,0),MAX(T38-P38,0))/T38,IF(INDEX(Panel!$A$5:$A$815,S38+1)<=DATE(2024,9,30),0.000625,IF(INDEX(Panel!$A$5:$A$815,S38+1)<=DATE(2026,3,31),0.001,0.0015))*(0.3989*Inputs!$B$28*SQRT(MAX(INDEX(Panel!$G$5:$G$815,S38+1),0)/365))+2*Inputs!$B$29+Inputs!$B$19)+IF(B38<0,(Inputs!$B$21+Inputs!$B$22+Inputs!$B$23),(Inputs!$B$20+Inputs!$B$22+Inputs!$B$23)) -> 0.00021 | Z38: =-SUMPRODUCT((Panel!$F$5:$F$815>=O38)*(Panel!$F$5:$F$815<S38)*Panel!$N$5:$N$815*Panel!$BD$5:$BD$815)/365 -> -0.0048082192 | AA38: =W38-X38-Y38+Z38 -> 0.00087075387 | AB38: 0.00087075387 | AC38: =AA38-AB38 -> 9.3783488e-17
A39: aarav | B39: -1 | C39: 2023-12-29 09:15 | D39: 165 | E39: 9.9947418 | F39: 5.4802222 | G39: =INDEX(Panel!$U$5:$U$815,D39+1) -> 4.3928634 | H39: =INDEX(Panel!$T$5:$T$815,D39+1) -> 1.0231243 | I39: =INDEX(Panel!$S$5:$S$815,D39+1) -> -7.2978375e-05 | J39: =INDEX(Panel!$V$5:$V$815,D39+1) -> 0.002675989 | K39: =(E39-G39-H39*F39-I39*D39)/J39 -> 2.6050725 | L39: 1.5 | M39: =IF(ABS(K39)>L39,"Yes","No") -> Yes | N39: 2023-12-29 09:30 | O39: 165 | P39: 21895.85 | Q39: 239.89 | R39: 2024-01-25 15:15 | S39: 184 | T39: 21351 | U39: 236.7 | V39: expiry | W39: =B39*((LN(T39)-LN(P39))-(LN(U39)-LN(Q39))) -> 0.011811576 | X39: =IF(INDEX(Panel!$A$5:$A$815,O39+1)<=DATE(2024,9,30),0.000625,IF(INDEX(Panel!$A$5:$A$815,O39+1)<=DATE(2026,3,31),0.001,0.0015))*(0.3989*Inputs!$B$28*SQRT(MAX(INDEX(Panel!$G$5:$G$815,O39+1),0)/365))+2*Inputs!$B$29+Inputs!$B$19+0.00003*(0.3989*Inputs!$B$28*SQRT(MAX(INDEX(Panel!$G$5:$G$815,O39+1),0)/365))+IF(B39<0,(Inputs!$B$20+Inputs!$B$22+Inputs!$B$23),(Inputs!$B$21+Inputs!$B$22+Inputs!$B$23)) -> 0.00046494876 | Y39: =IF(V39="expiry",IF(INDEX(Panel!$A$5:$A$815,S39+1)<=DATE(2026,3,31),0.00125,0.0015)*IF(B39<0,MAX(P39-T39,0),MAX(T39-P39,0))/T39,IF(INDEX(Panel!$A$5:$A$815,S39+1)<=DATE(2024,9,30),0.000625,IF(INDEX(Panel!$A$5:$A$815,S39+1)<=DATE(2026,3,31),0.001,0.0015))*(0.3989*Inputs!$B$28*SQRT(MAX(INDEX(Panel!$G$5:$G$815,S39+1),0)/365))+2*Inputs!$B$29+Inputs!$B$19)+IF(B39<0,(Inputs!$B$21+Inputs!$B$22+Inputs!$B$23),(Inputs!$B$20+Inputs!$B$22+Inputs!$B$23)) -> 0.00024189839 | Z39: =-SUMPRODUCT((Panel!$F$5:$F$815>=O39)*(Panel!$F$5:$F$815<S39)*Panel!$N$5:$N$815*Panel!$BD$5:$BD$815)/365 -> -0.0048082192 | AA39: =W39-X39-Y39+Z39 -> 0.0062965094 | AB39: 0.0062965094 | AC39: =AA39-AB39 -> 0
A40: aarav | B40: -1 | C40: 2024-01-29 09:15 | D40: 185 | E40: 9.9850998 | F40: 5.4734884 | G40: =INDEX(Panel!$U$5:$U$815,D40+1) -> 4.3625945 | H40: =INDEX(Panel!$T$5:$T$815,D40+1) -> 1.0288252 | I40: =INDEX(Panel!$S$5:$S$815,D40+1) -> -7.6640707e-05 | J40: =INDEX(Panel!$V$5:$V$815,D40+1) -> 0.0026490065 | K40: =(E40-G40-H40*F40-I40*D40)/J40 -> 2.0465126 | L40: 1.5 | M40: =IF(ABS(K40)>L40,"Yes","No") -> Yes | N40: 2024-01-29 09:30 | O40: 185 | P40: 21692.6 | Q40: 238.39 | R40: 2024-02-29 15:15 | S40: 208 | T40: 21985.7 | U40: 243.9 | V40: expiry | W40: =B40*((LN(T40)-LN(P40))-(LN(U40)-LN(Q40))) -> 0.0094292638 | X40: =IF(INDEX(Panel!$A$5:$A$815,O40+1)<=DATE(2024,9,30),0.000625,IF(INDEX(Panel!$A$5:$A$815,O40+1)<=DATE(2026,3,31),0.001,0.0015))*(0.3989*Inputs!$B$28*SQRT(MAX(INDEX(Panel!$G$5:$G$815,O40+1),0)/365))+2*Inputs!$B$29+Inputs!$B$19+0.00003*(0.3989*Inputs!$B$28*SQRT(MAX(INDEX(Panel!$G$5:$G$815,O40+1),0)/365))+IF(B40<0,(Inputs!$B$20+Inputs!$B$22+Inputs!$B$23),(Inputs!$B$21+Inputs!$B$22+Inputs!$B$23)) -> 0.00046566026 | Y40: =IF(V40="expiry",IF(INDEX(Panel!$A$5:$A$815,S40+1)<=DATE(2026,3,31),0.00125,0.0015)*IF(B40<0,MAX(P40-T40,0),MAX(T40-P40,0))/T40,IF(INDEX(Panel!$A$5:$A$815,S40+1)<=DATE(2024,9,30),0.000625,IF(INDEX(Panel!$A$5:$A$815,S40+1)<=DATE(2026,3,31),0.001,0.0015))*(0.3989*Inputs!$B$28*SQRT(MAX(INDEX(Panel!$G$5:$G$815,S40+1),0)/365))+2*Inputs!$B$29+Inputs!$B$19)+IF(B40<0,(Inputs!$B$21+Inputs!$B$22+Inputs!$B$23),(Inputs!$B$20+Inputs!$B$22+Inputs!$B$23)) -> 0.00021 | Z40: =-SUMPRODUCT((Panel!$F$5:$F$815>=O40)*(Panel!$F$5:$F$815<S40)*Panel!$N$5:$N$815*Panel!$BD$5:$BD$815)/365 -> -0.0055205479 | AA40: =W40-X40-Y40+Z40 -> 0.0032330556 | AB40: 0.0032330556 | AC40: =AA40-AB40 -> 1.5612511e-17
A41: aarav | B41: -1 | C41: 2024-03-01 09:15 | D41: 209 | E41: 10.009906 | F41: 5.4995016 | G41: =INDEX(Panel!$U$5:$U$815,D41+1) -> 4.3539923 | H41: =INDEX(Panel!$T$5:$T$815,D41+1) -> 1.0304329 | I41: =INDEX(Panel!$S$5:$S$815,D41+1) -> -7.6518134e-05 | J41: =INDEX(Panel!$V$5:$V$815,D41+1) -> 0.0026173972 | K41: =(E41-G41-H41*F41-I41*D41)/J41 -> 1.9252105 | L41: 1.5 | M41: =IF(ABS(K41)>L41,"Yes","No") -> Yes | N41: 2024-03-01 09:30 | O41: 209 | P41: 22275.15 | Q41: 244.98 | R41: 2024-03-28 15:15 | S41: 227 | T41: 22328.5 | U41: 247.1 | V41: expiry | W41: =B41*((LN(T41)-LN(P41))-(LN(U41)-LN(Q41))) -> 0.0062243564 | X41: =IF(INDEX(Panel!$A$5:$A$815,O41+1)<=DATE(2024,9,30),0.000625,IF(INDEX(Panel!$A$5:$A$815,O41+1)<=DATE(2026,3,31),0.001,0.0015))*(0.3989*Inputs!$B$28*SQRT(MAX(INDEX(Panel!$G$5:$G$815,O41+1),0)/365))+2*Inputs!$B$29+Inputs!$B$19+0.00003*(0.3989*Inputs!$B$28*SQRT(MAX(INDEX(Panel!$G$5:$G$815,O41+1),0)/365))+IF(B41<0,(Inputs!$B$20+Inputs!$B$22+Inputs!$B$23),(Inputs!$B$21+Inputs!$B$22+Inputs!$B$23)) -> 0.00046494876 | Y41: =IF(V41="expiry",IF(INDEX(Panel!$A$5:$A$815,S41+1)<=DATE(2026,3,31),0.00125,0.0015)*IF(B41<0,MAX(P41-T41,0),MAX(T41-P41,0))/T41,IF(INDEX(Panel!$A$5:$A$815,S41+1)<=DATE(2024,9,30),0.000625,IF(INDEX(Panel!$A$5:$A$815,S41+1)<=DATE(2026,3,31),0.001,0.0015))*(0.3989*Inputs!$B$28*SQRT(MAX(INDEX(Panel!$G$5:$G$815,S41+1),0)/365))+2*Inputs!$B$29+Inputs!$B$19)+IF(B41<0,(Inputs!$B$21+Inputs!$B$22+Inputs!$B$23),(Inputs!$B$20+Inputs!$B$22+Inputs!$B$23)) -> 0.00021 | Z41: =-SUMPRODUCT((Panel!$F$5:$F$815>=O41)*(Panel!$F$5:$F$815<S41)*Panel!$N$5:$N$815*Panel!$BD$5:$BD$815)/365 -> -0.0048082192 | AA41: =W41-X41-Y41+Z41 -> 0.00074118845 | AB41: 0.00074118845 | AC41: =AA41-AB41 -> 6.1691104e-17
A42: aarav | B42: -1 | C42: 2024-04-01 09:15 | D42: 228 | E42: 10.025778 | F42: 5.5157647 | G42: =INDEX(Panel!$U$5:$U$815,D42+1) -> 4.3431878 | H42: =INDEX(Panel!$T$5:$T$815,D42+1) -> 1.0324051 | I42: =INDEX(Panel!$S$5:$S$815,D42+1) -> -7.3305293e-05 | J42: =INDEX(Panel!$V$5:$V$815,D42+1) -> 0.0026109863 | K42: =(E42-G42-H42*F42-I42*D42)/J42 -> 1.8384913 | L42: 1.5 | M42: =IF(ABS(K42)>L42,"Yes","No") -> Yes | N42: 2024-04-01 09:30 | O42: 228 | P42: 22603.15 | Q42: 248.7 | R42: 2024-04-25 15:15 | S42: 244 | T42: 22574.7 | U42: 249.38 | V42: expiry | W42: =B42*((LN(T42)-LN(P42))-(LN(U42)-LN(Q42))) -> 0.0039899537 | X42: =IF(INDEX(Panel!$A$5:$A$815,O42+1)<=DATE(2024,9,30),0.000625,IF(INDEX(Panel!$A$5:$A$815,O42+1)<=DATE(2026,3,31),0.001,0.0015))*(0.3989*Inputs!$B$28*SQRT(MAX(INDEX(Panel!$G$5:$G$815,O42+1),0)/365))+2*Inputs!$B$29+Inputs!$B$19+0.00003*(0.3989*Inputs!$B$28*SQRT(MAX(INDEX(Panel!$G$5:$G$815,O42+1),0)/365))+IF(B42<0,(Inputs!$B$20+Inputs!$B$22+Inputs!$B$23),(Inputs!$B$21+Inputs!$B$22+Inputs!$B$23)) -> 0.00046437978 | Y42: =IF(V42="expiry",IF(INDEX(Panel!$A$5:$A$815,S42+1)<=DATE(2026,3,31),0.00125,0.0015)*IF(B42<0,MAX(P42-T42,0),MAX(T42-P42,0))/T42,IF(INDEX(Panel!$A$5:$A$815,S42+1)<=DATE(2024,9,30),0.000625,IF(INDEX(Panel!$A$5:$A$815,S42+1)<=DATE(2026,3,31),0.001,0.0015))*(0.3989*Inputs!$B$28*SQRT(MAX(INDEX(Panel!$G$5:$G$815,S42+1),0)/365))+2*Inputs!$B$29+Inputs!$B$19)+IF(B42<0,(Inputs!$B$21+Inputs!$B$22+Inputs!$B$23),(Inputs!$B$20+Inputs!$B$22+Inputs!$B$23)) -> 0.00021157533 | Z42: =-SUMPRODUCT((Panel!$F$5:$F$815>=O42)*(Panel!$F$5:$F$815<S42)*Panel!$N$5:$N$815*Panel!$BD$5:$BD$815)/365 -> -0.0042739726 | AA42: =W42-X42-Y42+Z42 -> -0.00095997403 | AB42: -0.00095997403 | AC42: =AA42-AB42 -> -9.97466e-17
A43: aarav | B43: -1 | C43: 2024-04-26 09:15 | D43: 245 | E43: 10.029695 | F43: 5.5203403 | G43: =INDEX(Panel!$U$5:$U$815,D43+1) -> 4.3318274 | H43: =INDEX(Panel!$T$5:$T$815,D43+1) -> 1.0345313 | I43: =INDEX(Panel!$S$5:$S$815,D43+1) -> -7.393455e-05 | J43: =INDEX(Panel!$V$5:$V$815,D43+1) -> 0.0025806215 | K43: =(E43-G43-H43*F43-I43*D43)/J43 -> 1.9439762 | L43: 1.5 | M43: =IF(ABS(K43)>L43,"Yes","No") -> Yes | N43: 2024-04-26 09:30 | O43: 245 | P43: 22689 | Q43: 249.77 | R43: 2024-05-30 15:15 | S43: 268 | T43: 22487.75 | U43: 251 | V43: expiry | W43: =B43*((LN(T43)-LN(P43))-(LN(U43)-LN(Q43))) -> 0.013821954 | X43: =IF(INDEX(Panel!$A$5:$A$815,O43+1)<=DATE(2024,9,30),0.000625,IF(INDEX(Panel!$A$5:$A$815,O43+1)<=DATE(2026,3,31),0.001,0.0015))*(0.3989*Inputs!$B$28*SQRT(MAX(INDEX(Panel!$G$5:$G$815,O43+1),0)/365))+2*Inputs!$B$29+Inputs!$B$19+0.00003*(0.3989*Inputs!$B$28*SQRT(MAX(INDEX(Panel!$G$5:$G$815,O43+1),0)/365))+IF(B43<0,(Inputs!$B$20+Inputs!$B$22+Inputs!$B$23),(Inputs!$B$21+Inputs!$B$22+Inputs!$B$23)) -> 0.00046616417 | Y43: =IF(V43="expiry",IF(INDEX(Panel!$A$5:$A$815,S43+1)<=DATE(2026,3,31),0.00125,0.0015)*IF(B43<0,MAX(P43-T43,0),MAX(T43-P43,0))/T43,IF(INDEX(Panel!$A$5:$A$815,S43+1)<=DATE(2024,9,30),0.000625,IF(INDEX(Panel!$A$5:$A$815,S43+1)<=DATE(2026,3,31),0.001,0.0015))*(0.3989*Inputs!$B$28*SQRT(MAX(INDEX(Panel!$G$5:$G$815,S43+1),0)/365))+2*Inputs!$B$29+Inputs!$B$19)+IF(B43<0,(Inputs!$B$21+Inputs!$B$22+Inputs!$B$23),(Inputs!$B$20+Inputs!$B$22+Inputs!$B$23)) -> 0.00022118665 | Z43: =-SUMPRODUCT((Panel!$F$5:$F$815>=O43)*(Panel!$F$5:$F$815<S43)*Panel!$N$5:$N$815*Panel!$BD$5:$BD$815)/365 -> -0.0060547945 | AA43: =W43-X43-Y43+Z43 -> 0.0070798084 | AB43: 0.0070798084 | AC43: =AA43-AB43 -> 6.3317407e-17
A44: aarav | B44: -1 | C44: 2024-06-03 15:15 | D44: 270 | E44: 10.062626 | F44: 5.5541217 | G44: =INDEX(Panel!$U$5:$U$815,D44+1) -> 4.3288825 | H44: =INDEX(Panel!$T$5:$T$815,D44+1) -> 1.0348825 | I44: =INDEX(Panel!$S$5:$S$815,D44+1) -> -6.6965429e-05 | J44: =INDEX(Panel!$V$5:$V$815,D44+1) -> 0.0025556508 | K44: =(E44-G44-H44*F44-I44*D44)/J44 -> 1.549827 | L44: 1.5 | M44: =IF(ABS(K44)>L44,"Yes","No") -> Yes | N44: 2024-06-04 09:15 | O44: 271 | P44: 22607.5 | Q44: 250.27 | R44: 2024-06-27 15:15 | S44: 287 | T44: 24047.1 | U44: 266.95 | V44: expiry | W44: =B44*((LN(T44)-LN(P44))-(LN(U44)-LN(Q44))) -> 0.0027883423 | X44: =IF(INDEX(Panel!$A$5:$A$815,O44+1)<=DATE(2024,9,30),0.000625,IF(INDEX(Panel!$A$5:$A$815,O44+1)<=DATE(2026,3,31),0.001,0.0015))*(0.3989*Inputs!$B$28*SQRT(MAX(INDEX(Panel!$G$5:$G$815,O44+1),0)/365))+2*Inputs!$B$29+Inputs!$B$19+0.00003*(0.3989*Inputs!$B$28*SQRT(MAX(INDEX(Panel!$G$5:$G$815,O44+1),0)/365))+IF(B44<0,(Inputs!$B$20+Inputs!$B$22+Inputs!$B$23),(Inputs!$B$21+Inputs!$B$22+Inputs!$B$23)) -> 0.00046418229 | Y44: =IF(V44="expiry",IF(INDEX(Panel!$A$5:$A$815,S44+1)<=DATE(2026,3,31),0.00125,0.0015)*IF(B44<0,MAX(P44-T44,0),MAX(T44-P44,0))/T44,IF(INDEX(Panel!$A$5:$A$815,S44+1)<=DATE(2024,9,30),0.000625,IF(INDEX(Panel!$A$5:$A$815,S44+1)<=DATE(2026,3,31),0.001,0.0015))*(0.3989*Inputs!$B$28*SQRT(MAX(INDEX(Panel!$G$5:$G$815,S44+1),0)/365))+2*Inputs!$B$29+Inputs!$B$19)+IF(B44<0,(Inputs!$B$21+Inputs!$B$22+Inputs!$B$23),(Inputs!$B$20+Inputs!$B$22+Inputs!$B$23)) -> 0.00021 | Z44: =-SUMPRODUCT((Panel!$F$5:$F$815>=O44)*(Panel!$F$5:$F$815<S44)*Panel!$N$5:$N$815*Panel!$BD$5:$BD$815)/365 -> -0.0040958904 | AA44: =W44-X44-Y44+Z44 -> -0.0019817304 | AB44: -0.0019817304 | AC44: =AA44-AB44 -> -2.6454533e-17
A45: aarav | B45: -1 | C45: 2024-10-03 14:00 | D45: 354 | E45: 10.145924 | F45: 5.6436786 | G45: =INDEX(Panel!$U$5:$U$815,D45+1) -> 4.3273311 | H45: =INDEX(Panel!$T$5:$T$815,D45+1) -> 1.0360569 | I45: =INDEX(Panel!$S$5:$S$815,D45+1) -> -9.582644e-05 | J45: =INDEX(Panel!$V$5:$V$815,D45+1) -> 0.0034744591 | K45: =(E45-G45-H45*F45-I45*D45)/J45 -> 1.5378307 | L45: 1.5 | M45: =IF(ABS(K45)>L45,"Yes","No") -> Yes | N45: 2024-10-03 14:15 | O45: 354 | P45: 25460.95 | Q45: 282.6 | R45: 2024-10-31 15:15 | S45: 374 | T45: 24203.95 | U45: 270.9 | V45: expiry | W45: =B45*((LN(T45)-LN(P45))-(LN(U45)-LN(Q45))) -> 0.0083473417 | X45: =IF(INDEX(Panel!$A$5:$A$815,O45+1)<=DATE(2024,9,30),0.000625,IF(INDEX(Panel!$A$5:$A$815,O45+1)<=DATE(2026,3,31),0.001,0.0015))*(0.3989*Inputs!$B$28*SQRT(MAX(INDEX(Panel!$G$5:$G$815,O45+1),0)/365))+2*Inputs!$B$29+Inputs!$B$19+0.00003*(0.3989*Inputs!$B$28*SQRT(MAX(INDEX(Panel!$G$5:$G$815,O45+1),0)/365))+IF(B45<0,(Inputs!$B$20+Inputs!$B$22+Inputs!$B$23),(Inputs!$B$21+Inputs!$B$22+Inputs!$B$23)) -> 0.00047093169 | Y45: =IF(V45="expiry",IF(INDEX(Panel!$A$5:$A$815,S45+1)<=DATE(2026,3,31),0.00125,0.0015)*IF(B45<0,MAX(P45-T45,0),MAX(T45-P45,0))/T45,IF(INDEX(Panel!$A$5:$A$815,S45+1)<=DATE(2024,9,30),0.000625,IF(INDEX(Panel!$A$5:$A$815,S45+1)<=DATE(2026,3,31),0.001,0.0015))*(0.3989*Inputs!$B$28*SQRT(MAX(INDEX(Panel!$G$5:$G$815,S45+1),0)/365))+2*Inputs!$B$29+Inputs!$B$19)+IF(B45<0,(Inputs!$B$21+Inputs!$B$22+Inputs!$B$23),(Inputs!$B$20+Inputs!$B$22+Inputs!$B$23)) -> 0.00027491709 | Z45: =-SUMPRODUCT((Panel!$F$5:$F$815>=O45)*(Panel!$F$5:$F$815<S45)*Panel!$N$5:$N$815*Panel!$BD$5:$BD$815)/365 -> -0.0049863014 | AA45: =W45-X45-Y45+Z45 -> 0.0026151916 | AB45: 0.0026151916 | AC45: =AA45-AB45 -> 8.8904578e-17
... A59: aarav | B59: -1 | C59: 2026-05-27 10:00 | D59: 760 | E59: 10.086226 | F59: 5.6025984 | G59: =INDEX(Panel!$U$5:$U$815,D59+1) -> 4.4317981 | H59: =INDEX(Panel!$T$5:$T$815,D59+1) -> 1.0141497 | I59: =INDEX(Panel!$S$5:$S$815,D59+1) -> -4.1227986e-05 | J59: =INDEX(Panel!$V$5:$V$815,D59+1) -> 0.0023557714 | K59: =(E59-G59-H59*F59-I59*D59)/J59 -> 1.6500804 | L59: 1.5 | M59: =IF(ABS(K59)>L59,"Yes","No") -> Yes | N59: 2026-05-27 10:15 | O59: 760 | P59: 24027 | Q59: 271.3 | R59: 2026-06-30 15:15 | S59: 782 | T59: 23864.3 | U59: 272.43 | V59: expiry | W59: =B59*((LN(T59)-LN(P59))-(LN(U59)-LN(Q59))) -> 0.01095106 | X59: =IF(INDEX(Panel!$A$5:$A$815,O59+1)<=DATE(2024,9,30),0.000625,IF(INDEX(Panel!$A$5:$A$815,O59+1)<=DATE(2026,3,31),0.001,0.0015))*(0.3989*Inputs!$B$28*SQRT(MAX(INDEX(Panel!$G$5:$G$815,O59+1),0)/365))+2*Inputs!$B$29+Inputs!$B$19+0.00003*(0.3989*Inputs!$B$28*SQRT(MAX(INDEX(Panel!$G$5:$G$815,O59+1),0)/365))+IF(B59<0,(Inputs!$B$20+Inputs!$B$22+Inputs!$B$23),(Inputs!$B$21+Inputs!$B$22+Inputs!$B$23)) -> 0.00048107813 | Y59: =IF(V59="expiry",IF(INDEX(Panel!$A$5:$A$815,S59+1)<=DATE(2026,3,31),0.00125,0.0015)*IF(B59<0,MAX(P59-T59,0),MAX(T59-P59,0))/T59,IF(INDEX(Panel!$A$5:$A$815,S59+1)<=DATE(2024,9,30),0.000625,IF(INDEX(Panel!$A$5:$A$815,S59+1)<=DATE(2026,3,31),0.001,0.0015))*(0.3989*Inputs!$B$28*SQRT(MAX(INDEX(Panel!$G$5:$G$815,S59+1),0)/365))+2*Inputs!$B$29+Inputs!$B$19)+IF(B59<0,(Inputs!$B$21+Inputs!$B$22+Inputs!$B$23),(Inputs!$B$20+Inputs!$B$22+Inputs!$B$23)) -> 0.00022022657 | Z59: =-SUMPRODUCT((Panel!$F$5:$F$815>=O59)*(Panel!$F$5:$F$815<S59)*Panel!$N$5:$N$815*Panel!$BD$5:$BD$815)/365 -> -0.004890411 | AA59: =W59-X59-Y59+Z59 -> 0.0053593447 | AB59: 0.0053593447 | AC59: =AA59-AB59 -> 7.4593109e-17
A60: meera | B60: -1 | C60: 2023-07-28 12:30 | D60: 62 | E60: 9.8889829 | F60: 5.3741203 | G60: =INDEX(Panel!$U$5:$U$815,D60+1) -> 4.2338414 | H60: =INDEX(Panel!$T$5:$T$815,D60+1) -> 1.0538075 | I60: =INDEX(Panel!$S$5:$S$815,D60+1) -> -0.00020051329 | J60: =INDEX(Panel!$V$5:$V$815,D60+1) -> 0.0016779358 | K60: =(E60-G60-H60*F60-I60*D60)/J60 -> 2.5536613 | L60: 2.5 | M60: =IF(ABS(K60)>L60,"Yes","No") -> Yes | N60: 2023-07-28 12:45 | O60: 62 | P60: 19702.2 | Q60: 215.69 | R60: 2023-08-01 11:30 | S60: 64 | T60: 19824 | U60: 217.5 | V60: closed | W60: =B60*((LN(T60)-LN(P60))-(LN(U60)-LN(Q60))) -> 0.0021936386 | X60: =IF(INDEX(Panel!$A$5:$A$815,O60+1)<=DATE(2024,9,30),0.000625,IF(INDEX(Panel!$A$5:$A$815,O60+1)<=DATE(2026,3,31),0.001,0.0015))*(0.3989*Inputs!$B$28*SQRT(MAX(INDEX(Panel!$G$5:$G$815,O60+1),0)/365))+2*Inputs!$B$29+Inputs!$B$19+0.00003*(0.3989*Inputs!$B$28*SQRT(MAX(INDEX(Panel!$G$5:$G$815,O60+1),0)/365))+IF(B60<0,(Inputs!$B$20+Inputs!$B$22+Inputs!$B$23),(Inputs!$B$21+Inputs!$B$22+Inputs!$B$23)) -> 0.00046616417 | Y60: =IF(V60="expiry",IF(INDEX(Panel!$A$5:$A$815,S60+1)<=DATE(2026,3,31),0.00125,0.0015)*IF(B60<0,MAX(P60-T60,0),MAX(T60-P60,0))/T60,IF(INDEX(Panel!$A$5:$A$815,S60+1)<=DATE(2024,9,30),0.000625,IF(INDEX(Panel!$A$5:$A$815,S60+1)<=DATE(2026,3,31),0.001,0.0015))*(0.3989*Inputs!$B$28*SQRT(MAX(INDEX(Panel!$G$5:$G$815,S60+1),0)/365))+2*Inputs!$B$29+Inputs!$B$19)+IF(B60<0,(Inputs!$B$21+Inputs!$B$22+Inputs!$B$23),(Inputs!$B$20+Inputs!$B$22+Inputs!$B$23)) -> 0.00032500659 | Z60: =-SUMPRODUCT((Panel!$F$5:$F$815>=O60)*(Panel!$F$5:$F$815<S60)*(Panel!$N$5:$N$815+0.75*(Inputs!$B$13-Panel!$N$5:$N$815))*Panel!$BD$5:$BD$815)/365 -> -0.0013287671 | AA60: =W60-X60-Y60+Z60 -> 7.3700757e-05 | AB60: 7.3700757e-05 | AC60: =AA60-AB60 -> 0
A61: meera | B61: -1 | C61: 2023-09-01 09:15 | D61: 86 | E61: 9.8724612 | F61: 5.3609165 | G61: =INDEX(Panel!$U$5:$U$815,D61+1) -> 4.2252851 | H61: =INDEX(Panel!$T$5:$T$815,D61+1) -> 1.0553828 | I61: =INDEX(Panel!$S$5:$S$815,D61+1) -> -0.0001905105 | J61: =INDEX(Panel!$V$5:$V$815,D61+1) -> 0.0017694952 | K61: =(E61-G61-H61*F61-I61*D61)/J61 -> 3.2443583 | L61: 2.5 | M61: =IF(ABS(K61)>L61,"Yes","No") -> Yes | N61: 2023-09-01 09:30 | O61: 86 | P61: 19409 | Q61: 213.19 | R61: 2023-09-14 10:30 | S61: 95 | T61: 20129.85 | U61: 221.68 | V61: closed | W61: =B61*((LN(T61)-LN(P61))-(LN(U61)-LN(Q61))) -> 0.0025842016 | X61: =IF(INDEX(Panel!$A$5:$A$815,O61+1)<=DATE(2024,9,30),0.000625,IF(INDEX(Panel!$A$5:$A$815,O61+1)<=DATE(2026,3,31),0.001,0.0015))*(0.3989*Inputs!$B$28*SQRT(MAX(INDEX(Panel!$G$5:$G$815,O61+1),0)/365))+2*Inputs!$B$29+Inputs!$B$19+0.00003*(0.3989*Inputs!$B$28*SQRT(MAX(INDEX(Panel!$G$5:$G$815,O61+1),0)/365))+IF(B61<0,(Inputs!$B$20+Inputs!$B$22+Inputs!$B$23),(Inputs!$B$21+Inputs!$B$22+Inputs!$B$23)) -> 0.00046494876 | Y61: =IF(V61="expiry",IF(INDEX(Panel!$A$5:$A$815,S61+1)<=DATE(2026,3,31),0.00125,0.0015)*IF(B61<0,MAX(P61-T61,0),MAX(T61-P61,0))/T61,IF(INDEX(Panel!$A$5:$A$815,S61+1)<=DATE(2024,9,30),0.000625,IF(INDEX(Panel!$A$5:$A$815,S61+1)<=DATE(2026,3,31),0.001,0.0015))*(0.3989*Inputs!$B$28*SQRT(MAX(INDEX(Panel!$G$5:$G$815,S61+1),0)/365))+2*Inputs!$B$29+Inputs!$B$19)+IF(B61<0,(Inputs!$B$21+Inputs!$B$22+Inputs!$B$23),(Inputs!$B$20+Inputs!$B$22+Inputs!$B$23)) -> 0.00032183581 | Z61: =-SUMPRODUCT((Panel!$F$5:$F$815>=O61)*(Panel!$F$5:$F$815<S61)*(Panel!$N$5:$N$815+0.75*(Inputs!$B$13-Panel!$N$5:$N$815))*Panel!$BD$5:$BD$815)/365 -> -0.0043184932 | AA61: =W61-X61-Y61+Z61 -> -0.0025210761 | AB61: -0.0025210761 | AC61: =AA61-AB61 -> 0
A62: meera | B62: -1 | C62: 2023-09-29 13:30 | D62: 105 | E62: 9.8910632 | F62: 5.3792059 | G62: =INDEX(Panel!$U$5:$U$815,D62+1) -> 4.3423895 | H62: =INDEX(Panel!$T$5:$T$815,D62+1) -> 1.0330804 | I62: =INDEX(Panel!$S$5:$S$815,D62+1) -> -0.00013368028 | J62: =INDEX(Panel!$V$5:$V$815,D62+1) -> 0.0020419793 | K62: =(E62-G62-H62*F62-I62*D62)/J62 -> 2.7217805 | L62: 2.5 | M62: =IF(ABS(K62)>L62,"Yes","No") -> Yes | N62: 2023-09-29 13:45 | O62: 105 | P62: 19775.25 | Q62: 216.97 | R62: 2023-10-03 09:15 | S62: 106 | T62: 19594.75 | U62: 215.51 | V62: closed | W62: =B62*((LN(T62)-LN(P62))-(LN(U62)-LN(Q62))) -> 0.0024176996 | X62: =IF(INDEX(Panel!$A$5:$A$815,O62+1)<=DATE(2024,9,30),0.000625,IF(INDEX(Panel!$A$5:$A$815,O62+1)<=DATE(2026,3,31),0.001,0.0015))*(0.3989*Inputs!$B$28*SQRT(MAX(INDEX(Panel!$G$5:$G$815,O62+1),0)/365))+2*Inputs!$B$29+Inputs!$B$19+0.00003*(0.3989*Inputs!$B$28*SQRT(MAX(INDEX(Panel!$G$5:$G$815,O62+1),0)/365))+IF(B62<0,(Inputs!$B$20+Inputs!$B$22+Inputs!$B$23),(Inputs!$B$21+Inputs!$B$22+Inputs!$B$23)) -> 0.00046494876 | Y62: =IF(V62="expiry",IF(INDEX(Panel!$A$5:$A$815,S62+1)<=DATE(2026,3,31),0.00125,0.0015)*IF(B62<0,MAX(P62-T62,0),MAX(T62-P62,0))/T62,IF(INDEX(Panel!$A$5:$A$815,S62+1)<=DATE(2024,9,30),0.000625,IF(INDEX(Panel!$A$5:$A$815,S62+1)<=DATE(2026,3,31),0.001,0.0015))*(0.3989*Inputs!$B$28*SQRT(MAX(INDEX(Panel!$G$5:$G$815,S62+1),0)/365))+2*Inputs!$B$29+Inputs!$B$19)+IF(B62<0,(Inputs!$B$21+Inputs!$B$22+Inputs!$B$23),(Inputs!$B$20+Inputs!$B$22+Inputs!$B$23)) -> 0.00032376172 | Z62: =-SUMPRODUCT((Panel!$F$5:$F$815>=O62)*(Panel!$F$5:$F$815<S62)*(Panel!$N$5:$N$815+0.75*(Inputs!$B$13-Panel!$N$5:$N$815))*Panel!$BD$5:$BD$815)/365 -> -0.0013287671 | AA62: =W62-X62-Y62+Z62 -> 0.00030022203 | AB62: 0.00030022203 | AC62: =AA62-AB62 -> 5.7842186e-17
A63: meera | B63: -1 | C63: 2023-10-27 09:45 | D63: 123 | E63: 9.8566527 | F63: 5.3465359 | G63: =INDEX(Panel!$U$5:$U$815,D63+1) -> 4.3831546 | H63: =INDEX(Panel!$T$5:$T$815,D63+1) -> 1.025347 | I63: =INDEX(Panel!$S$5:$S$815,D63+1) -> -0.00012000142 | J63: =INDEX(Panel!$V$5:$V$815,D63+1) -> 0.0020221093 | K63: =(E63-G63-H63*F63-I63*D63)/J63 -> 3.0680249 | L63: 2.5 | M63: =IF(ABS(K63)>L63,"Yes","No") -> Yes | N63: 2023-10-27 10:00 | O63: 123 | P63: 19075.35 | Q63: 209.91 | R63: 2023-11-30 10:00 | S63: 145 | T63: 20037.2 | U63: 221.29 | V63: closed | W63: =B63*((LN(T63)-LN(P63))-(LN(U63)-LN(Q63))) -> 0.0036015708 | X63: =IF(INDEX(Panel!$A$5:$A$815,O63+1)<=DATE(2024,9,30),0.000625,IF(INDEX(Panel!$A$5:$A$815,O63+1)<=DATE(2026,3,31),0.001,0.0015))*(0.3989*Inputs!$B$28*SQRT(MAX(INDEX(Panel!$G$5:$G$815,O63+1),0)/365))+2*Inputs!$B$29+Inputs!$B$19+0.00003*(0.3989*Inputs!$B$28*SQRT(MAX(INDEX(Panel!$G$5:$G$815,O63+1),0)/365))+IF(B63<0,(Inputs!$B$20+Inputs!$B$22+Inputs!$B$23),(Inputs!$B$21+Inputs!$B$22+Inputs!$B$23)) -> 0.00046616417 | Y63: =IF(V63="expiry",IF(INDEX(Panel!$A$5:$A$815,S63+1)<=DATE(2026,3,31),0.00125,0.0015)*IF(B63<0,MAX(P63-T63,0),MAX(T63-P63,0))/T63,IF(INDEX(Panel!$A$5:$A$815,S63+1)<=DATE(2024,9,30),0.000625,IF(INDEX(Panel!$A$5:$A$815,S63+1)<=DATE(2026,3,31),0.001,0.0015))*(0.3989*Inputs!$B$28*SQRT(MAX(INDEX(Panel!$G$5:$G$815,S63+1),0)/365))+2*Inputs!$B$29+Inputs!$B$19)+IF(B63<0,(Inputs!$B$21+Inputs!$B$22+Inputs!$B$23),(Inputs!$B$20+Inputs!$B$22+Inputs!$B$23)) -> 0.000315 | Z63: =-SUMPRODUCT((Panel!$F$5:$F$815>=O63)*(Panel!$F$5:$F$815<S63)*(Panel!$N$5:$N$815+0.75*(Inputs!$B$13-Panel!$N$5:$N$815))*Panel!$BD$5:$BD$815)/365 -> -0.011294521 | AA63: =W63-X63-Y63+Z63 -> -0.0084741139 | AB63: -0.0084741139 | AC63: =AA63-AB63 -> 0
A64: meera | B64: -1 | C64: 2023-12-01 09:15 | D64: 146 | E64: 9.9212268 | F64: 5.4076201 | G64: =INDEX(Panel!$U$5:$U$815,D64+1) -> 4.6018034 | H64: =INDEX(Panel!$T$5:$T$815,D64+1) -> 0.98395675 | I64: =INDEX(Panel!$S$5:$S$815,D64+1) -> -6.5832204e-05 | J64: =INDEX(Panel!$V$5:$V$815,D64+1) -> 0.0023156597 | K64: =(E64-G64-H64*F64-I64*D64)/J64 -> 3.5283871 | L64: 2.5 | M64: =IF(ABS(K64)>L64,"Yes","No") -> Yes | N64: 2023-12-01 09:30 | O64: 146 | P64: 20346.6 | Q64: 223 | R64: 2023-12-19 09:15 | S64: 158 | T64: 21502.55 | U64: 236.46 | V64: closed | W64: =B64*((LN(T64)-LN(P64))-(LN(U64)-LN(Q64))) -> 0.003349578 | X64: =IF(INDEX(Panel!$A$5:$A$815,O64+1)<=DATE(2024,9,30),0.000625,IF(INDEX(Panel!$A$5:$A$815,O64+1)<=DATE(2026,3,31),0.001,0.0015))*(0.3989*Inputs!$B$28*SQRT(MAX(INDEX(Panel!$G$5:$G$815,O64+1),0)/365))+2*Inputs!$B$29+Inputs!$B$19+0.00003*(0.3989*Inputs!$B$28*SQRT(MAX(INDEX(Panel!$G$5:$G$815,O64+1),0)/365))+IF(B64<0,(Inputs!$B$20+Inputs!$B$22+Inputs!$B$23),(Inputs!$B$21+Inputs!$B$22+Inputs!$B$23)) -> 0.00046494876 | Y64: =IF(V64="expiry",IF(INDEX(Panel!$A$5:$A$815,S64+1)<=DATE(2026,3,31),0.00125,0.0015)*IF(B64<0,MAX(P64-T64,0),MAX(T64-P64,0))/T64,IF(INDEX(Panel!$A$5:$A$815,S64+1)<=DATE(2024,9,30),0.000625,IF(INDEX(Panel!$A$5:$A$815,S64+1)<=DATE(2026,3,31),0.001,0.0015))*(0.3989*Inputs!$B$28*SQRT(MAX(INDEX(Panel!$G$5:$G$815,S64+1),0)/365))+2*Inputs!$B$29+Inputs!$B$19)+IF(B64<0,(Inputs!$B$21+Inputs!$B$22+Inputs!$B$23),(Inputs!$B$20+Inputs!$B$22+Inputs!$B$23)) -> 0.00032048084 | Z64: =-SUMPRODUCT((Panel!$F$5:$F$815>=O64)*(Panel!$F$5:$F$815<S64)*(Panel!$N$5:$N$815+0.75*(Inputs!$B$13-Panel!$N$5:$N$815))*Panel!$BD$5:$BD$815)/365 -> -0.0059794521 | AA64: =W64-X64-Y64+Z64 -> -0.0034153037 | AB64: -0.0034153037 | AC64: =AA64-AB64 -> -1.8648277e-17
A65: meera | B65: -1 | C65: 2023-12-29 09:15 | D65: 165 | E65: 9.9947418 | F65: 5.4802222 | G65: =INDEX(Panel!$U$5:$U$815,D65+1) -> 4.3928634 | H65: =INDEX(Panel!$T$5:$T$815,D65+1) -> 1.0231243 | I65: =INDEX(Panel!$S$5:$S$815,D65+1) -> -7.2978375e-05 | J65: =INDEX(Panel!$V$5:$V$815,D65+1) -> 0.002675989 | K65: =(E65-G65-H65*F65-I65*D65)/J65 -> 2.6050725 | L65: 2.5 | M65: =IF(ABS(K65)>L65,"Yes","No") -> Yes | N65: 2023-12-29 09:30 | O65: 165 | P65: 21895.85 | Q65: 239.89 | R65: 2024-01-05 13:00 | S65: 170 | T65: 21772.1 | U65: 239.5 | V65: closed | W65: =B65*((LN(T65)-LN(P65))-(LN(U65)-LN(Q65))) -> 0.0040407194 | X65: =IF(INDEX(Panel!$A$5:$A$815,O65+1)<=DATE(2024,9,30),0.000625,IF(INDEX(Panel!$A$5:$A$815,O65+1)<=DATE(2026,3,31),0.001,0.0015))*(0.3989*Inputs!$B$28*SQRT(MAX(INDEX(Panel!$G$5:$G$815,O65+1),0)/365))+2*Inputs!$B$29+Inputs!$B$19+0.00003*(0.3989*Inputs!$B$28*SQRT(MAX(INDEX(Panel!$G$5:$G$815,O65+1),0)/365))+IF(B65<0,(Inputs!$B$20+Inputs!$B$22+Inputs!$B$23),(Inputs!$B$21+Inputs!$B$22+Inputs!$B$23)) -> 0.00046494876 | Y65: =IF(V65="expiry",IF(INDEX(Panel!$A$5:$A$815,S65+1)<=DATE(2026,3,31),0.00125,0.0015)*IF(B65<0,MAX(P65-T65,0),MAX(T65-P65,0))/T65,IF(INDEX(Panel!$A$5:$A$815,S65+1)<=DATE(2024,9,30),0.000625,IF(INDEX(Panel!$A$5:$A$815,S65+1)<=DATE(2026,3,31),0.001,0.0015))*(0.3989*Inputs!$B$28*SQRT(MAX(INDEX(Panel!$G$5:$G$815,S65+1),0)/365))+2*Inputs!$B$29+Inputs!$B$19)+IF(B65<0,(Inputs!$B$21+Inputs!$B$22+Inputs!$B$23),(Inputs!$B$20+Inputs!$B$22+Inputs!$B$23)) -> 0.00032317035 | Z65: =-SUMPRODUCT((Panel!$F$5:$F$815>=O65)*(Panel!$F$5:$F$815<S65)*(Panel!$N$5:$N$815+0.75*(Inputs!$B$13-Panel!$N$5:$N$815))*Panel!$BD$5:$BD$815)/365 -> -0.0023253425 | AA65: =W65-X65-Y65+Z65 -> 0.00092725787 | AB65: 0.00092725787 | AC65: =AA65-AB65 -> 2.4394549e-17
A66: meera | B66: -1 | C66: 2025-12-31 09:15 | D66: 662 | E66: 10.172636 | F66: 5.6835458 | G66: =INDEX(Panel!$U$5:$U$815,D66+1) -> 4.3840657 | H66: =INDEX(Panel!$T$5:$T$815,D66+1) -> 1.0253067 | I66: =INDEX(Panel!$S$5:$S$815,D66+1) -> -6.6993394e-05 | J66: =INDEX(Panel!$V$5:$V$815,D66+1) -> 0.0021890025 | K66: =(E66-G66-H66*F66-I66*D66)/J66 -> 2.5320295 | L66: 2.5 | M66: =IF(ABS(K66)>L66,"Yes","No") -> Yes | N66: 2025-12-31 09:30 | O66: 662 | P66: 26138 | Q66: 293.69 | R66: 2026-01-09 09:15 | S66: 669 | T66: 25961.5 | U66: 292.55 | V66: closed | W66: =B66*((LN(T66)-LN(P66))-(LN(U66)-LN(Q66))) -> 0.0028863258 | X66: =IF(INDEX(Panel!$A$5:$A$815,O66+1)<=DATE(2024,9,30),0.000625,IF(INDEX(Panel!$A$5:$A$815,O66+1)<=DATE(2026,3,31),0.001,0.0015))*(0.3989*Inputs!$B$28*SQRT(MAX(INDEX(Panel!$G$5:$G$815,O66+1),0)/365))+2*Inputs!$B$29+Inputs!$B$19+0.00003*(0.3989*Inputs!$B$28*SQRT(MAX(INDEX(Panel!$G$5:$G$815,O66+1),0)/365))+IF(B66<0,(Inputs!$B$20+Inputs!$B$22+Inputs!$B$23),(Inputs!$B$21+Inputs!$B$22+Inputs!$B$23)) -> 0.00047064461 | Y66: =IF(V66="expiry",IF(INDEX(Panel!$A$5:$A$815,S66+1)<=DATE(2026,3,31),0.00125,0.0015)*IF(B66<0,MAX(P66-T66,0),MAX(T66-P66,0))/T66,IF(INDEX(Panel!$A$5:$A$815,S66+1)<=DATE(2024,9,30),0.000625,IF(INDEX(Panel!$A$5:$A$815,S66+1)<=DATE(2026,3,31),0.001,0.0015))*(0.3989*Inputs!$B$28*SQRT(MAX(INDEX(Panel!$G$5:$G$815,S66+1),0)/365))+2*Inputs!$B$29+Inputs!$B$19)+IF(B66<0,(Inputs!$B$21+Inputs!$B$22+Inputs!$B$23),(Inputs!$B$20+Inputs!$B$22+Inputs!$B$23)) -> 0.00032740172 | Z66: =-SUMPRODUCT((Panel!$F$5:$F$815>=O66)*(Panel!$F$5:$F$815<S66)*(Panel!$N$5:$N$815+0.75*(Inputs!$B$13-Panel!$N$5:$N$815))*Panel!$BD$5:$BD$815)/365 -> -0.0029126712 | AA66: =W66-X66-Y66+Z66 -> -0.0008243918 | AB66: -0.0008243918 | AC66: =AA66-AB66 -> -7.2099444e-17
A67: meera | B67: -1 | C67: 2026-01-29 10:00 | D67: 681 | E67: 10.139271 | F67: 5.6518574 | G67: =INDEX(Panel!$U$5:$U$815,D67+1) -> 4.3701615 | H67: =INDEX(Panel!$T$5:$T$815,D67+1) -> 1.0279238 | I67: =INDEX(Panel!$S$5:$S$815,D67+1) -> -6.8214477e-05 | J67: =INDEX(Panel!$V$5:$V$815,D67+1) -> 0.0022741128 | K67: =(E67-G67-H67*F67-I67*D67)/J67 -> 2.5878082 | L67: 2.5 | M67: =IF(ABS(K67)>L67,"Yes","No") -> Yes | N67: 2026-01-29 10:15 | O67: 681 | P67: 25292.5 | Q67: 284.6 | R67: 2026-02-01 09:45 | S67: 683 | T67: 25403.3 | U67: 287.06 | V67: closed | W67: =B67*((LN(T67)-LN(P67))-(LN(U67)-LN(Q67))) -> 0.0042353897 | X67: =IF(INDEX(Panel!$A$5:$A$815,O67+1)<=DATE(2024,9,30),0.000625,IF(INDEX(Panel!$A$5:$A$815,O67+1)<=DATE(2026,3,31),0.001,0.0015))*(0.3989*Inputs!$B$28*SQRT(MAX(INDEX(Panel!$G$5:$G$815,O67+1),0)/365))+2*Inputs!$B$29+Inputs!$B$19+0.00003*(0.3989*Inputs!$B$28*SQRT(MAX(INDEX(Panel!$G$5:$G$815,O67+1),0)/365))+IF(B67<0,(Inputs!$B$20+Inputs!$B$22+Inputs!$B$23),(Inputs!$B$21+Inputs!$B$22+Inputs!$B$23)) -> 0.00047035216 | Y67: =IF(V67="expiry",IF(INDEX(Panel!$A$5:$A$815,S67+1)<=DATE(2026,3,31),0.00125,0.0015)*IF(B67<0,MAX(P67-T67,0),MAX(T67-P67,0))/T67,IF(INDEX(Panel!$A$5:$A$815,S67+1)<=DATE(2024,9,30),0.000625,IF(INDEX(Panel!$A$5:$A$815,S67+1)<=DATE(2026,3,31),0.001,0.0015))*(0.3989*Inputs!$B$28*SQRT(MAX(INDEX(Panel!$G$5:$G$815,S67+1),0)/365))+2*Inputs!$B$29+Inputs!$B$19)+IF(B67<0,(Inputs!$B$21+Inputs!$B$22+Inputs!$B$23),(Inputs!$B$20+Inputs!$B$22+Inputs!$B$23)) -> 0.00032901876 | Z67: =-SUMPRODUCT((Panel!$F$5:$F$815>=O67)*(Panel!$F$5:$F$815<S67)*(Panel!$N$5:$N$815+0.75*(Inputs!$B$13-Panel!$N$5:$N$815))*Panel!$BD$5:$BD$815)/365 -> -0.00097089041 | AA67: =W67-X67-Y67+Z67 -> 0.0024651284 | AB67: 0.0024651284 | AC67: =AA67-AB67 -> 4.7271215e-17
A68: meera | B68: -1 | C68: 2026-02-25 09:15 | D68: 701 | E68: 10.15617 | F68: 5.6680171 | G68: =INDEX(Panel!$U$5:$U$815,D68+1) -> 4.3958176 | H68: =INDEX(Panel!$T$5:$T$815,D68+1) -> 1.0232593 | I68: =INDEX(Panel!$S$5:$S$815,D68+1) -> -6.6785699e-05 | J68: =INDEX(Panel!$V$5:$V$815,D68+1) -> 0.0022690512 | K68: =(E68-G68-H68*F68-I68*D68)/J68 -> 3.2252779 | L68: 2.5 | M68: =IF(ABS(K68)>L68,"Yes","No") -> Yes | N68: 2026-02-25 09:30 | O68: 701 | P68: 25720 | Q68: 289.32 | R68: 2026-03-09 09:15 | S68: 708 | T68: 23832.8 | U68: 269.33 | V68: closed | W68: =B68*((LN(T68)-LN(P68))-(LN(U68)-LN(Q68))) -> 0.0046101678 | X68: =IF(INDEX(Panel!$A$5:$A$815,O68+1)<=DATE(2024,9,30),0.000625,IF(INDEX(Panel!$A$5:$A$815,O68+1)<=DATE(2026,3,31),0.001,0.0015))*(0.3989*Inputs!$B$28*SQRT(MAX(INDEX(Panel!$G$5:$G$815,O68+1),0)/365))+2*Inputs!$B$29+Inputs!$B$19+0.00003*(0.3989*Inputs!$B$28*SQRT(MAX(INDEX(Panel!$G$5:$G$815,O68+1),0)/365))+IF(B68<0,(Inputs!$B$20+Inputs!$B$22+Inputs!$B$23),(Inputs!$B$21+Inputs!$B$22+Inputs!$B$23)) -> 0.00047229577 | Y68: =IF(V68="expiry",IF(INDEX(Panel!$A$5:$A$815,S68+1)<=DATE(2026,3,31),0.00125,0.0015)*IF(B68<0,MAX(P68-T68,0),MAX(T68-P68,0))/T68,IF(INDEX(Panel!$A$5:$A$815,S68+1)<=DATE(2024,9,30),0.000625,IF(INDEX(Panel!$A$5:$A$815,S68+1)<=DATE(2026,3,31),0.001,0.0015))*(0.3989*Inputs!$B$28*SQRT(MAX(INDEX(Panel!$G$5:$G$815,S68+1),0)/365))+2*Inputs!$B$29+Inputs!$B$19)+IF(B68<0,(Inputs!$B$21+Inputs!$B$22+Inputs!$B$23),(Inputs!$B$20+Inputs!$B$22+Inputs!$B$23)) -> 0.00032839539 | Z68: =-SUMPRODUCT((Panel!$F$5:$F$815>=O68)*(Panel!$F$5:$F$815<S68)*(Panel!$N$5:$N$815+0.75*(Inputs!$B$13-Panel!$N$5:$N$815))*Panel!$BD$5:$BD$815)/365 -> -0.0038835616 | AA68: =W68-X68-Y68+Z68 -> -7.4085031e-05 | AB68: -7.4085031e-05 | AC68: =AA68-AB68 -> 8.6736174e-19
A69: meera | B69: -1 | C69: 2026-04-01 11:30 | D69: 723 | E69: 10.039268 | F69: 5.554857 | G69: =INDEX(Panel!$U$5:$U$815,D69+1) -> 4.4280662 | H69: =INDEX(Panel!$T$5:$T$815,D69+1) -> 1.0169977 | I69: =INDEX(Panel!$S$5:$S$815,D69+1) -> -6.1285691e-05 | J69: =INDEX(Panel!$V$5:$V$815,D69+1) -> 0.0024172452 | K69: =(E69-G69-H69*F69-I69*D69)/J69 -> 2.579146 | L69: 2.5 | M69: =IF(ABS(K69)>L69,"Yes","No") -> Yes | N69: 2026-04-01 11:45 | O69: 723 | P69: 22884.9 | Q69: 258.29 | R69: 2026-04-01 14:45 | S69: 723 | T69: 22780 | U69: 258.2 | V69: closed | W69: =B69*((LN(T69)-LN(P69))-(LN(U69)-LN(Q69))) -> 0.0042458401 | X69: =IF(INDEX(Panel!$A$5:$A$815,O69+1)<=DATE(2024,9,30),0.000625,IF(INDEX(Panel!$A$5:$A$815,O69+1)<=DATE(2026,3,31),0.001,0.0015))*(0.3989*Inputs!$B$28*SQRT(MAX(INDEX(Panel!$G$5:$G$815,O69+1),0)/365))+2*Inputs!$B$29+Inputs!$B$19+0.00003*(0.3989*Inputs!$B$28*SQRT(MAX(INDEX(Panel!$G$5:$G$815,O69+1),0)/365))+IF(B69<0,(Inputs!$B$20+Inputs!$B$22+Inputs!$B$23),(Inputs!$B$21+Inputs!$B$22+Inputs!$B$23)) -> 0.00047823908 | Y69: =IF(V69="expiry",IF(INDEX(Panel!$A$5:$A$815,S69+1)<=DATE(2026,3,31),0.00125,0.0015)*IF(B69<0,MAX(P69-T69,0),MAX(T69-P69,0))/T69,IF(INDEX(Panel!$A$5:$A$815,S69+1)<=DATE(2024,9,30),0.000625,IF(INDEX(Panel!$A$5:$A$815,S69+1)<=DATE(2026,3,31),0.001,0.0015))*(0.3989*Inputs!$B$28*SQRT(MAX(INDEX(Panel!$G$5:$G$815,S69+1),0)/365))+2*Inputs!$B$29+Inputs!$B$19)+IF(B69<0,(Inputs!$B$21+Inputs!$B$22+Inputs!$B$23),(Inputs!$B$20+Inputs!$B$22+Inputs!$B$23)) -> 0.00033778341 | Z69: =-SUMPRODUCT((Panel!$F$5:$F$815>=O69)*(Panel!$F$5:$F$815<S69)*(Panel!$N$5:$N$815+0.75*(Inputs!$B$13-Panel!$N$5:$N$815))*Panel!$BD$5:$BD$815)/365 -> 0 | AA69: =W69-X69-Y69+Z69 -> 0.0034298176 | AB69: 0.0034298176 | AC69: =AA69-AB69 -> 1.994932e-17
A70: meera | B70: -1 | C70: 2026-04-01 15:00 | D70: 723 | E70: 10.034472 | F70: 5.5498929 | G70: =INDEX(Panel!$U$5:$U$815,D70+1) -> 4.4280662 | H70: =INDEX(Panel!$T$5:$T$815,D70+1) -> 1.0169977 | I70: =INDEX(Panel!$S$5:$S$815,D70+1) -> -6.1285691e-05 | J70: =INDEX(Panel!$V$5:$V$815,D70+1) -> 0.0024172452 | K70: =(E70-G70-H70*F70-I70*D70)/J70 -> 2.6837298 | L70: 2.5 | M70: =IF(ABS(K70)>L70,"Yes","No") -> Yes | N70: 2026-04-01 15:15 | O70: 723 | P70: 22828 | Q70: 257.99 | R70: 2026-04-16 14:00 | S70: 732 | T70: 24171 | U70: 273.52 | V70: closed | W70: =B70*((LN(T70)-LN(P70))-(LN(U70)-LN(Q70))) -> 0.0012882061 | X70: =IF(INDEX(Panel!$A$5:$A$815,O70+1)<=DATE(2024,9,30),0.000625,IF(INDEX(Panel!$A$5:$A$815,O70+1)<=DATE(2026,3,31),0.001,0.0015))*(0.3989*Inputs!$B$28*SQRT(MAX(INDEX(Panel!$G$5:$G$815,O70+1),0)/365))+2*Inputs!$B$29+Inputs!$B$19+0.00003*(0.3989*Inputs!$B$28*SQRT(MAX(INDEX(Panel!$G$5:$G$815,O70+1),0)/365))+IF(B70<0,(Inputs!$B$20+Inputs!$B$22+Inputs!$B$23),(Inputs!$B$21+Inputs!$B$22+Inputs!$B$23)) -> 0.00047823908 | Y70: =IF(V70="expiry",IF(INDEX(Panel!$A$5:$A$815,S70+1)<=DATE(2026,3,31),0.00125,0.0015)*IF(B70<0,MAX(P70-T70,0),MAX(T70-P70,0))/T70,IF(INDEX(Panel!$A$5:$A$815,S70+1)<=DATE(2024,9,30),0.000625,IF(INDEX(Panel!$A$5:$A$815,S70+1)<=DATE(2026,3,31),0.001,0.0015))*(0.3989*Inputs!$B$28*SQRT(MAX(INDEX(Panel!$G$5:$G$815,S70+1),0)/365))+2*Inputs!$B$29+Inputs!$B$19)+IF(B70<0,(Inputs!$B$21+Inputs!$B$22+Inputs!$B$23),(Inputs!$B$20+Inputs!$B$22+Inputs!$B$23)) -> 0.00033018894 | Z70: =-SUMPRODUCT((Panel!$F$5:$F$815>=O70)*(Panel!$F$5:$F$815<S70)*(Panel!$N$5:$N$815+0.75*(Inputs!$B$13-Panel!$N$5:$N$815))*Panel!$BD$5:$BD$815)/365 -> -0.0048544521 | AA70: =W70-X70-Y70+Z70 -> -0.004374674 | AB70: -0.004374674 | AC70: =AA70-AB70 -> 0
A71: meera | B71: -1 | C71: 2026-04-29 09:15 | D71: 741 | E71: 10.094108 | F71: 5.6081522 | G71: =INDEX(Panel!$U$5:$U$815,D71+1) -> 4.4692644 | H71: =INDEX(Panel!$T$5:$T$815,D71+1) -> 1.0088384 | I71: =INDEX(Panel!$S$5:$S$815,D71+1) -> -5.3053487e-05 | J71: =INDEX(Panel!$V$5:$V$815,D71+1) -> 0.0025090561 | K71: =(E71-G71-H71*F71-I71*D71)/J71 -> 2.5655058 | L71: 2.5 | M71: =IF(ABS(K71)>L71,"Yes","No") -> Yes | N71: 2026-04-29 09:30 | O71: 741 | P71: 24229.2 | Q71: 272.86 | R71: 2026-05-11 09:45 | S71: 748 | T71: 23905 | U71: 270.68 | V71: closed | W71: =B71*((LN(T71)-LN(P71))-(LN(U71)-LN(Q71))) -> 0.0054493435 | X71: =IF(INDEX(Panel!$A$5:$A$815,O71+1)<=DATE(2024,9,30),0.000625,IF(INDEX(Panel!$A$5:$A$815,O71+1)<=DATE(2026,3,31),0.001,0.0015))*(0.3989*Inputs!$B$28*SQRT(MAX(INDEX(Panel!$G$5:$G$815,O71+1),0)/365))+2*Inputs!$B$29+Inputs!$B$19+0.00003*(0.3989*Inputs!$B$28*SQRT(MAX(INDEX(Panel!$G$5:$G$815,O71+1),0)/365))+IF(B71<0,(Inputs!$B$20+Inputs!$B$22+Inputs!$B$23),(Inputs!$B$21+Inputs!$B$22+Inputs!$B$23)) -> 0.00047823908 | Y71: =IF(V71="expiry",IF(INDEX(Panel!$A$5:$A$815,S71+1)<=DATE(2026,3,31),0.00125,0.0015)*IF(B71<0,MAX(P71-T71,0),MAX(T71-P71,0))/T71,IF(INDEX(Panel!$A$5:$A$815,S71+1)<=DATE(2024,9,30),0.000625,IF(INDEX(Panel!$A$5:$A$815,S71+1)<=DATE(2026,3,31),0.001,0.0015))*(0.3989*Inputs!$B$28*SQRT(MAX(INDEX(Panel!$G$5:$G$815,S71+1),0)/365))+2*Inputs!$B$29+Inputs!$B$19)+IF(B71<0,(Inputs!$B$21+Inputs!$B$22+Inputs!$B$23),(Inputs!$B$20+Inputs!$B$22+Inputs!$B$23)) -> 0.00033198175 | Z71: =-SUMPRODUCT((Panel!$F$5:$F$815>=O71)*(Panel!$F$5:$F$815<S71)*(Panel!$N$5:$N$815+0.75*(Inputs!$B$13-Panel!$N$5:$N$815))*Panel!$BD$5:$BD$815)/365 -> -0.0038835616 | AA71: =W71-X71-Y71+Z71 -> 0.00075556104 | AB71: 0.00075556104 | AC71: =AA71-AB71 -> 9.8987658e-17
A72: rohan | B72: -1 | C72: 2023-07-28 12:30 | D72: 62 | E72: 9.8889829 | F72: 5.3741203 | G72: =INDEX(Panel!$U$5:$U$815,D72+1) -> 4.2338414 | H72: =INDEX(Panel!$T$5:$T$815,D72+1) -> 1.0538075 | I72: =INDEX(Panel!$S$5:$S$815,D72+1) -> -0.00020051329 | J72: =INDEX(Panel!$V$5:$V$815,D72+1) -> 0.0016779358 | K72: =(E72-G72-H72*F72-I72*D72)/J72 -> 2.5536613 | L72: 2.5 | M72: =IF(ABS(K72)>L72,"Yes","No") -> Yes | N72: 2023-07-28 12:45 | O72: 62 | P72: 19702.2 | Q72: 215.69 | R72: 2023-08-31 15:15 | S72: 85 | T72: 19254 | U72: 213.2 | V72: expiry | W72: =B72*(LN(T72)-LN(P72)) -> 0.023011473 | X72: =IF(INDEX(Panel!$A$5:$A$815,O72+1)<=DATE(2024,9,30),0.000625,IF(INDEX(Panel!$A$5:$A$815,O72+1)<=DATE(2026,3,31),0.001,0.0015))*(0.3989*Inputs!$B$28*SQRT(MAX(INDEX(Panel!$G$5:$G$815,O72+1),0)/365))+2*Inputs!$B$29+Inputs!$B$19+0.00003*(0.3989*Inputs!$B$28*SQRT(MAX(INDEX(Panel!$G$5:$G$815,O72+1),0)/365))+0 -> 0.00011616417 | Y72: =IF(V72="expiry",IF(INDEX(Panel!$A$5:$A$815,S72+1)<=DATE(2026,3,31),0.00125,0.0015)*IF(B72<0,MAX(P72-T72,0),MAX(T72-P72,0))/T72,IF(INDEX(Panel!$A$5:$A$815,S72+1)<=DATE(2024,9,30),0.000625,IF(INDEX(Panel!$A$5:$A$815,S72+1)<=DATE(2026,3,31),0.001,0.0015))*(0.3989*Inputs!$B$28*SQRT(MAX(INDEX(Panel!$G$5:$G$815,S72+1),0)/365))+2*Inputs!$B$29+Inputs!$B$19)+0 -> 2.909785e-05 | Z72: =0 -> 0 | AA72: =W72-X72-Y72+Z72 -> 0.022866211 | AB72: 0.022866211 | AC72: =AA72-AB72 -> 0
A73: rohan | B73: -1 | C73: 2023-09-01 09:15 | D73: 86 | E73: 9.8724612 | F73: 5.3609165 | G73: =INDEX(Panel!$U$5:$U$815,D73+1) -> 4.2252851 | H73: =INDEX(Panel!$T$5:$T$815,D73+1) -> 1.0553828 | I73: =INDEX(Panel!$S$5:$S$815,D73+1) -> -0.0001905105 | J73: =INDEX(Panel!$V$5:$V$815,D73+1) -> 0.0017694952 | K73: =(E73-G73-H73*F73-I73*D73)/J73 -> 3.2443583 | L73: 2.5 | M73: =IF(ABS(K73)>L73,"Yes","No") -> Yes | N73: 2023-09-01 09:30 | O73: 86 | P73: 19409 | Q73: 213.19 | R73: 2023-09-28 15:15 | S73: 104 | T73: 19525 | U73: 216.14 | V73: expiry | W73: =B73*(LN(T73)-LN(P73)) -> -0.0059588197 | X73: =IF(INDEX(Panel!$A$5:$A$815,O73+1)<=DATE(2024,9,30),0.000625,IF(INDEX(Panel!$A$5:$A$815,O73+1)<=DATE(2026,3,31),0.001,0.0015))*(0.3989*Inputs!$B$28*SQRT(MAX(INDEX(Panel!$G$5:$G$815,O73+1),0)/365))+2*Inputs!$B$29+Inputs!$B$19+0.00003*(0.3989*Inputs!$B$28*SQRT(MAX(INDEX(Panel!$G$5:$G$815,O73+1),0)/365))+0 -> 0.00011494876 | Y73: =IF(V73="expiry",IF(INDEX(Panel!$A$5:$A$815,S73+1)<=DATE(2026,3,31),0.00125,0.0015)*IF(B73<0,MAX(P73-T73,0),MAX(T73-P73,0))/T73,IF(INDEX(Panel!$A$5:$A$815,S73+1)<=DATE(2024,9,30),0.000625,IF(INDEX(Panel!$A$5:$A$815,S73+1)<=DATE(2026,3,31),0.001,0.0015))*(0.3989*Inputs!$B$28*SQRT(MAX(INDEX(Panel!$G$5:$G$815,S73+1),0)/365))+2*Inputs!$B$29+Inputs!$B$19)+0 -> 0 | Z73: =0 -> 0 | AA73: =W73-X73-Y73+Z73 -> -0.0060737685 | AB73: -0.0060737685 | AC73: =AA73-AB73 -> -8.500145e-17
A74: rohan | B74: -1 | C74: 2023-09-29 13:30 | D74: 105 | E74: 9.8910632 | F74: 5.3792059 | G74: =INDEX(Panel!$U$5:$U$815,D74+1) -> 4.3423895 | H74: =INDEX(Panel!$T$5:$T$815,D74+1) -> 1.0330804 | I74: =INDEX(Panel!$S$5:$S$815,D74+1) -> -0.00013368028 | J74: =INDEX(Panel!$V$5:$V$815,D74+1) -> 0.0020419793 | K74: =(E74-G74-H74*F74-I74*D74)/J74 -> 2.7217805 | L74: 2.5 | M74: =IF(ABS(K74)>L74,"Yes","No") -> Yes | N74: 2023-09-29 13:45 | O74: 105 | P74: 19775.25 | Q74: 216.97 | R74: 2023-10-26 15:15 | S74: 122 | T74: 18859 | U74: 208.8 | V74: expiry | W74: =B74*(LN(T74)-LN(P74)) -> 0.047440902 | X74: =IF(INDEX(Panel!$A$5:$A$815,O74+1)<=DATE(2024,9,30),0.000625,IF(INDEX(Panel!$A$5:$A$815,O74+1)<=DATE(2026,3,31),0.001,0.0015))*(0.3989*Inputs!$B$28*SQRT(MAX(INDEX(Panel!$G$5:$G$815,O74+1),0)/365))+2*Inputs!$B$29+Inputs!$B$19+0.00003*(0.3989*Inputs!$B$28*SQRT(MAX(INDEX(Panel!$G$5:$G$815,O74+1),0)/365))+0 -> 0.00011494876 | Y74: =IF(V74="expiry",IF(INDEX(Panel!$A$5:$A$815,S74+1)<=DATE(2026,3,31),0.00125,0.0015)*IF(B74<0,MAX(P74-T74,0),MAX(T74-P74,0))/T74,IF(INDEX(Panel!$A$5:$A$815,S74+1)<=DATE(2024,9,30),0.000625,IF(INDEX(Panel!$A$5:$A$815,S74+1)<=DATE(2026,3,31),0.001,0.0015))*(0.3989*Inputs!$B$28*SQRT(MAX(INDEX(Panel!$G$5:$G$815,S74+1),0)/365))+2*Inputs!$B$29+Inputs!$B$19)+0 -> 6.0730288e-05 | Z74: =0 -> 0 | AA74: =W74-X74-Y74+Z74 -> 0.047265223 | AB74: 0.047265223 | AC74: =AA74-AB74 -> 0
A75: rohan | B75: -1 | C75: 2023-10-27 09:45 | D75: 123 | E75: 9.8566527 | F75: 5.3465359 | G75: =INDEX(Panel!$U$5:$U$815,D75+1) -> 4.3831546 | H75: =INDEX(Panel!$T$5:$T$815,D75+1) -> 1.025347 | I75: =INDEX(Panel!$S$5:$S$815,D75+1) -> -0.00012000142 | J75: =INDEX(Panel!$V$5:$V$815,D75+1) -> 0.0020221093 | K75: =(E75-G75-H75*F75-I75*D75)/J75 -> 3.0680249 | L75: 2.5 | M75: =IF(ABS(K75)>L75,"Yes","No") -> Yes | N75: 2023-10-27 10:00 | O75: 123 | P75: 19075.35 | Q75: 209.91 | R75: 2023-11-30 15:15 | S75: 145 | T75: 20134 | U75: 222.23 | V75: expiry | W75: =B75*(LN(T75)-LN(P75)) -> -0.054013003 | X75: =IF(INDEX(Panel!$A$5:$A$815,O75+1)<=DATE(2024,9,30),0.000625,IF(INDEX(Panel!$A$5:$A$815,O75+1)<=DATE(2026,3,31),0.001,0.0015))*(0.3989*Inputs!$B$28*SQRT(MAX(INDEX(Panel!$G$5:$G$815,O75+1),0)/365))+2*Inputs!$B$29+Inputs!$B$19+0.00003*(0.3989*Inputs!$B$28*SQRT(MAX(INDEX(Panel!$G$5:$G$815,O75+1),0)/365))+0 -> 0.00011616417 | Y75: =IF(V75="expiry",IF(INDEX(Panel!$A$5:$A$815,S75+1)<=DATE(2026,3,31),0.00125,0.0015)*IF(B75<0,MAX(P75-T75,0),MAX(T75-P75,0))/T75,IF(INDEX(Panel!$A$5:$A$815,S75+1)<=DATE(2024,9,30),0.000625,IF(INDEX(Panel!$A$5:$A$815,S75+1)<=DATE(2026,3,31),0.001,0.0015))*(0.3989*Inputs!$B$28*SQRT(MAX(INDEX(Panel!$G$5:$G$815,S75+1),0)/365))+2*Inputs!$B$29+Inputs!$B$19)+0 -> 0 | Z75: =0 -> 0 | AA75: =W75-X75-Y75+Z75 -> -0.054129167 | AB75: -0.054129167 | AC75: =AA75-AB75 -> 0
A76: rohan | B76: -1 | C76: 2023-12-01 09:15 | D76: 146 | E76: 9.9212268 | F76: 5.4076201 | G76: =INDEX(Panel!$U$5:$U$815,D76+1) -> 4.6018034 | H76: =INDEX(Panel!$T$5:$T$815,D76+1) -> 0.98395675 | I76: =INDEX(Panel!$S$5:$S$815,D76+1) -> -6.5832204e-05 | J76: =INDEX(Panel!$V$5:$V$815,D76+1) -> 0.0023156597 | K76: =(E76-G76-H76*F76-I76*D76)/J76 -> 3.5283871 | L76: 2.5 | M76: =IF(ABS(K76)>L76,"Yes","No") -> Yes | N76: 2023-12-01 09:30 | O76: 146 | P76: 20346.6 | Q76: 223 | R76: 2023-12-28 15:15 | S76: 164 | T76: 21780.75 | U76: 240.24 | V76: expiry | W76: =B76*(LN(T76)-LN(P76)) -> -0.06811273 | X76: =IF(INDEX(Panel!$A$5:$A$815,O76+1)<=DATE(2024,9,30),0.000625,IF(INDEX(Panel!$A$5:$A$815,O76+1)<=DATE(2026,3,31),0.001,0.0015))*(0.3989*Inputs!$B$28*SQRT(MAX(INDEX(Panel!$G$5:$G$815,O76+1),0)/365))+2*Inputs!$B$29+Inputs!$B$19+0.00003*(0.3989*Inputs!$B$28*SQRT(MAX(INDEX(Panel!$G$5:$G$815,O76+1),0)/365))+0 -> 0.00011494876 | Y76: =IF(V76="expiry",IF(INDEX(Panel!$A$5:$A$815,S76+1)<=DATE(2026,3,31),0.00125,0.0015)*IF(B76<0,MAX(P76-T76,0),MAX(T76-P76,0))/T76,IF(INDEX(Panel!$A$5:$A$815,S76+1)<=DATE(2024,9,30),0.000625,IF(INDEX(Panel!$A$5:$A$815,S76+1)<=DATE(2026,3,31),0.001,0.0015))*(0.3989*Inputs!$B$28*SQRT(MAX(INDEX(Panel!$G$5:$G$815,S76+1),0)/365))+2*Inputs!$B$29+Inputs!$B$19)+0 -> 0 | Z76: =0 -> 0 | AA76: =W76-X76-Y76+Z76 -> -0.068227679 | AB76: -0.068227679 | AC76: =AA76-AB76 -> 0
A77: rohan | B77: -1 | C77: 2023-12-29 09:15 | D77: 165 | E77: 9.9947418 | F77: 5.4802222 | G77: =INDEX(Panel!$U$5:$U$815,D77+1) -> 4.3928634 | H77: =INDEX(Panel!$T$5:$T$815,D77+1) -> 1.0231243 | I77: =INDEX(Panel!$S$5:$S$815,D77+1) -> -7.2978375e-05 | J77: =INDEX(Panel!$V$5:$V$815,D77+1) -> 0.002675989 | K77: =(E77-G77-H77*F77-I77*D77)/J77 -> 2.6050725 | L77: 2.5 | M77: =IF(ABS(K77)>L77,"Yes","No") -> Yes | N77: 2023-12-29 09:30 | O77: 165 | P77: 21895.85 | Q77: 239.89 | R77: 2024-01-25 15:15 | S77: 184 | T77: 21351 | U77: 236.7 | V77: expiry | W77: =B77*(LN(T77)-LN(P77)) -> 0.025198544 | X77: =IF(INDEX(Panel!$A$5:$A$815,O77+1)<=DATE(2024,9,30),0.000625,IF(INDEX(Panel!$A$5:$A$815,O77+1)<=DATE(2026,3,31),0.001,0.0015))*(0.3989*Inputs!$B$28*SQRT(MAX(INDEX(Panel!$G$5:$G$815,O77+1),0)/365))+2*Inputs!$B$29+Inputs!$B$19+0.00003*(0.3989*Inputs!$B$28*SQRT(MAX(INDEX(Panel!$G$5:$G$815,O77+1),0)/365))+0 -> 0.00011494876 | Y77: =IF(V77="expiry",IF(INDEX(Panel!$A$5:$A$815,S77+1)<=DATE(2026,3,31),0.00125,0.0015)*IF(B77<0,MAX(P77-T77,0),MAX(T77-P77,0))/T77,IF(INDEX(Panel!$A$5:$A$815,S77+1)<=DATE(2024,9,30),0.000625,IF(INDEX(Panel!$A$5:$A$815,S77+1)<=DATE(2026,3,31),0.001,0.0015))*(0.3989*Inputs!$B$28*SQRT(MAX(INDEX(Panel!$G$5:$G$815,S77+1),0)/365))+2*Inputs!$B$29+Inputs!$B$19)+0 -> 3.1898389e-05 | Z77: =0 -> 0 | AA77: =W77-X77-Y77+Z77 -> 0.025051697 | AB77: 0.025051697 | AC77: =AA77-AB77 -> 0
A78: rohan | B78: -1 | C78: 2025-12-31 09:15 | D78: 662 | E78: 10.172636 | F78: 5.6835458 | G78: =INDEX(Panel!$U$5:$U$815,D78+1) -> 4.3840657 | H78: =INDEX(Panel!$T$5:$T$815,D78+1) -> 1.0253067 | I78: =INDEX(Panel!$S$5:$S$815,D78+1) -> -6.6993394e-05 | J78: =INDEX(Panel!$V$5:$V$815,D78+1) -> 0.0021890025 | K78: =(E78-G78-H78*F78-I78*D78)/J78 -> 2.5320295 | L78: 2.5 | M78: =IF(ABS(K78)>L78,"Yes","No") -> Yes | N78: 2025-12-31 09:30 | O78: 662 | P78: 26138 | Q78: 293.69 | R78: 2026-01-27 15:15 | S78: 679 | T78: 25174 | U78: 285.89 | V78: expiry | W78: =B78*(LN(T78)-LN(P78)) -> 0.037578478 | X78: =IF(INDEX(Panel!$A$5:$A$815,O78+1)<=DATE(2024,9,30),0.000625,IF(INDEX(Panel!$A$5:$A$815,O78+1)<=DATE(2026,3,31),0.001,0.0015))*(0.3989*Inputs!$B$28*SQRT(MAX(INDEX(Panel!$G$5:$G$815,O78+1),0)/365))+2*Inputs!$B$29+Inputs!$B$19+0.00003*(0.3989*Inputs!$B$28*SQRT(MAX(INDEX(Panel!$G$5:$G$815,O78+1),0)/365))+0 -> 0.00012064461 | Y78: =IF(V78="expiry",IF(INDEX(Panel!$A$5:$A$815,S78+1)<=DATE(2026,3,31),0.00125,0.0015)*IF(B78<0,MAX(P78-T78,0),MAX(T78-P78,0))/T78,IF(INDEX(Panel!$A$5:$A$815,S78+1)<=DATE(2024,9,30),0.000625,IF(INDEX(Panel!$A$5:$A$815,S78+1)<=DATE(2026,3,31),0.001,0.0015))*(0.3989*Inputs!$B$28*SQRT(MAX(INDEX(Panel!$G$5:$G$815,S78+1),0)/365))+2*Inputs!$B$29+Inputs!$B$19)+0 -> 4.7866847e-05 | Z78: =0 -> 0 | AA78: =W78-X78-Y78+Z78 -> 0.037409967 | AB78: 0.037409967 | AC78: =AA78-AB78 -> 0
A79: rohan | B79: -1 | C79: 2026-01-29 10:00 | D79: 681 | E79: 10.139271 | F79: 5.6518574 | G79: =INDEX(Panel!$U$5:$U$815,D79+1) -> 4.3701615 | H79: =INDEX(Panel!$T$5:$T$815,D79+1) -> 1.0279238 | I79: =INDEX(Panel!$S$5:$S$815,D79+1) -> -6.8214477e-05 | J79: =INDEX(Panel!$V$5:$V$815,D79+1) -> 0.0022741128 | K79: =(E79-G79-H79*F79-I79*D79)/J79 -> 2.5878082 | L79: 2.5 | M79: =IF(ABS(K79)>L79,"Yes","No") -> Yes | N79: 2026-01-29 10:15 | O79: 681 | P79: 25292.5 | Q79: 284.6 | R79: 2026-02-24 15:15 | S79: 700 | T79: 25423.4 | U79: 288 | V79: expiry | W79: =B79*(LN(T79)-LN(P79)) -> -0.0051621007 | X79: =IF(INDEX(Panel!$A$5:$A$815,O79+1)<=DATE(2024,9,30),0.000625,IF(INDEX(Panel!$A$5:$A$815,O79+1)<=DATE(2026,3,31),0.001,0.0015))*(0.3989*Inputs!$B$28*SQRT(MAX(INDEX(Panel!$G$5:$G$815,O79+1),0)/365))+2*Inputs!$B$29+Inputs!$B$19+0.00003*(0.3989*Inputs!$B$28*SQRT(MAX(INDEX(Panel!$G$5:$G$815,O79+1),0)/365))+0 -> 0.00012035216 | Y79: =IF(V79="expiry",IF(INDEX(Panel!$A$5:$A$815,S79+1)<=DATE(2026,3,31),0.00125,0.0015)*IF(B79<0,MAX(P79-T79,0),MAX(T79-P79,0))/T79,IF(INDEX(Panel!$A$5:$A$815,S79+1)<=DATE(2024,9,30),0.000625,IF(INDEX(Panel!$A$5:$A$815,S79+1)<=DATE(2026,3,31),0.001,0.0015))*(0.3989*Inputs!$B$28*SQRT(MAX(INDEX(Panel!$G$5:$G$815,S79+1),0)/365))+2*Inputs!$B$29+Inputs!$B$19)+0 -> 0 | Z79: =0 -> 0 | AA79: =W79-X79-Y79+Z79 -> -0.0052824528 | AB79: -0.0052824528 | AC79: =AA79-AB79 -> -6.1582683e-17
A80: rohan | B80: -1 | C80: 2026-02-25 09:15 | D80: 701 | E80: 10.15617 | F80: 5.6680171 | G80: =INDEX(Panel!$U$5:$U$815,D80+1) -> 4.3958176 | H80: =INDEX(Panel!$T$5:$T$815,D80+1) -> 1.0232593 | I80: =INDEX(Panel!$S$5:$S$815,D80+1) -> -6.6785699e-05 | J80: =INDEX(Panel!$V$5:$V$815,D80+1) -> 0.0022690512 | K80: =(E80-G80-H80*F80-I80*D80)/J80 -> 3.2252779 | L80: 2.5 | M80: =IF(ABS(K80)>L80,"Yes","No") -> Yes | N80: 2026-02-25 09:30 | O80: 701 | P80: 25720 | Q80: 289.32 | R80: 2026-03-30 15:15 | S80: 722 | T80: 22330 | U80: 255.26 | V80: expiry | W80: =B80*(LN(T80)-LN(P80)) -> 0.14133783 | X80: =IF(INDEX(Panel!$A$5:$A$815,O80+1)<=DATE(2024,9,30),0.000625,IF(INDEX(Panel!$A$5:$A$815,O80+1)<=DATE(2026,3,31),0.001,0.0015))*(0.3989*Inputs!$B$28*SQRT(MAX(INDEX(Panel!$G$5:$G$815,O80+1),0)/365))+2*Inputs!$B$29+Inputs!$B$19+0.00003*(0.3989*Inputs!$B$28*SQRT(MAX(INDEX(Panel!$G$5:$G$815,O80+1),0)/365))+0 -> 0.00012229577 | Y80: =IF(V80="expiry",IF(INDEX(Panel!$A$5:$A$815,S80+1)<=DATE(2026,3,31),0.00125,0.0015)*IF(B80<0,MAX(P80-T80,0),MAX(T80-P80,0))/T80,IF(INDEX(Panel!$A$5:$A$815,S80+1)<=DATE(2024,9,30),0.000625,IF(INDEX(Panel!$A$5:$A$815,S80+1)<=DATE(2026,3,31),0.001,0.0015))*(0.3989*Inputs!$B$28*SQRT(MAX(INDEX(Panel!$G$5:$G$815,S80+1),0)/365))+2*Inputs!$B$29+Inputs!$B$19)+0 -> 0.00018976713 | Z80: =0 -> 0 | AA80: =W80-X80-Y80+Z80 -> 0.14102577 | AB80: 0.14102577 | AC80: =AA80-AB80 -> 0
A81: rohan | B81: -1 | C81: 2026-04-01 11:30 | D81: 723 | E81: 10.039268 | F81: 5.554857 | G81: =INDEX(Panel!$U$5:$U$815,D81+1) -> 4.4280662 | H81: =INDEX(Panel!$T$5:$T$815,D81+1) -> 1.0169977 | I81: =INDEX(Panel!$S$5:$S$815,D81+1) -> -6.1285691e-05 | J81: =INDEX(Panel!$V$5:$V$815,D81+1) -> 0.0024172452 | K81: =(E81-G81-H81*F81-I81*D81)/J81 -> 2.579146 | L81: 2.5 | M81: =IF(ABS(K81)>L81,"Yes","No") -> Yes | N81: 2026-04-01 11:45 | O81: 723 | P81: 22884.9 | Q81: 258.29 | R81: 2026-04-28 15:15 | S81: 740 | T81: 23994.1 | U81: 271.8 | V81: expiry | W81: =B81*(LN(T81)-LN(P81)) -> -0.047330662 | X81: =IF(INDEX(Panel!$A$5:$A$815,O81+1)<=DATE(2024,9,30),0.000625,IF(INDEX(Panel!$A$5:$A$815,O81+1)<=DATE(2026,3,31),0.001,0.0015))*(0.3989*Inputs!$B$28*SQRT(MAX(INDEX(Panel!$G$5:$G$815,O81+1),0)/365))+2*Inputs!$B$29+Inputs!$B$19+0.00003*(0.3989*Inputs!$B$28*SQRT(MAX(INDEX(Panel!$G$5:$G$815,O81+1),0)/365))+0 -> 0.00012823908 | Y81: =IF(V81="expiry",IF(INDEX(Panel!$A$5:$A$815,S81+1)<=DATE(2026,3,31),0.00125,0.0015)*IF(B81<0,MAX(P81-T81,0),MAX(T81-P81,0))/T81,IF(INDEX(Panel!$A$5:$A$815,S81+1)<=DATE(2024,9,30),0.000625,IF(INDEX(Panel!$A$5:$A$815,S81+1)<=DATE(2026,3,31),0.001,0.0015))*(0.3989*Inputs!$B$28*SQRT(MAX(INDEX(Panel!$G$5:$G$815,S81+1),0)/365))+2*Inputs!$B$29+Inputs!$B$19)+0 -> 0 | Z81: =0 -> 0 | AA81: =W81-X81-Y81+Z81 -> -0.047458901 | AB81: -0.047458901 | AC81: =AA81-AB81 -> 0
A82: rohan | B82: -1 | C82: 2026-04-29 09:15 | D82: 741 | E82: 10.094108 | F82: 5.6081522 | G82: =INDEX(Panel!$U$5:$U$815,D82+1) -> 4.4692644 | H82: =INDEX(Panel!$T$5:$T$815,D82+1) -> 1.0088384 | I82: =INDEX(Panel!$S$5:$S$815,D82+1) -> -5.3053487e-05 | J82: =INDEX(Panel!$V$5:$V$815,D82+1) -> 0.0025090561 | K82: =(E82-G82-H82*F82-I82*D82)/J82 -> 2.5655058 | L82: 2.5 | M82: =IF(ABS(K82)>L82,"Yes","No") -> Yes | N82: 2026-04-29 09:30 | O82: 741 | P82: 24229.2 | Q82: 272.86 | R82: 2026-05-26 15:15 | S82: 759 | T82: 23911.2 | U82: 271.07 | V82: expiry | W82: =B82*(LN(T82)-LN(P82)) -> 0.013211549 | X82: =IF(INDEX(Panel!$A$5:$A$815,O82+1)<=DATE(2024,9,30),0.000625,IF(INDEX(Panel!$A$5:$A$815,O82+1)<=DATE(2026,3,31),0.001,0.0015))*(0.3989*Inputs!$B$28*SQRT(MAX(INDEX(Panel!$G$5:$G$815,O82+1),0)/365))+2*Inputs!$B$29+Inputs!$B$19+0.00003*(0.3989*Inputs!$B$28*SQRT(MAX(INDEX(Panel!$G$5:$G$815,O82+1),0)/365))+0 -> 0.00012823908 | Y82: =IF(V82="expiry",IF(INDEX(Panel!$A$5:$A$815,S82+1)<=DATE(2026,3,31),0.00125,0.0015)*IF(B82<0,MAX(P82-T82,0),MAX(T82-P82,0))/T82,IF(INDEX(Panel!$A$5:$A$815,S82+1)<=DATE(2024,9,30),0.000625,IF(INDEX(Panel!$A$5:$A$815,S82+1)<=DATE(2026,3,31),0.001,0.0015))*(0.3989*Inputs!$B$28*SQRT(MAX(INDEX(Panel!$G$5:$G$815,S82+1),0)/365))+2*Inputs!$B$29+Inputs!$B$19)+0 -> 1.9948811e-05 | Z82: =0 -> 0 | AA82: =W82-X82-Y82+Z82 -> 0.013063361 | AB82: 0.013063361 | AC82: =AA82-AB82 -> 0
A83: kavya | B83: -1 | C83: 2023-07-28 12:30 | D83: 62 | E83: 9.8889829 | F83: 5.3741203 | G83: =INDEX(Panel!$U$5:$U$815,D83+1) -> 4.2338414 | H83: =INDEX(Panel!$T$5:$T$815,D83+1) -> 1.0538075 | I83: =INDEX(Panel!$S$5:$S$815,D83+1) -> -0.00020051329 | J83: =INDEX(Panel!$V$5:$V$815,D83+1) -> 0.0016779358 | K83: =(E83-G83-H83*F83-I83*D83)/J83 -> 2.5536613 | L83: 2.5 | M83: =IF(ABS(K83)>L83,"Yes","No") -> Yes | N83: 2023-07-28 12:45 | O83: 62 | P83: 19702.2 | Q83: 215.69 | R83: 2023-08-31 15:15 | S83: 85 | T83: 19254 | U83: 213.2 | V83: expiry | W83: =B83*((LN(T83)-LN(P83))-(LN(U83)-LN(Q83))) -> 0.011399974 | X83: =IF(INDEX(Panel!$A$5:$A$815,O83+1)<=DATE(2024,9,30),0.000625,IF(INDEX(Panel!$A$5:$A$815,O83+1)<=DATE(2026,3,31),0.001,0.0015))*(0.3989*Inputs!$B$28*SQRT(MAX(INDEX(Panel!$G$5:$G$815,O83+1),0)/365))+2*Inputs!$B$30+Inputs!$B$25+0.00003*(0.3989*Inputs!$B$28*SQRT(MAX(INDEX(Panel!$G$5:$G$815,O83+1),0)/365))+IF(B83<0,(Inputs!$B$20+Inputs!$B$26+Inputs!$B$27),(Inputs!$B$21+Inputs!$B$26+Inputs!$B$27)) -> 0.00031816417 | Y83: =IF(V83="expiry",IF(INDEX(Panel!$A$5:$A$815,S83+1)<=DATE(2026,3,31),0.00125,0.0015)*IF(B83<0,MAX(P83-T83,0),MAX(T83-P83,0))/T83,IF(INDEX(Panel!$A$5:$A$815,S83+1)<=DATE(2024,9,30),0.000625,IF(INDEX(Panel!$A$5:$A$815,S83+1)<=DATE(2026,3,31),0.001,0.0015))*(0.3989*Inputs!$B$28*SQRT(MAX(INDEX(Panel!$G$5:$G$815,S83+1),0)/365))+2*Inputs!$B$30+Inputs!$B$25)+IF(B83<0,(Inputs!$B$21+Inputs!$B$26+Inputs!$B$27),(Inputs!$B$20+Inputs!$B$26+Inputs!$B$27)) -> 0.00014409785 | Z83: =B83*SUMPRODUCT((Panel!$F$5:$F$815>=O83)*(Panel!$F$5:$F$815<S83)*(Panel!$N$5:$N$815+Inputs!$B$14)*Panel!$BD$5:$BD$815)/365 -> -0.0067534247 | AA83: =W83-X83-Y83+Z83 -> 0.0041842873 | AB83: 0.0041842873 | AC83: =AA83-AB83 -> 4.3368087e-17
A84: kavya | B84: -1 | C84: 2023-09-01 09:15 | D84: 86 | E84: 9.8724612 | F84: 5.3609165 | G84: =INDEX(Panel!$U$5:$U$815,D84+1) -> 4.2252851 | H84: =INDEX(Panel!$T$5:$T$815,D84+1) -> 1.0553828 | I84: =INDEX(Panel!$S$5:$S$815,D84+1) -> -0.0001905105 | J84: =INDEX(Panel!$V$5:$V$815,D84+1) -> 0.0017694952 | K84: =(E84-G84-H84*F84-I84*D84)/J84 -> 3.2443583 | L84: 2.5 | M84: =IF(ABS(K84)>L84,"Yes","No") -> Yes | N84: 2023-09-01 09:30 | O84: 86 | P84: 19409 | Q84: 213.19 | R84: 2023-09-28 15:15 | S84: 104 | T84: 19525 | U84: 216.14 | V84: expiry | W84: =B84*((LN(T84)-LN(P84))-(LN(U84)-LN(Q84))) -> 0.0077837393 | X84: =IF(INDEX(Panel!$A$5:$A$815,O84+1)<=DATE(2024,9,30),0.000625,IF(INDEX(Panel!$A$5:$A$815,O84+1)<=DATE(2026,3,31),0.001,0.0015))*(0.3989*Inputs!$B$28*SQRT(MAX(INDEX(Panel!$G$5:$G$815,O84+1),0)/365))+2*Inputs!$B$30+Inputs!$B$25+0.00003*(0.3989*Inputs!$B$28*SQRT(MAX(INDEX(Panel!$G$5:$G$815,O84+1),0)/365))+IF(B84<0,(Inputs!$B$20+Inputs!$B$26+Inputs!$B$27),(Inputs!$B$21+Inputs!$B$26+Inputs!$B$27)) -> 0.00031694876 | Y84: =IF(V84="expiry",IF(INDEX(Panel!$A$5:$A$815,S84+1)<=DATE(2026,3,31),0.00125,0.0015)*IF(B84<0,MAX(P84-T84,0),MAX(T84-P84,0))/T84,IF(INDEX(Panel!$A$5:$A$815,S84+1)<=DATE(2024,9,30),0.000625,IF(INDEX(Panel!$A$5:$A$815,S84+1)<=DATE(2026,3,31),0.001,0.0015))*(0.3989*Inputs!$B$28*SQRT(MAX(INDEX(Panel!$G$5:$G$815,S84+1),0)/365))+2*Inputs!$B$30+Inputs!$B$25)+IF(B84<0,(Inputs!$B$21+Inputs!$B$26+Inputs!$B$27),(Inputs!$B$20+Inputs!$B$26+Inputs!$B$27)) -> 0.000115 | Z84: =B84*SUMPRODUCT((Panel!$F$5:$F$815>=O84)*(Panel!$F$5:$F$815<S84)*(Panel!$N$5:$N$815+Inputs!$B$14)*Panel!$BD$5:$BD$815)/365 -> -0.0053630137 | AA84: =W84-X84-Y84+Z84 -> 0.0019887768 | AB84: 0.0019887768 | AC84: =AA84-AB84 -> 8.7603536e-17
A85: kavya | B85: -1 | C85: 2023-09-29 13:30 | D85: 105 | E85: 9.8910632 | F85: 5.3792059 | G85: =INDEX(Panel!$U$5:$U$815,D85+1) -> 4.3423895 | H85: =INDEX(Panel!$T$5:$T$815,D85+1) -> 1.0330804 | I85: =INDEX(Panel!$S$5:$S$815,D85+1) -> -0.00013368028 | J85: =INDEX(Panel!$V$5:$V$815,D85+1) -> 0.0020419793 | K85: =(E85-G85-H85*F85-I85*D85)/J85 -> 2.7217805 | L85: 2.5 | M85: =IF(ABS(K85)>L85,"Yes","No") -> Yes | N85: 2023-09-29 13:45 | O85: 105 | P85: 19775.25 | Q85: 216.97 | R85: 2023-10-26 15:15 | S85: 122 | T85: 18859 | U85: 208.8 | V85: expiry | W85: =B85*((LN(T85)-LN(P85))-(LN(U85)-LN(Q85))) -> 0.0090586631 | X85: =IF(INDEX(Panel!$A$5:$A$815,O85+1)<=DATE(2024,9,30),0.000625,IF(INDEX(Panel!$A$5:$A$815,O85+1)<=DATE(2026,3,31),0.001,0.0015))*(0.3989*Inputs!$B$28*SQRT(MAX(INDEX(Panel!$G$5:$G$815,O85+1),0)/365))+2*Inputs!$B$30+Inputs!$B$25+0.00003*(0.3989*Inputs!$B$28*SQRT(MAX(INDEX(Panel!$G$5:$G$815,O85+1),0)/365))+IF(B85<0,(Inputs!$B$20+Inputs!$B$26+Inputs!$B$27),(Inputs!$B$21+Inputs!$B$26+Inputs!$B$27)) -> 0.00031694876 | Y85: =IF(V85="expiry",IF(INDEX(Panel!$A$5:$A$815,S85+1)<=DATE(2026,3,31),0.00125,0.0015)*IF(B85<0,MAX(P85-T85,0),MAX(T85-P85,0))/T85,IF(INDEX(Panel!$A$5:$A$815,S85+1)<=DATE(2024,9,30),0.000625,IF(INDEX(Panel!$A$5:$A$815,S85+1)<=DATE(2026,3,31),0.001,0.0015))*(0.3989*Inputs!$B$28*SQRT(MAX(INDEX(Panel!$G$5:$G$815,S85+1),0)/365))+2*Inputs!$B$30+Inputs!$B$25)+IF(B85<0,(Inputs!$B$21+Inputs!$B$26+Inputs!$B$27),(Inputs!$B$20+Inputs!$B$26+Inputs!$B$27)) -> 0.00017573029 | Z85: =B85*SUMPRODUCT((Panel!$F$5:$F$815>=O85)*(Panel!$F$5:$F$815<S85)*(Panel!$N$5:$N$815+Inputs!$B$14)*Panel!$BD$5:$BD$815)/365 -> -0.0053630137 | AA85: =W85-X85-Y85+Z85 -> 0.0032029704 | AB85: 0.0032029704 | AC85: =AA85-AB85 -> 2.8622937e-17
A86: kavya | B86: -1 | C86: 2023-10-27 09:45 | D86: 123 | E86: 9.8566527 | F86: 5.3465359 | G86: =INDEX(Panel!$U$5:$U$815,D86+1) -> 4.3831546 | H86: =INDEX(Panel!$T$5:$T$815,D86+1) -> 1.025347 | I86: =INDEX(Panel!$S$5:$S$815,D86+1) -> -0.00012000142 | J86: =INDEX(Panel!$V$5:$V$815,D86+1) -> 0.0020221093 | K86: =(E86-G86-H86*F86-I86*D86)/J86 -> 3.0680249 | L86: 2.5 | M86: =IF(ABS(K86)>L86,"Yes","No") -> Yes | N86: 2023-10-27 10:00 | O86: 123 | P86: 19075.35 | Q86: 209.91 | R86: 2023-11-30 15:15 | S86: 145 | T86: 20134 | U86: 222.23 | V86: expiry | W86: =B86*((LN(T86)-LN(P86))-(LN(U86)-LN(Q86))) -> 0.0030210115 | X86: =IF(INDEX(Panel!$A$5:$A$815,O86+1)<=DATE(2024,9,30),0.000625,IF(INDEX(Panel!$A$5:$A$815,O86+1)<=DATE(2026,3,31),0.001,0.0015))*(0.3989*Inputs!$B$28*SQRT(MAX(INDEX(Panel!$G$5:$G$815,O86+1),0)/365))+2*Inputs!$B$30+Inputs!$B$25+0.00003*(0.3989*Inputs!$B$28*SQRT(MAX(INDEX(Panel!$G$5:$G$815,O86+1),0)/365))+IF(B86<0,(Inputs!$B$20+Inputs!$B$26+Inputs!$B$27),(Inputs!$B$21+Inputs!$B$26+Inputs!$B$27)) -> 0.00031816417 | Y86: =IF(V86="expiry",IF(INDEX(Panel!$A$5:$A$815,S86+1)<=DATE(2026,3,31),0.00125,0.0015)*IF(B86<0,MAX(P86-T86,0),MAX(T86-P86,0))/T86,IF(INDEX(Panel!$A$5:$A$815,S86+1)<=DATE(2024,9,30),0.000625,IF(INDEX(Panel!$A$5:$A$815,S86+1)<=DATE(2026,3,31),0.001,0.0015))*(0.3989*Inputs!$B$28*SQRT(MAX(INDEX(Panel!$G$5:$G$815,S86+1),0)/365))+2*Inputs!$B$30+Inputs!$B$25)+IF(B86<0,(Inputs!$B$21+Inputs!$B$26+Inputs!$B$27),(Inputs!$B$20+Inputs!$B$26+Inputs!$B$27)) -> 0.000115 | Z86: =B86*SUMPRODUCT((Panel!$F$5:$F$815>=O86)*(Panel!$F$5:$F$815<S86)*(Panel!$N$5:$N$815+Inputs!$B$14)*Panel!$BD$5:$BD$815)/365 -> -0.0067534247 | AA86: =W86-X86-Y86+Z86 -> -0.0041655773 | AB86: -0.0041655773 | AC86: =AA86-AB86 -> -7.979728e-17
A87: kavya | B87: -1 | C87: 2023-12-01 09:15 | D87: 146 | E87: 9.9212268 | F87: 5.4076201 | G87: =INDEX(Panel!$U$5:$U$815,D87+1) -> 4.6018034 | H87: =INDEX(Panel!$T$5:$T$815,D87+1) -> 0.98395675 | I87: =INDEX(Panel!$S$5:$S$815,D87+1) -> -6.5832204e-05 | J87: =INDEX(Panel!$V$5:$V$815,D87+1) -> 0.0023156597 | K87: =(E87-G87-H87*F87-I87*D87)/J87 -> 3.5283871 | L87: 2.5 | M87: =IF(ABS(K87)>L87,"Yes","No") -> Yes | N87: 2023-12-01 09:30 | O87: 146 | P87: 20346.6 | Q87: 223 | R87: 2023-12-28 15:15 | S87: 164 | T87: 21780.75 | U87: 240.24 | V87: expiry | W87: =B87*((LN(T87)-LN(P87))-(LN(U87)-LN(Q87))) -> 0.0063539218 | X87: =IF(INDEX(Panel!$A$5:$A$815,O87+1)<=DATE(2024,9,30),0.000625,IF(INDEX(Panel!$A$5:$A$815,O87+1)<=DATE(2026,3,31),0.001,0.0015))*(0.3989*Inputs!$B$28*SQRT(MAX(INDEX(Panel!$G$5:$G$815,O87+1),0)/365))+2*Inputs!$B$30+Inputs!$B$25+0.00003*(0.3989*Inputs!$B$28*SQRT(MAX(INDEX(Panel!$G$5:$G$815,O87+1),0)/365))+IF(B87<0,(Inputs!$B$20+Inputs!$B$26+Inputs!$B$27),(Inputs!$B$21+Inputs!$B$26+Inputs!$B$27)) -> 0.00031694876 | Y87: =IF(V87="expiry",IF(INDEX(Panel!$A$5:$A$815,S87+1)<=DATE(2026,3,31),0.00125,0.0015)*IF(B87<0,MAX(P87-T87,0),MAX(T87-P87,0))/T87,IF(INDEX(Panel!$A$5:$A$815,S87+1)<=DATE(2024,9,30),0.000625,IF(INDEX(Panel!$A$5:$A$815,S87+1)<=DATE(2026,3,31),0.001,0.0015))*(0.3989*Inputs!$B$28*SQRT(MAX(INDEX(Panel!$G$5:$G$815,S87+1),0)/365))+2*Inputs!$B$30+Inputs!$B$25)+IF(B87<0,(Inputs!$B$21+Inputs!$B$26+Inputs!$B$27),(Inputs!$B$20+Inputs!$B$26+Inputs!$B$27)) -> 0.000115 | Z87: =B87*SUMPRODUCT((Panel!$F$5:$F$815>=O87)*(Panel!$F$5:$F$815<S87)*(Panel!$N$5:$N$815+Inputs!$B$14)*Panel!$BD$5:$BD$815)/365 -> -0.0053630137 | AA87: =W87-X87-Y87+Z87 -> 0.00055895935 | AB87: 0.00055895935 | AC87: =AA87-AB87 -> 4.8138576e-17
A88: kavya | B88: -1 | C88: 2023-12-29 09:15 | D88: 165 | E88: 9.9947418 | F88: 5.4802222 | G88: =INDEX(Panel!$U$5:$U$815,D88+1) -> 4.3928634 | H88: =INDEX(Panel!$T$5:$T$815,D88+1) -> 1.0231243 | I88: =INDEX(Panel!$S$5:$S$815,D88+1) -> -7.2978375e-05 | J88: =INDEX(Panel!$V$5:$V$815,D88+1) -> 0.002675989 | K88: =(E88-G88-H88*F88-I88*D88)/J88 -> 2.6050725 | L88: 2.5 | M88: =IF(ABS(K88)>L88,"Yes","No") -> Yes | N88: 2023-12-29 09:30 | O88: 165 | P88: 21895.85 | Q88: 239.89 | R88: 2024-01-25 15:15 | S88: 184 | T88: 21351 | U88: 236.7 | V88: expiry | W88: =B88*((LN(T88)-LN(P88))-(LN(U88)-LN(Q88))) -> 0.011811576 | X88: =IF(INDEX(Panel!$A$5:$A$815,O88+1)<=DATE(2024,9,30),0.000625,IF(INDEX(Panel!$A$5:$A$815,O88+1)<=DATE(2026,3,31),0.001,0.0015))*(0.3989*Inputs!$B$28*SQRT(MAX(INDEX(Panel!$G$5:$G$815,O88+1),0)/365))+2*Inputs!$B$30+Inputs!$B$25+0.00003*(0.3989*Inputs!$B$28*SQRT(MAX(INDEX(Panel!$G$5:$G$815,O88+1),0)/365))+IF(B88<0,(Inputs!$B$20+Inputs!$B$26+Inputs!$B$27),(Inputs!$B$21+Inputs!$B$26+Inputs!$B$27)) -> 0.00031694876 | Y88: =IF(V88="expiry",IF(INDEX(Panel!$A$5:$A$815,S88+1)<=DATE(2026,3,31),0.00125,0.0015)*IF(B88<0,MAX(P88-T88,0),MAX(T88-P88,0))/T88,IF(INDEX(Panel!$A$5:$A$815,S88+1)<=DATE(2024,9,30),0.000625,IF(INDEX(Panel!$A$5:$A$815,S88+1)<=DATE(2026,3,31),0.001,0.0015))*(0.3989*Inputs!$B$28*SQRT(MAX(INDEX(Panel!$G$5:$G$815,S88+1),0)/365))+2*Inputs!$B$30+Inputs!$B$25)+IF(B88<0,(Inputs!$B$21+Inputs!$B$26+Inputs!$B$27),(Inputs!$B$20+Inputs!$B$26+Inputs!$B$27)) -> 0.00014689839 | Z88: =B88*SUMPRODUCT((Panel!$F$5:$F$815>=O88)*(Panel!$F$5:$F$815<S88)*(Panel!$N$5:$N$815+Inputs!$B$14)*Panel!$BD$5:$BD$815)/365 -> -0.0053630137 | AA88: =W88-X88-Y88+Z88 -> 0.0059847149 | AB88: 0.0059847149 | AC88: =AA88-AB88 -> 6.505213e-17
A89: kavya | B89: 1 | C89: 2024-06-04 11:00 | D89: 271 | E89: 10.006166 | F89: 5.5176938 | G89: =INDEX(Panel!$U$5:$U$815,D89+1) -> 4.3271796 | H89: =INDEX(Panel!$T$5:$T$815,D89+1) -> 1.0351848 | I89: =INDEX(Panel!$S$5:$S$815,D89+1) -> -6.6531627e-05 | J89: =INDEX(Panel!$V$5:$V$815,D89+1) -> 0.0025584547 | K89: =(E89-G89-H89*F89-I89*D89)/J89 -> -5.7912342 | L89: 2.5 | M89: =IF(ABS(K89)>L89,"Yes","No") -> Yes | N89: 2024-06-04 11:15 | O89: 271 | P89: 22323.65 | Q89: 251 | R89: 2024-06-27 15:15 | S89: 287 | T89: 24047.1 | U89: 266.95 | V89: expiry | W89: =B89*((LN(T89)-LN(P89))-(LN(U89)-LN(Q89))) -> 0.012759317 | X89: =IF(INDEX(Panel!$A$5:$A$815,O89+1)<=DATE(2024,9,30),0.000625,IF(INDEX(Panel!$A$5:$A$815,O89+1)<=DATE(2026,3,31),0.001,0.0015))*(0.3989*Inputs!$B$28*SQRT(MAX(INDEX(Panel!$G$5:$G$815,O89+1),0)/365))+2*Inputs!$B$30+Inputs!$B$25+0.00003*(0.3989*Inputs!$B$28*SQRT(MAX(INDEX(Panel!$G$5:$G$815,O89+1),0)/365))+IF(B89<0,(Inputs!$B$20+Inputs!$B$26+Inputs!$B$27),(Inputs!$B$21+Inputs!$B$26+Inputs!$B$27)) -> 0.00017618229 | Y89: =IF(V89="expiry",IF(INDEX(Panel!$A$5:$A$815,S89+1)<=DATE(2026,3,31),0.00125,0.0015)*IF(B89<0,MAX(P89-T89,0),MAX(T89-P89,0))/T89,IF(INDEX(Panel!$A$5:$A$815,S89+1)<=DATE(2024,9,30),0.000625,IF(INDEX(Panel!$A$5:$A$815,S89+1)<=DATE(2026,3,31),0.001,0.0015))*(0.3989*Inputs!$B$28*SQRT(MAX(INDEX(Panel!$G$5:$G$815,S89+1),0)/365))+2*Inputs!$B$30+Inputs!$B$25)+IF(B89<0,(Inputs!$B$21+Inputs!$B$26+Inputs!$B$27),(Inputs!$B$20+Inputs!$B$26+Inputs!$B$27)) -> 0.00034458721 | Z89: =B89*SUMPRODUCT((Panel!$F$5:$F$815>=O89)*(Panel!$F$5:$F$815<S89)*(Panel!$N$5:$N$815+Inputs!$B$14)*Panel!$BD$5:$BD$815)/365 -> 0.0045684932 | AA89: =W89-X89-Y89+Z89 -> 0.01680704 | AB89: 0.01680704 | AC89: =AA89-AB89 -> 0
A90: kavya | B90: 1 | C90: 2024-08-05 14:15 | D90: 313 | E90: 10.088285 | F90: 5.5973473 | G90: =INDEX(Panel!$U$5:$U$815,D90+1) -> 4.4043408 | H90: =INDEX(Panel!$T$5:$T$815,D90+1) -> 1.0207352 | I90: =INDEX(Panel!$S$5:$S$815,D90+1) -> -6.1923508e-05 | J90: =INDEX(Panel!$V$5:$V$815,D90+1) -> 0.0035034126 | K90: =(E90-G90-H90*F90-I90*D90)/J90 -> -2.8780079 | L90: 2.5 | M90: =IF(ABS(K90)>L90,"Yes","No") -> Yes | N90: 2024-08-05 14:30 | O90: 313 | P90: 24103.75 | Q90: 269.8 | R90: 2024-08-29 15:15 | S90: 330 | T90: 25155.65 | U90: 280 | V90: expiry | W90: =B90*((LN(T90)-LN(P90))-(LN(U90)-LN(Q90))) -> 0.005606434 | X90: =IF(INDEX(Panel!$A$5:$A$815,O90+1)<=DATE(2024,9,30),0.000625,IF(INDEX(Panel!$A$5:$A$815,O90+1)<=DATE(2026,3,31),0.001,0.0015))*(0.3989*Inputs!$B$28*SQRT(MAX(INDEX(Panel!$G$5:$G$815,O90+1),0)/365))+2*Inputs!$B$30+Inputs!$B$25+0.00003*(0.3989*Inputs!$B$28*SQRT(MAX(INDEX(Panel!$G$5:$G$815,O90+1),0)/365))+IF(B90<0,(Inputs!$B$20+Inputs!$B$26+Inputs!$B$27),(Inputs!$B$21+Inputs!$B$26+Inputs!$B$27)) -> 0.00017637978 | Y90: =IF(V90="expiry",IF(INDEX(Panel!$A$5:$A$815,S90+1)<=DATE(2026,3,31),0.00125,0.0015)*IF(B90<0,MAX(P90-T90,0),MAX(T90-P90,0))/T90,IF(INDEX(Panel!$A$5:$A$815,S90+1)<=DATE(2024,9,30),0.000625,IF(INDEX(Panel!$A$5:$A$815,S90+1)<=DATE(2026,3,31),0.001,0.0015))*(0.3989*Inputs!$B$28*SQRT(MAX(INDEX(Panel!$G$5:$G$815,S90+1),0)/365))+2*Inputs!$B$30+Inputs!$B$25)+IF(B90<0,(Inputs!$B$21+Inputs!$B$26+Inputs!$B$27),(Inputs!$B$20+Inputs!$B$26+Inputs!$B$27)) -> 0.00030726957 | Z90: =B90*SUMPRODUCT((Panel!$F$5:$F$815>=O90)*(Panel!$F$5:$F$815<S90)*(Panel!$N$5:$N$815+Inputs!$B$14)*Panel!$BD$5:$BD$815)/365 -> 0.0047671233 | AA90: =W90-X90-Y90+Z90 -> 0.0098899079 | AB90: 0.0098899079 | AC90: =AA90-AB90 -> 0
A91: kavya | B91: 1 | C91: 2025-04-07 09:15 | D91: 480 | E91: 10.006044 | F91: 5.5212609 | G91: =INDEX(Panel!$U$5:$U$815,D91+1) -> 4.5940761 | H91: =INDEX(Panel!$T$5:$T$815,D91+1) -> 0.98559117 | I91: =INDEX(Panel!$S$5:$S$815,D91+1) -> -4.4453433e-05 | J91: =INDEX(Panel!$V$5:$V$815,D91+1) -> 0.0033300796 | K91: =(E91-G91-H91*F91-I91*D91)/J91 -> -2.5225353 | L91: 2.5 | M91: =IF(ABS(K91)>L91,"Yes","No") -> Yes | N91: 2025-04-07 09:30 | O91: 480 | P91: 22112.75 | Q91: 247.83 | R91: 2025-04-24 15:15 | S91: 490 | T91: 24248 | U91: 270.95 | V91: expiry | W91: =B91*((LN(T91)-LN(P91))-(LN(U91)-LN(Q91))) -> 0.0029884997 | X91: =IF(INDEX(Panel!$A$5:$A$815,O91+1)<=DATE(2024,9,30),0.000625,IF(INDEX(Panel!$A$5:$A$815,O91+1)<=DATE(2026,3,31),0.001,0.0015))*(0.3989*Inputs!$B$28*SQRT(MAX(INDEX(Panel!$G$5:$G$815,O91+1),0)/365))+2*Inputs!$B$30+Inputs!$B$25+0.00003*(0.3989*Inputs!$B$28*SQRT(MAX(INDEX(Panel!$G$5:$G$815,O91+1),0)/365))+IF(B91<0,(Inputs!$B$20+Inputs!$B$26+Inputs!$B$27),(Inputs!$B$21+Inputs!$B$26+Inputs!$B$27)) -> 0.00017941387 | Y91: =IF(V91="expiry",IF(INDEX(Panel!$A$5:$A$815,S91+1)<=DATE(2026,3,31),0.00125,0.0015)*IF(B91<0,MAX(P91-T91,0),MAX(T91-P91,0))/T91,IF(INDEX(Panel!$A$5:$A$815,S91+1)<=DATE(2024,9,30),0.000625,IF(INDEX(Panel!$A$5:$A$815,S91+1)<=DATE(2026,3,31),0.001,0.0015))*(0.3989*Inputs!$B$28*SQRT(MAX(INDEX(Panel!$G$5:$G$815,S91+1),0)/365))+2*Inputs!$B$30+Inputs!$B$25)+IF(B91<0,(Inputs!$B$21+Inputs!$B$26+Inputs!$B$27),(Inputs!$B$20+Inputs!$B$26+Inputs!$B$27)) -> 0.00036507351 | Z91: =B91*SUMPRODUCT((Panel!$F$5:$F$815>=O91)*(Panel!$F$5:$F$815<S91)*(Panel!$N$5:$N$815+Inputs!$B$14)*Panel!$BD$5:$BD$815)/365 -> 0.0031575342 | AA91: =W91-X91-Y91+Z91 -> 0.0056015466 | AB91: 0.0056015466 | AC91: =AA91-AB91 -> 6.0715322e-17
A92: kavya | B92: 1 | C92: 2025-07-25 12:15 | D92: 555 | E92: 10.120585 | F92: 5.6350753 | G92: =INDEX(Panel!$U$5:$U$815,D92+1) -> 4.4898244 | H92: =INDEX(Panel!$T$5:$T$815,D92+1) -> 1.0030923 | I92: =INDEX(Panel!$S$5:$S$815,D92+1) -> -2.8456652e-05 | J92: =INDEX(Panel!$V$5:$V$815,D92+1) -> 0.0023573445 | K92: =(E92-G92-H92*F92-I92*D92)/J92 -> -2.5226419 | L92: 2.5 | M92: =IF(ABS(K92)>L92,"Yes","No") -> Yes | N92: 2025-07-25 12:30 | O92: 555 | P92: 24874.8 | Q92: 280.33 | R92: 2025-07-31 15:15 | S92: 559 | T92: 24766.8 | U92: 279.34 | V92: expiry | W92: =B92*((LN(T92)-LN(P92))-(LN(U92)-LN(Q92))) -> -0.00081339344 | X92: =IF(INDEX(Panel!$A$5:$A$815,O92+1)<=DATE(2024,9,30),0.000625,IF(INDEX(Panel!$A$5:$A$815,O92+1)<=DATE(2026,3,31),0.001,0.0015))*(0.3989*Inputs!$B$28*SQRT(MAX(INDEX(Panel!$G$5:$G$815,O92+1),0)/365))+2*Inputs!$B$30+Inputs!$B$25+0.00003*(0.3989*Inputs!$B$28*SQRT(MAX(INDEX(Panel!$G$5:$G$815,O92+1),0)/365))+IF(B92<0,(Inputs!$B$20+Inputs!$B$26+Inputs!$B$27),(Inputs!$B$21+Inputs!$B$26+Inputs!$B$27)) -> 0.00017437494 | Y92: =IF(V92="expiry",IF(INDEX(Panel!$A$5:$A$815,S92+1)<=DATE(2026,3,31),0.00125,0.0015)*IF(B92<0,MAX(P92-T92,0),MAX(T92-P92,0))/T92,IF(INDEX(Panel!$A$5:$A$815,S92+1)<=DATE(2024,9,30),0.000625,IF(INDEX(Panel!$A$5:$A$815,S92+1)<=DATE(2026,3,31),0.001,0.0015))*(0.3989*Inputs!$B$28*SQRT(MAX(INDEX(Panel!$G$5:$G$815,S92+1),0)/365))+2*Inputs!$B$30+Inputs!$B$25)+IF(B92<0,(Inputs!$B$21+Inputs!$B$26+Inputs!$B$27),(Inputs!$B$20+Inputs!$B$26+Inputs!$B$27)) -> 0.000255 | Z92: =B92*SUMPRODUCT((Panel!$F$5:$F$815>=O92)*(Panel!$F$5:$F$815<S92)*(Panel!$N$5:$N$815+Inputs!$B$14)*Panel!$BD$5:$BD$815)/365 -> 0.0010273973 | AA92: =W92-X92-Y92+Z92 -> -0.00021537112 | AB92: -0.00021537112 | AC92: =AA92-AB92 -> -8.7115645e-17
A93: kavya | B93: -1 | C93: 2025-12-31 09:15 | D93: 662 | E93: 10.172636 | F93: 5.6835458 | G93: =INDEX(Panel!$U$5:$U$815,D93+1) -> 4.3840657 | H93: =INDEX(Panel!$T$5:$T$815,D93+1) -> 1.0253067 | I93: =INDEX(Panel!$S$5:$S$815,D93+1) -> -6.6993394e-05 | J93: =INDEX(Panel!$V$5:$V$815,D93+1) -> 0.0021890025 | K93: =(E93-G93-H93*F93-I93*D93)/J93 -> 2.5320295 | L93: 2.5 | M93: =IF(ABS(K93)>L93,"Yes","No") -> Yes | N93: 2025-12-31 09:30 | O93: 662 | P93: 26138 | Q93: 293.69 | R93: 2026-01-27 15:15 | S93: 679 | T93: 25174 | U93: 285.89 | V93: expiry | W93: =B93*((LN(T93)-LN(P93))-(LN(U93)-LN(Q93))) -> 0.01066081 | X93: =IF(INDEX(Panel!$A$5:$A$815,O93+1)<=DATE(2024,9,30),0.000625,IF(INDEX(Panel!$A$5:$A$815,O93+1)<=DATE(2026,3,31),0.001,0.0015))*(0.3989*Inputs!$B$28*SQRT(MAX(INDEX(Panel!$G$5:$G$815,O93+1),0)/365))+2*Inputs!$B$30+Inputs!$B$25+0.00003*(0.3989*Inputs!$B$28*SQRT(MAX(INDEX(Panel!$G$5:$G$815,O93+1),0)/365))+IF(B93<0,(Inputs!$B$20+Inputs!$B$26+Inputs!$B$27),(Inputs!$B$21+Inputs!$B$26+Inputs!$B$27)) -> 0.00032264461 | Y93: =IF(V93="expiry",IF(INDEX(Panel!$A$5:$A$815,S93+1)<=DATE(2026,3,31),0.00125,0.0015)*IF(B93<0,MAX(P93-T93,0),MAX(T93-P93,0))/T93,IF(INDEX(Panel!$A$5:$A$815,S93+1)<=DATE(2024,9,30),0.000625,IF(INDEX(Panel!$A$5:$A$815,S93+1)<=DATE(2026,3,31),0.001,0.0015))*(0.3989*Inputs!$B$28*SQRT(MAX(INDEX(Panel!$G$5:$G$815,S93+1),0)/365))+2*Inputs!$B$30+Inputs!$B$25)+IF(B93<0,(Inputs!$B$21+Inputs!$B$26+Inputs!$B$27),(Inputs!$B$20+Inputs!$B$26+Inputs!$B$27)) -> 0.00016286685 | Z93: =B93*SUMPRODUCT((Panel!$F$5:$F$815>=O93)*(Panel!$F$5:$F$815<S93)*(Panel!$N$5:$N$815+Inputs!$B$14)*Panel!$BD$5:$BD$815)/365 -> -0.0044383562 | AA93: =W93-X93-Y93+Z93 -> 0.0057369429 | AB93: 0.0057369429 | AC93: =AA93-AB93 -> 8.7603536e-17
A94: kavya | B94: -1 | C94: 2026-01-29 10:00 | D94: 681 | E94: 10.139271 | F94: 5.6518574 | G94: =INDEX(Panel!$U$5:$U$815,D94+1) -> 4.3701615 | H94: =INDEX(Panel!$T$5:$T$815,D94+1) -> 1.0279238 | I94: =INDEX(Panel!$S$5:$S$815,D94+1) -> -6.8214477e-05 | J94: =INDEX(Panel!$V$5:$V$815,D94+1) -> 0.0022741128 | K94: =(E94-G94-H94*F94-I94*D94)/J94 -> 2.5878082 | L94: 2.5 | M94: =IF(ABS(K94)>L94,"Yes","No") -> Yes | N94: 2026-01-29 10:15 | O94: 681 | P94: 25292.5 | Q94: 284.6 | R94: 2026-02-24 15:15 | S94: 700 | T94: 25423.4 | U94: 288 | V94: expiry | W94: =B94*((LN(T94)-LN(P94))-(LN(U94)-LN(Q94))) -> 0.0067136938 | X94: =IF(INDEX(Panel!$A$5:$A$815,O94+1)<=DATE(2024,9,30),0.000625,IF(INDEX(Panel!$A$5:$A$815,O94+1)<=DATE(2026,3,31),0.001,0.0015))*(0.3989*Inputs!$B$28*SQRT(MAX(INDEX(Panel!$G$5:$G$815,O94+1),0)/365))+2*Inputs!$B$30+Inputs!$B$25+0.00003*(0.3989*Inputs!$B$28*SQRT(MAX(INDEX(Panel!$G$5:$G$815,O94+1),0)/365))+IF(B94<0,(Inputs!$B$20+Inputs!$B$26+Inputs!$B$27),(Inputs!$B$21+Inputs!$B$26+Inputs!$B$27)) -> 0.00032235216 | Y94: =IF(V94="expiry",IF(INDEX(Panel!$A$5:$A$815,S94+1)<=DATE(2026,3,31),0.00125,0.0015)*IF(B94<0,MAX(P94-T94,0),MAX(T94-P94,0))/T94,IF(INDEX(Panel!$A$5:$A$815,S94+1)<=DATE(2024,9,30),0.000625,IF(INDEX(Panel!$A$5:$A$815,S94+1)<=DATE(2026,3,31),0.001,0.0015))*(0.3989*Inputs!$B$28*SQRT(MAX(INDEX(Panel!$G$5:$G$815,S94+1),0)/365))+2*Inputs!$B$30+Inputs!$B$25)+IF(B94<0,(Inputs!$B$21+Inputs!$B$26+Inputs!$B$27),(Inputs!$B$20+Inputs!$B$26+Inputs!$B$27)) -> 0.000115 | Z94: =B94*SUMPRODUCT((Panel!$F$5:$F$815>=O94)*(Panel!$F$5:$F$815<S94)*(Panel!$N$5:$N$815+Inputs!$B$14)*Panel!$BD$5:$BD$815)/365 -> -0.0042739726 | AA94: =W94-X94-Y94+Z94 -> 0.002002369 | AB94: 0.002002369 | AC94: =AA94-AB94 -> 9.1940344e-17
... A97: kavya | B97: -1 | C97: 2026-04-29 09:15 | D97: 741 | E97: 10.094108 | F97: 5.6081522 | G97: =INDEX(Panel!$U$5:$U$815,D97+1) -> 4.4692644 | H97: =INDEX(Panel!$T$5:$T$815,D97+1) -> 1.0088384 | I97: =INDEX(Panel!$S$5:$S$815,D97+1) -> -5.3053487e-05 | J97: =INDEX(Panel!$V$5:$V$815,D97+1) -> 0.0025090561 | K97: =(E97-G97-H97*F97-I97*D97)/J97 -> 2.5655058 | L97: 2.5 | M97: =IF(ABS(K97)>L97,"Yes","No") -> Yes | N97: 2026-04-29 09:30 | O97: 741 | P97: 24229.2 | Q97: 272.86 | R97: 2026-05-26 15:15 | S97: 759 | T97: 23911.2 | U97: 271.07 | V97: expiry | W97: =B97*((LN(T97)-LN(P97))-(LN(U97)-LN(Q97))) -> 0.0066297959 | X97: =IF(INDEX(Panel!$A$5:$A$815,O97+1)<=DATE(2024,9,30),0.000625,IF(INDEX(Panel!$A$5:$A$815,O97+1)<=DATE(2026,3,31),0.001,0.0015))*(0.3989*Inputs!$B$28*SQRT(MAX(INDEX(Panel!$G$5:$G$815,O97+1),0)/365))+2*Inputs!$B$30+Inputs!$B$25+0.00003*(0.3989*Inputs!$B$28*SQRT(MAX(INDEX(Panel!$G$5:$G$815,O97+1),0)/365))+IF(B97<0,(Inputs!$B$20+Inputs!$B$26+Inputs!$B$27),(Inputs!$B$21+Inputs!$B$26+Inputs!$B$27)) -> 0.00033023908 | Y97: =IF(V97="expiry",IF(INDEX(Panel!$A$5:$A$815,S97+1)<=DATE(2026,3,31),0.00125,0.0015)*IF(B97<0,MAX(P97-T97,0),MAX(T97-P97,0))/T97,IF(INDEX(Panel!$A$5:$A$815,S97+1)<=DATE(2024,9,30),0.000625,IF(INDEX(Panel!$A$5:$A$815,S97+1)<=DATE(2026,3,31),0.001,0.0015))*(0.3989*Inputs!$B$28*SQRT(MAX(INDEX(Panel!$G$5:$G$815,S97+1),0)/365))+2*Inputs!$B$30+Inputs!$B$25)+IF(B97<0,(Inputs!$B$21+Inputs!$B$26+Inputs!$B$27),(Inputs!$B$20+Inputs!$B$26+Inputs!$B$27)) -> 0.00013494881 | Z97: =B97*SUMPRODUCT((Panel!$F$5:$F$815>=O97)*(Panel!$F$5:$F$815<S97)*(Panel!$N$5:$N$815+Inputs!$B$14)*Panel!$BD$5:$BD$815)/365 -> -0.0044383562 | AA97: =W97-X97-Y97+Z97 -> 0.0017262519 | AB97: 0.0017262519 | AC97: =AA97-AB97 -> 9.8879238e-17
A100: Summary
A101: Who | B101: Trades | C101: Σ net | D101: ₹ a year | E101: Capital | F101: Return above risk-free
A102: signal | B102: =COUNTIF($A$5:$A$97,A102) -> 29 | C102: =SUMIF($A$5:$A$97,A102,$AA$5:$AA$97) -> 0.068673898 | D102: =C102/'8 Four people'!$B$5*'8 Four people'!$B$4 -> 34198.108 | E102: =1*'8 Four people'!$B$4 -> 1602620.5 | F102: =D102/E102 -> 0.021338868
A103: aarav | B103: =COUNTIF($A$5:$A$97,A103) -> 26 | C103: =SUMIF($A$5:$A$97,A103,$AA$5:$AA$97) -> 0.062622874 | D103: =C103/'8 Four people'!$B$5*'8 Four people'!$B$4 -> 31184.829 | E103: =(1+Inputs!$B$12)*'8 Four people'!$B$4 -> 1810961.2 | F103: =D103/E103 -> 0.017220043
A104: meera | B104: =COUNTIF($A$5:$A$97,A104) -> 12 | C104: =SUMIF($A$5:$A$97,A104,$AA$5:$AA$97) -> -0.011731957 | D104: =C104/'8 Four people'!$B$5*'8 Four people'!$B$4 -> -5842.2594 | E104: =(0.25+Inputs!$B$12)*'8 Four people'!$B$4 -> 608995.79 | F104: =D104/E104 -> -0.0095932673
A105: rohan | B105: =COUNTIF($A$5:$A$97,A105) -> 11 | C105: =SUMIF($A$5:$A$97,A105,$AA$5:$AA$97) -> 0.10551026 | D105: =C105/'8 Four people'!$B$5*'8 Four people'!$B$4 -> 52541.816 | E105: =(0.5*Inputs!$B$12)*'8 Four people'!$B$4 -> 104170.33 | F105: =D105/E105 -> 0.50438368
A106: kavya | B106: =COUNTIF($A$5:$A$97,A106) -> 15 | C106: =SUMIF($A$5:$A$97,A106,$AA$5:$AA$97) -> 0.062105483 | D106: =C106/'8 Four people'!$B$5*'8 Four people'!$B$4 -> 30927.18 | E106: =(Inputs!$B$12*(1-Inputs!$B$15))*'8 Four people'!$B$4 -> 62502.2 | F106: =D106/E106 -> 0.49481747

Sheet 10 Course tests
A1: Course-outline tests on the 29 signal trades (sessions 7–12)
A2: Computed from sheet 9, rows of the base signal: entry 2σ, hold to expiry, both directions, retail costs.
A4: Trades n | B4: =COUNT('9 Trades 15-min'!$AA$5:$AA$33) -> 29
A5: Mean net per trade (bp) | B5: =AVERAGE('9 Trades 15-min'!$AA$5:$AA$33)*10000 -> 23.680654
A6: Standard deviation (bp) | B6: =STDEV('9 Trades 15-min'!$AA$5:$AA$33)*10000 -> 41.702892
A7: One-sample t (H0: mean = 0) | B7: =B5/(B6/SQRT(B4)) -> 3.0579229 | C7: Python: 3.06
A8: p-value, two-sided | B8: =TDIST(ABS(B7),B4-1,2) -> 0.0048650021 | C8: Python: 0.0049
A9: 95% CI, lower (bp) | B9: =B5-TINV(0.05,B4-1)*B6/SQRT(B4) -> 7.8177227
A10: 95% CI, upper (bp) | B10: =B5+TINV(0.05,B4-1)*B6/SQRT(B4) -> 39.543586
A11: Winning trades | B11: =COUNTIF('9 Trades 15-min'!$AA$5:$AA$33,">0") -> 22
A12: Proportion test z (H0: win rate = 50%) | B12: =(B11/B4-0.5)/SQRT(0.25/B4) -> 2.7854301 | C12: Python: 3.25
A13: p-value, one-sided | B13: =1-NORMSDIST(B12) -> 0.0026728384
A14: Trades in the first half | B14: =COUNTIF('9 Trades 15-min'!$O$5:$O$33,"<405") -> 15
A15: Welch two-sample t-test p (1st vs 2nd half) | B15: =TTEST(OFFSET('9 Trades 15-min'!$AA$5,0,0,B14,1),OFFSET('9 Trades 15-min'!$AA$5,B14,0,B4-B14,1),2,3) -> 0.66301579 | C15: Python: 0.663
A16: F-test for equal variances p | B16: =FTEST(OFFSET('9 Trades 15-min'!$AA$5,0,0,B14,1),OFFSET('9 Trades 15-min'!$AA$5,B14,0,B4-B14,1)) -> 0.40739081 | C16: Python: 0.4074
A18: Chi-square: direction × outcome (Yates-corrected, as in Python)
B19: Loss | C19: Win
A20: buy futures, sell ETF | B20: =COUNTIFS('9 Trades 15-min'!$B$5:$B$33,">0",'9 Trades 15-min'!$AA$5:$AA$33,"<=0") -> 4 | C20: =COUNTIFS('9 Trades 15-min'!$B$5:$B$33,">0",'9 Trades 15-min'!$AA$5:$AA$33,">0") -> 4
A21: sell futures, buy ETF | B21: =COUNTIFS('9 Trades 15-min'!$B$5:$B$33,"<0",'9 Trades 15-min'!$AA$5:$AA$33,"<=0") -> 3 | C21: =COUNTIFS('9 Trades 15-min'!$B$5:$B$33,"<0",'9 Trades 15-min'!$AA$5:$AA$33,">0") -> 18
A23: χ² (Yates) | B23: =((ABS(B20-SUM(B20:C20)*SUM(B20:B21)/SUM(B20:C21))-0.5)^2/(SUM(B20:C20)*SUM(B20:B21)/SUM(B20:C21))+(ABS(C20-SUM(B20:C20)*SUM(C20:C21)/SUM(B20:C21))-0.5)^2/(SUM(B20:C20)*SUM(C20:C21)/SUM(B20:C21))+(ABS(B21-SUM(B21:C21)*SUM(B20:B21)/SUM(B20:C21))-0.5)^2/(SUM(B21:C21)*SUM(B20:B21)/SUM(B20:C21))+(ABS(C21-SUM(B21:C21)*SUM(C20:C21)/SUM(B20:C21))-0.5)^2/(SUM(B21:C21)*SUM(C20:C21)/SUM(B20:C21))) -> 2.3205492 | C23: Python: 2.321
A24: p-value | B24: =CHIDIST(B23,1) -> 0.12767494 | C24: Python: 0.1277
A26: Wilcoxon signed-rank, ANOVA, regression diagnostics and the classifiers are in the notebook (Python/Jamovi); plain Excel has no built-in functions for them.
